Workbook

Sheet Ctrl
B3: Project Eagle
B4: Model Control | G4: Runway | H4: Fundraise | I4: Fund. Date | J4: End. ARR | K4: Deferred Rev.
B5: ="CASE "&$H$11&": "&H12 -> CASE 1: BASE CASE | G5: =Sum!$E$19 -> 16 | H5: =Sum!$E$28 -> 3259.9201 | I5: =Sum!$E$21 -> 45626 | J5: ='Calc.Mth'!$AI$57 -> 2999.7355 | K5: =Fin.Mth!$AI$81 -> 1487.7626
I10: KEY SCENARIOS | P10: SENSITIVITIES
H11: 1 | I11: 1 | J11: =I11+1 -> 2 | K11: =J11+1 -> 3 | L11: =K11+1 -> 4 | M11: =L11+1 -> 5 | N11: =M11+1 -> 6 | O11: =N11+1 -> 7 | P11: =O11+1 -> 8 | Q11: =P11+1 -> 9 | ... W11: =V11+1 -> 15
B12: SCENARIO SELECTOR>> | H12: =OFFSET(H12,,H11) -> BASE CASE | I12: BASE CASE | J12: DISC. CASE | K12: LOWER CHURN (MTHLY) | L12: LOWER CHURN (ANN) | M12: PRICE ESCALATION | N12: UPSELL | O12: LOWER CHURN + UPSELL | P12: +10% LAUNCH VOLUME | Q12: -10% LAUNCH VOLUME | R12: -10% CHURN | S12: +10% CHURN | T12: +10% MoM GROWTH | U12: -10% MoM GROWTH | V12: +10% PRICING | W12: -10% PRICING
N14: 1
A15: X | B15: OUTPUTS
B17: Fundraising Size | F17: $K | H17: =H5 -> 3259.9201 | I17: 3259.9201 | J17: 4893.9226 | K17: 3516.2757 | L17: 3555.9476 | M17: 3168.3163 | N17: 3167.8482 | O17: 3258.6784 | P17: 3225.5844 | Q17: 3134.2058 | R17: 3555.9476 | S17: 3199.723 | T17: 3330.8753 | U17: 3254.7806 | V17: 2858.7619 | W17: 3763.2283
B18: Fundraising Date | F18: date | H18: =Sum!E21 -> 45626 | I18: 45626 | J18: 45504 | K18: 45626 | L18: 45626 | M18: 45626 | N18: 45657 | O18: 45626 | P18: 45626 | Q18: 45657 | R18: 45626 | S18: 45657 | T18: 45626 | U18: 45626 | V18: 45688 | W18: 45596
B19: Runway | F19: months | H19: =G5 -> 16 | I19: 16 | J19: 12 | K19: 16 | L19: 16 | M19: 16 | N19: 17 | O19: 16 | P19: 16 | Q19: 17 | R19: 16 | S19: 17 | T19: 16 | U19: 16 | V19: 18 | W19: 15
B20: Ending ARR | F20: $K | H20: =J5 -> 2999.7355 | I20: 2999.7355 | J20: 3568.1302 | K20: 3459.7404 | L20: 3647.4052 | M20: 3101.0088 | N20: 3762.9422 | O20: 4262.16 | P20: 3299.7091 | Q20: 2699.762 | R20: 3647.4052 | S20: 2770.2446 | T20: 3673.9487 | U20: 2423.4551 | V20: 3299.7091 | W20: 2699.762
A22: X | B22: FUNDRAISING ASSUMPTIONS
B24: Minimum Cash | F24: $K | H24: =OFFSET(H24,,H$11) -> 1500 | I24: 1500 | J24: =$I24 -> 1500 | K24: =$I24 -> 1500 | L24: =$I24 -> 1500 | M24: =$I24 -> 1500 | N24: =$I24 -> 1500 | O24: =$I24 -> 1500 | P24: =$I24 -> 1500 | Q24: =$I24 -> 1500 | ... W24: =$I24 -> 1500
B25: Runway Trigger Prior to Fundraise | F25: months | H25: =OFFSET(H25,,H$11) -> 6 | I25: 6 | J25: =$I25 -> 6 | K25: =$I25 -> 6 | L25: =$I25 -> 6 | M25: =$I25 -> 6 | N25: =$I25 -> 6 | O25: =$I25 -> 6 | P25: =$I25 -> 6 | Q25: =$I25 -> 6 | ... W25: =$I25 -> 6
B26: Growth Runway Post-Fundraise | F26: months | H26: =OFFSET(H26,,H$11) -> 0 | I26: 0 | J26: =$I26 -> 0 | K26: =$I26 -> 0 | L26: =$I26 -> 0 | M26: =$I26 -> 0 | N26: =$I26 -> 0 | O26: =$I26 -> 0 | P26: =$I26 -> 0 | Q26: =$I26 -> 0 | ... W26: =$I26 -> 0
A28: X | B28: VOLUME & PRICING ASSUMPTIONS
B30: Launch Profile
B31: Gross Adds Post-Launch Period | F31: # | H31: =OFFSET(H31,,H$11) -> 9830 | I31: 9830 | J31: =$I31 -> 9830 | K31: =$I31 -> 9830 | L31: =$I31 -> 9830 | M31: =$I31 -> 9830 | N31: =$I31 -> 9830 | O31: =$I31 -> 9830 | P31: =$I31*(1+0.1) -> 10813 | Q31: =$I31*(1-0.1) -> 8847 | R31: =$I31 -> 9830 | S31: =$I31 -> 9830 | T31: =$I31 -> 9830 | U31: =$I31 -> 9830 | V31: =$I31 -> 9830 | W31: =$I31 -> 9830 | X31: << required # of customers post-launch to reach $3m ARR
B33: Ramp-up Profile
B34: Month 1 | F34: % | H34: =OFFSET(H34,,H$11) -> 0.5 | I34: 0.5 | J34: =$I34 -> 0.5 | K34: =$I34 -> 0.5 | L34: =$I34 -> 0.5 | M34: =$I34 -> 0.5 | N34: =$I34 -> 0.5 | O34: =$I34 -> 0.5 | P34: =$I34 -> 0.5 | Q34: =$I34 -> 0.5 | ... W34: =$I34 -> 0.5
B35: Month 2 | F35: % | H35: =OFFSET(H35,,H$11) -> 0.3 | I35: 0.3 | J35: =$I35 -> 0.3 | K35: =$I35 -> 0.3 | L35: =$I35 -> 0.3 | M35: =$I35 -> 0.3 | N35: =$I35 -> 0.3 | O35: =$I35 -> 0.3 | P35: =$I35 -> 0.3 | Q35: =$I35 -> 0.3 | ... W35: =$I35 -> 0.3
B36: Month 3 | F36: % | H36: =OFFSET(H36,,H$11) -> 0.2 | I36: 0.2 | J36: =$I36 -> 0.2 | K36: =$I36 -> 0.2 | L36: =$I36 -> 0.2 | M36: =$I36 -> 0.2 | N36: =$I36 -> 0.2 | O36: =$I36 -> 0.2 | P36: =$I36 -> 0.2 | Q36: =$I36 -> 0.2 | ... W36: =$I36 -> 0.2
B38: MoM Growth (%)
B39: Monthly Plan | F39: % | H39: =OFFSET(H39,,H$11) -> 0.1 | I39: 0.1 | J39: =I39*(1+0.2) -> 0.12 | K39: =$I39 -> 0.1 | L39: =$I39 -> 0.1 | M39: =$I39 -> 0.1 | N39: =$I39 -> 0.1 | O39: =$I39 -> 0.1 | P39: =$I39 -> 0.1 | Q39: =$I39 -> 0.1 | R39: =$I39 -> 0.1 | S39: =$I39 -> 0.1 | T39: =$I39*(1+0.1) -> 0.11 | U39: =$I39*(1-0.1) -> 0.09 | V39: =$I39 -> 0.1 | W39: =$I39 -> 0.1
B40: Annual Plan | F40: % | H40: =OFFSET(H40,,H$11) -> 0.07 | I40: 0.07 | J40: =I40*(1+0.2) -> 0.084 | K40: =$I40 -> 0.07 | L40: =$I40 -> 0.07 | M40: =$I40 -> 0.07 | N40: =I40*(1+0.1) -> 0.077 | O40: =N40 -> 0.077 | P40: =$I40 -> 0.07 | Q40: =$I40 -> 0.07 | R40: =$I40 -> 0.07 | S40: =$I40 -> 0.07 | T40: =$I40*(1+0.1) -> 0.077 | U40: =$I40*(1-0.1) -> 0.063 | V40: =$I40 -> 0.07 | W40: =$I40 -> 0.07
B42: Churn (%)
B43: =$B$39 -> Monthly Plan | F43: % | H43: =OFFSET(H43,,H$11) -> 0.25 | I43: 0.25 | J43: =$I43 -> 0.25 | K43: 0.15 | L43: 0.15 | M43: =$I43 -> 0.25 | N43: =I43*(1+0.1) -> 0.275 | O43: =N43-10% -> 0.175 | P43: =$I43 -> 0.25 | Q43: =$I43 -> 0.25 | R43: =$I43-10% -> 0.15 | S43: =$I43+10% -> 0.35 | T43: =$I43 -> 0.25 | U43: =$I43 -> 0.25 | V43: =$I43 -> 0.25 | W43: =$I43 -> 0.25
B44: =$B$40 -> Annual Plan | F44: % | H44: =OFFSET(H44,,H$11) -> 0.35 | I44: 0.35 | J44: =$I44 -> 0.35 | K44: 0.35 | L44: 0.25 | M44: =$I44 -> 0.35 | N44: 0.35 | O44: =N44-10% -> 0.25 | P44: =$I44 -> 0.35 | Q44: =$I44 -> 0.35 | R44: =$I44-10% -> 0.25 | S44: =$I44+10% -> 0.45 | T44: =$I44 -> 0.35 | U44: =$I44 -> 0.35 | V44: =$I44 -> 0.35 | W44: =$I44 -> 0.35
B46: Pricing
B47: =$B$39 -> Monthly Plan | F47: $ | H47: =OFFSET(H47,,H$11) -> 30 | I47: 30 | J47: =I47*(1-0.2) -> 24 | K47: =$I47 -> 30 | L47: =$I47 -> 30 | M47: =$I47 -> 30 | N47: =$I47 -> 30 | O47: =$I47 -> 30 | P47: =$I47 -> 30 | Q47: =$I47 -> 30 | R47: =$I47 -> 30 | ... U47: =$I47 -> 30 | V47: =$I47*(1+0.1) -> 33 | W47: =$I47*(1-0.1) -> 27
B48: =$B$40 -> Annual Plan | F48: $ | H48: =OFFSET(H48,,H$11) -> 330 | I48: 330 | J48: =I48*(1-0.2) -> 264 | K48: =$I48 -> 330 | L48: =$I48 -> 330 | M48: =$I48 -> 330 | N48: =$I48 -> 330 | O48: =$I48 -> 330 | P48: =$I48 -> 330 | Q48: =$I48 -> 330 | R48: =$I48 -> 330 | ... U48: =$I48 -> 330 | V48: =$I48*(1+0.1) -> 363 | W48: =$I48*(1-0.1) -> 297
B50: % growth YoY
B51: =$B$39 -> Monthly Plan | F51: % | H51: =OFFSET(H51,,H$11) -> 0 | I51: 0 | J51: =$I51 -> 0 | K51: =$I51 -> 0 | L51: =$I51 -> 0 | M51: 0.03 | N51: 0.03 | O51: =N51 -> 0.03 | P51: =$I51 -> 0 | Q51: =$I51 -> 0 | R51: =$I51 -> 0 | S51: =$I51 -> 0 | T51: =$I51 -> 0 | U51: =$I51 -> 0 | V51: =$I51 -> 0 | W51: =$I51 -> 0
B52: =$B$40 -> Annual Plan | F52: % | H52: =OFFSET(H52,,H$11) -> 0 | I52: 0 | J52: =$I52 -> 0 | K52: =$I52 -> 0 | L52: =$I52 -> 0 | M52: 0.03 | N52: 0.03 | O52: =N52 -> 0.03 | P52: =$I52 -> 0 | Q52: =$I52 -> 0 | R52: =$I52 -> 0 | S52: =$I52 -> 0 | T52: =$I52 -> 0 | U52: =$I52 -> 0 | V52: =$I52 -> 0 | W52: =$I52 -> 0
A54: X | B54: MILESTONE ASSUMPTIONS
B56: ARR Milestone | F56: # | H56: =OFFSET(H56,,H$11) -> 750 | I56: 750 | J56: =$I56 -> 750 | K56: =$I56 -> 750 | L56: =$I56 -> 750 | M56: =$I56 -> 750 | N56: =$I56 -> 750 | O56: =$I56 -> 750 | P56: =$I56 -> 750 | Q56: =$I56 -> 750 | ... W56: =$I56 -> 750
B57: Customer Milestone | F57: # | H57: =OFFSET(H57,,H$11) -> 2500 | I57: 2500 | J57: =$I57 -> 2500 | K57: =$I57 -> 2500 | L57: =$I57 -> 2500 | M57: =$I57 -> 2500 | N57: =$I57 -> 2500 | O57: =$I57 -> 2500 | P57: =$I57 -> 2500 | Q57: =$I57 -> 2500 | ... W57: =$I57 -> 2500
B58: Headcount Milestone | F58: # | H58: =OFFSET(H58,,H$11) -> 20 | I58: 20 | J58: =$I58 -> 20 | K58: =$I58 -> 20 | L58: =$I58 -> 20 | M58: =$I58 -> 20 | N58: =$I58 -> 20 | O58: =$I58 -> 20 | P58: =$I58 -> 20 | Q58: =$I58 -> 20 | ... W58: =$I58 -> 20
A60: X | B60: HEADCOUNT ASSUMPTIONS
B62: Fringe Costs % of Base Salary | F62: % | H62: =OFFSET(H62,,H$11) -> 0.15 | I62: 0.15 | J62: =$I62 -> 0.15 | K62: =$I62 -> 0.15 | L62: =$I62 -> 0.15 | M62: =$I62 -> 0.15 | N62: =$I62 -> 0.15 | O62: =$I62 -> 0.15 | P62: =$I62 -> 0.15 | Q62: =$I62 -> 0.15 | ... W62: =$I62 -> 0.15
B63: YoY Salary Increase | F63: % | H63: =OFFSET(H63,,H$11) -> 0.08 | I63: 0.08 | J63: =$I63 -> 0.08 | K63: =$I63 -> 0.08 | L63: =$I63 -> 0.08 | M63: =$I63 -> 0.08 | N63: =$I63 -> 0.08 | O63: =$I63 -> 0.08 | P63: =$I63 -> 0.08 | Q63: =$I63 -> 0.08 | ... W63: =$I63 -> 0.08
B65: SALARIES
B66: Core Executive | F66: $K | H66: =OFFSET(H66,,H$11) -> 120 | I66: 120 | J66: =$I66 -> 120 | K66: =$I66 -> 120 | L66: =$I66 -> 120 | M66: =$I66 -> 120 | N66: =$I66 -> 120 | O66: =$I66 -> 120 | P66: =$I66 -> 120 | Q66: =$I66 -> 120 | ... W66: =$I66 -> 120
B67: New Executive | F67: $K | H67: =OFFSET(H67,,H$11) -> 150 | I67: 150 | J67: =$I67 -> 150 | K67: =$I67 -> 150 | L67: =$I67 -> 150 | M67: =$I67 -> 150 | N67: =$I67 -> 150 | O67: =$I67 -> 150 | P67: =$I67 -> 150 | Q67: =$I67 -> 150 | ... W67: =$I67 -> 150
B68: Engineers | F68: $K | H68: =OFFSET(H68,,H$11) -> 180 | I68: 180 | J68: =$I68 -> 180 | K68: =$I68 -> 180 | L68: =$I68 -> 180 | M68: =$I68 -> 180 | N68: =$I68 -> 180 | O68: =$I68 -> 180 | P68: =$I68 -> 180 | Q68: =$I68 -> 180 | ... W68: =$I68 -> 180
B69: Customer Support Representative | F69: $K | H69: =OFFSET(H69,,H$11) -> 120 | I69: 120 | J69: =$I69 -> 120 | K69: =$I69 -> 120 | L69: =$I69 -> 120 | M69: =$I69 -> 120 | N69: =$I69 -> 120 | O69: =$I69 -> 120 | P69: =$I69 -> 120 | Q69: =$I69 -> 120 | ... W69: =$I69 -> 120
A71: X | B71: COST ASSUMPTIONS
B73: G&A Annual Growth | F73: % | H73: =OFFSET(H73,,H$11) -> 0.07 | I73: 0.07 | J73: =$I73 -> 0.07 | K73: =$I73 -> 0.07 | L73: =$I73 -> 0.07 | M73: =$I73 -> 0.07 | N73: =$I73 -> 0.07 | O73: =$I73 -> 0.07 | P73: =$I73 -> 0.07 | Q73: =$I73 -> 0.07 | ... W73: =$I73 -> 0.07
B74: S&M / Customer | F74: $ | H74: =OFFSET(H74,,H$11) -> 200 | I74: 200 | J74: =$I74 -> 200 | K74: =$I74 -> 200 | L74: =$I74 -> 200 | M74: =$I74 -> 200 | N74: =$I74 -> 200 | O74: =$I74 -> 200 | P74: =$I74 -> 200 | Q74: =$I74 -> 200 | ... W74: =$I74 -> 200
A76: X | B76: END OF SHEET

Sheet Sum
B3: Project Eagle
B4: Model Summary | G4: Runway | H4: Fundraise | I4: Fund. Date | J4: End. ARR | K4: Deferred Rev.
B5: =Ctrl!$B$5 -> CASE 1: BASE CASE | G5: =Sum!$E$19 -> 16 | H5: =Sum!$E$28 -> 3259.9201 | I5: =Sum!$E$21 -> 45626 | J5: ='Calc.Mth'!$AI$57 -> 2999.7355 | K5: =Fin.Mth!$AI$81 -> 1487.7626
A10: 1 | B10: DASHBOARD | W10: 2 | X10: CHARTS
K12: Quarterly | T12: Annual | X12: Customers (Monthly vs. Annual) & Pricing | AE12: Bookings, Revenue and ARR | AL12: Upsell | AN12: Base | AO12: Inc | AP12: End | AQ12: ARR
G13: $K, Dec Y/E | K13: =Fin.Qtr!L7 -> 45382 | L13: =Fin.Qtr!M7 -> 45473 | M13: =Fin.Qtr!N7 -> 45565 | N13: =Fin.Qtr!O7 -> 45657 | O13: =Fin.Qtr!P7 -> 45747 | P13: =Fin.Qtr!Q7 -> 45838 | Q13: =Fin.Qtr!R7 -> 45930 | R13: =Fin.Qtr!S7 -> 46022 | T13: =Fin.Qtr!U7 -> 45657 | U13: =Fin.Qtr!V7 -> 46022 | AL13: Base Case ARR | AP13: =AQ13 -> 2999.7355 | AQ13: 2999.7355
B14: FUNDRAISING SUMMARY | G14: OPERATING METRICS | AL14: Add: ARR from Price Escalation | AN14: =AP13 -> 2999.7355 | AO14: =AQ14-AP13 -> 101.27332 | AQ14: =Ctrl!M20 -> 3101.0088
B15: Model Date | E15: 45292 | G15: =Fin.Qtr!B17 -> # CUSTOMERS | AL15: Add: ARR from Upsell from Monthly to Annual | AN15: =AQ14 -> 3101.0088 | AO15: =AQ15-AN15 -> 661.93336 | AQ15: =Ctrl!N20 -> 3762.9422
G16: =Fin.Qtr!B18 -> Monthly Plan | K16: =Fin.Qtr!L18 -> 3471.2188 | L16: =Fin.Qtr!M18 -> 2131.7622 | M16: =Fin.Qtr!N18 -> 1309.1685 | N16: =Fin.Qtr!O18 -> 803.99309 | O16: =Fin.Qtr!P18 -> 493.75225 | P16: =Fin.Qtr!Q18 -> 303.2256 | Q16: =Fin.Qtr!R18 -> 186.21842 | R16: =Fin.Qtr!S18 -> 114.36139 | T16: =Fin.Qtr!U18 -> 1929.0356 | U16: =Fin.Qtr!V18 -> 274.38942 | AL16: Revised ARR | AP16: =AQ15 -> 3762.9422
B17: Founders' Equity | E17: =Fin.Mth!K68 -> 3000 | G17: =Fin.Qtr!B19 -> Annual Plan | K17: =Fin.Qtr!L19 -> 4915 | L17: =Fin.Qtr!M19 -> 6021.0863 | M17: =Fin.Qtr!N19 -> 7376.0897 | N17: =Fin.Qtr!O19 -> 9036.027 | O17: =Fin.Qtr!P19 -> 9188.5143 | P17: =Fin.Qtr!Q19 -> 10842.727 | Q17: =Fin.Qtr!R19 -> 12776.132 | R17: =Fin.Qtr!S19 -> 15030.612 | T17: =Fin.Qtr!U19 -> 6837.0508 | U17: =Fin.Qtr!V19 -> 11959.496
G18: =Fin.Qtr!B20 -> TOTAL | K18: =Fin.Qtr!L20 -> 8386.2188 | L18: =Fin.Qtr!M20 -> 8152.8486 | M18: =Fin.Qtr!N20 -> 8685.2581 | N18: =Fin.Qtr!O20 -> 9840.0201 | O18: =Fin.Qtr!P20 -> 9682.2666 | P18: =Fin.Qtr!Q20 -> 11145.953 | Q18: =Fin.Qtr!R20 -> 12962.35 | R18: =Fin.Qtr!S20 -> 15144.973 | T18: =Fin.Qtr!U20 -> 8766.0864 | U18: =Fin.Qtr!V20 -> 12233.886
B19: Runway (months) | E19: =Fin.Mth!K69 -> 16 | G19: =Fin.Qtr!B22 -> PRICING
B20: Buffer | E20: =Ctrl!H25 -> 6 | G20: =Fin.Qtr!B23 -> Monthly | K20: =Fin.Qtr!L23 -> 30 | L20: =Fin.Qtr!M23 -> 30 | M20: =Fin.Qtr!N23 -> 30 | N20: =Fin.Qtr!O23 -> 30 | O20: =Fin.Qtr!P23 -> 30 | P20: =Fin.Qtr!Q23 -> 30 | Q20: =Fin.Qtr!R23 -> 30 | R20: =Fin.Qtr!S23 -> 30 | T20: =Fin.Qtr!U23 -> 30 | U20: =Fin.Qtr!V23 -> 30
B21: Date of Fundraise | E21: =EOMONTH(E15,E19-E20) -> 45626 | G21: =Fin.Qtr!B24 -> Annual | K21: =Fin.Qtr!L24 -> 330 | L21: =Fin.Qtr!M24 -> 330 | M21: =Fin.Qtr!N24 -> 330 | N21: =Fin.Qtr!O24 -> 330 | O21: =Fin.Qtr!P24 -> 330 | P21: =Fin.Qtr!Q24 -> 330 | Q21: =Fin.Qtr!R24 -> 330 | R21: =Fin.Qtr!S24 -> 330 | T21: =Fin.Qtr!U24 -> 330 | U21: =Fin.Qtr!V24 -> 330
B22: Months from Today | E22: =YEARFRAC(E15,E21)*12 -> 10.966667 | G22: BLENDED | K22: =Fin.Qtr!L25 -> 21.697049 | L22: =Fin.Qtr!M25 -> 28.473223 | M22: =Fin.Qtr!N25 -> 27.714799 | N22: =Fin.Qtr!O25 -> 27.217225 | O22: =Fin.Qtr!P25 -> 22.245689 | P22: =Fin.Qtr!Q25 -> 17.802969 | Q22: =Fin.Qtr!R25 -> 17.198682 | R22: =Fin.Qtr!S25 -> 16.673421 | T22: =Fin.Qtr!U25 -> 26.275574 | U22: =Fin.Qtr!V25 -> 18.48019
G23: REVENUE METRICS
B24: Fundraising Calculations | G24: =Fin.Qtr!B28 -> Bookings | K24: =Fin.Qtr!L28 -> 1685.077 | L24: =Fin.Qtr!M28 -> 710.00898 | M24: =Fin.Qtr!N28 -> 584.70451 | N24: =Fin.Qtr!O28 -> 623.31876 | O24: =Fin.Qtr!P28 -> 670.03803 | P24: =Fin.Qtr!Q28 -> 693.26005 | Q24: =Fin.Qtr!R28 -> 794.96787 | R24: =Fin.Qtr!S28 -> 924.24868 | T24: =Fin.Qtr!U28 -> 900.77732 | U24: =Fin.Qtr!V28 -> 770.62866
B25: Cash Requirement by Dec-25 | E25: =-(Fin.Mth!K68+Fin.Mth!K66) -> 1759.9201 | G25: =Fin.Qtr!B29 -> Revenue | K25: =Fin.Qtr!L29 -> 468.61453 | L25: =Fin.Qtr!M29 -> 697.54207 | M25: =Fin.Qtr!N29 -> 703.13388 | N25: =Fin.Qtr!O29 -> 768.39983 | O25: =Fin.Qtr!P29 -> 637.06934 | P25: =Fin.Qtr!Q29 -> 567.61636 | Q25: =Fin.Qtr!R29 -> 635.97525 | R25: =Fin.Qtr!S29 -> 719.51004 | T25: =Fin.Qtr!U29 -> 659.42258 | U25: =Fin.Qtr!V29 -> 640.04275
B26: Add: Minimum Cash Balance | E26: =Ctrl!H24 -> 1500 | G26: =Fin.Qtr!B30 -> ARR | K26: =Fin.Qtr!L30 -> 2681.7469 | L26: =Fin.Qtr!M30 -> 2757.1137 | M26: =Fin.Qtr!N30 -> 2867.3752 | N26: =Fin.Qtr!O30 -> 3199.3266 | O26: =Fin.Qtr!P30 -> 2230.6737 | P26: =Fin.Qtr!Q30 -> 2351.8352 | Q26: =Fin.Qtr!R30 -> 2646.7928 | R26: =Fin.Qtr!S30 -> 2999.7355 | T26: =Fin.Qtr!U30 -> 2876.3906 | U26: =Fin.Qtr!V30 -> 2557.2593
B27: Add: Allowance for Growth | E27: =Ctrl!H26*(E17/E19) -> 0 | G27: SaaS METRICS
B28: Required Fundraise | E28: =SUM(E25:E27) -> 3259.9201 | G28: =Fin.Qtr!B33 -> CAC Payback (Monthly) | L28: =Fin.Qtr!M33 -> 7.9432271 | M28: =Fin.Qtr!N33 -> 7.8733974 | N28: =Fin.Qtr!O33 -> 7.8658393 | O28: =Fin.Qtr!P33 -> 7.6802094 | P28: =Fin.Qtr!Q33 -> 7.7217484 | Q28: =Fin.Qtr!R33 -> 7.7293888 | R28: =Fin.Qtr!S33 -> 7.7386804 | T28: =Fin.Qtr!U33 -> 7.8941546 | U28: =Fin.Qtr!V33 -> 7.7175067 | X28: Revenue by Monthly vs. Annual Plan | AE28: Cash Balance over Time | AL28: TORNADO CHART | AO28: Base Case ARR | AP28: =AQ13 -> 2999.7355
G29: =Fin.Qtr!B34 -> CAC Payback (Annual) | L29: =Fin.Qtr!M34 -> 0.72211156 | M29: =Fin.Qtr!N34 -> 0.7157634 | N29: =Fin.Qtr!O34 -> 0.7150763 | O29: =Fin.Qtr!P34 -> 0.69820085 | P29: =Fin.Qtr!Q34 -> 0.70197712 | Q29: =Fin.Qtr!R34 -> 0.70267171 | R29: =Fin.Qtr!S34 -> 0.7035164 | T29: =Fin.Qtr!U34 -> 0.71765042 | U29: =Fin.Qtr!V34 -> 0.70159152 | AL29: Scenario | AN29: Low | AO29: High | AP29: Low | AQ29: High
G30: =Fin.Qtr!B35 -> GDR (Monthly) | L30: =Fin.Qtr!M35 -> 0.75 | M30: =Fin.Qtr!N35 -> 0.75 | N30: =Fin.Qtr!O35 -> 0.75 | O30: =Fin.Qtr!P35 -> 0.75 | P30: =Fin.Qtr!Q35 -> 0.75 | Q30: =Fin.Qtr!R35 -> 0.75 | R30: =Fin.Qtr!S35 -> 0.75 | T30: =Fin.Qtr!U35 -> 0.75 | U30: =Fin.Qtr!V35 -> 0.75 | AL30: Launch Volumes | AN30: 9 | AO30: 8 | AP30: =SUMIF(Ctrl!$I$11:$W$11,AN30,Ctrl!$I$20:$W$20)-$AP$28 -> -299.97355 | AQ30: =SUMIF(Ctrl!$I$11:$W$11,AO30,Ctrl!$I$20:$W$20)-$AP$28 -> 299.97355
G31: =Fin.Qtr!B36 -> GDR (Annual) | L31: =Fin.Qtr!M36 -> 1 | M31: =Fin.Qtr!N36 -> 1 | N31: =Fin.Qtr!O36 -> 1 | O31: =Fin.Qtr!P36 -> 0.93586809 | P31: =Fin.Qtr!Q36 -> 0.98673092 | Q31: =Fin.Qtr!R36 -> 0.98621814 | R31: =Fin.Qtr!S36 -> 0.98566412 | T31: =Fin.Qtr!U36 -> 1 | U31: =Fin.Qtr!V36 -> 0.97362032 | AL31: Churn | AN31: 11 | AO31: 10 | AP31: =SUMIF(Ctrl!$I$11:$W$11,AN31,Ctrl!$I$20:$W$20)-$AP$28 -> -229.49098 | AQ31: =SUMIF(Ctrl!$I$11:$W$11,AO31,Ctrl!$I$20:$W$20)-$AP$28 -> 647.66967
AL32: MoM Growth | AN32: 13 | AO32: 12 | AP32: =SUMIF(Ctrl!$I$11:$W$11,AN32,Ctrl!$I$20:$W$20)-$AP$28 -> -576.28045 | AQ32: =SUMIF(Ctrl!$I$11:$W$11,AO32,Ctrl!$I$20:$W$20)-$AP$28 -> 674.21317
G33: Headcount | L33: =Fin.Qtr!M38 -> 10.333333 | M33: =Fin.Qtr!N38 -> 11.333333 | N33: =Fin.Qtr!O38 -> 13 | O33: =Fin.Qtr!P38 -> 13 | P33: =Fin.Qtr!Q38 -> 15 | Q33: =Fin.Qtr!R38 -> 16.666667 | R33: =Fin.Qtr!S38 -> 18.666667 | T33: =Fin.Qtr!U38 -> 10.5 | U33: =Fin.Qtr!V38 -> 15.833333 | AL33: Pricing | AN33: 15 | AO33: 14 | AP33: =SUMIF(Ctrl!$I$11:$W$11,AN33,Ctrl!$I$20:$W$20)-$AP$28 -> -299.97355 | AQ33: =SUMIF(Ctrl!$I$11:$W$11,AO33,Ctrl!$I$20:$W$20)-$AP$28 -> 299.97355
G34: Bookings / FTE | L34: =L24/L33 -> 68.710547 | M34: =M24/M33 -> 51.591574 | N34: =N24/N33 -> 47.947597 | O34: =O24/O33 -> 51.541387 | P34: =P24/P33 -> 46.217337 | Q34: =Q24/Q33 -> 47.698072 | R34: =R24/R33 -> 49.513322 | T34: =AVERAGE(L34:O34) -> 54.947776 | U34: =AVERAGE(O34:R34) -> 48.74253
G35: Bookings / Headcount Cost | L35: =-L24/L46 -> 1.7149975 | M35: =-M24/M46 -> 1.2554042 | N35: =-N24/N46 -> 1.1088713 | O35: =-O24/O46 -> 1.1180997 | P35: =-P24/P46 -> 1.0012204 | Q35: =-Q24/Q46 -> 1.0241132 | R35: =-R24/R46 -> 1.063088 | T35: =AVERAGE(L35:O35) -> 1.2993432 | U35: =AVERAGE(O35:R35) -> 1.0516303
G36: Bookings / S&M | L36: =-L24/L48 -> 1.7758594 | M36: =-M24/M48 -> 1.5359482 | N36: =-N24/N48 -> 1.560856 | O36: =-O24/O48 -> 1.6110057 | P36: =-P24/P48 -> 1.5985809 | Q36: =-Q24/Q48 -> 1.5991079 | R36: =-R24/R48 -> 1.6027271 | T36: =AVERAGE(L36:O36) -> 1.6209173 | U36: =AVERAGE(O36:R36) -> 1.6028554
G38: SUMMARY FINANCIALS
G39: Monthly Plan | K39: =Fin.Qtr!L42 -> 225.32203 | L39: =Fin.Qtr!M42 -> 247.79946 | M39: =Fin.Qtr!N42 -> 152.17984 | N39: =Fin.Qtr!O42 -> 93.457446 | O39: =Fin.Qtr!P42 -> 57.394554 | P39: =Fin.Qtr!Q42 -> 35.24743 | Q39: =Fin.Qtr!R42 -> 21.646328 | R39: =Fin.Qtr!S42 -> 13.293551 | T39: =Fin.Qtr!U42 -> 718.75878 | U39: =Fin.Qtr!V42 -> 127.58186
G40: Annual Plan | K40: =Fin.Qtr!L43 -> 243.2925 | L40: =Fin.Qtr!M43 -> 449.74261 | M40: =Fin.Qtr!N43 -> 550.95403 | N40: =Fin.Qtr!O43 -> 674.94238 | O40: =Fin.Qtr!P43 -> 579.67479 | P40: =Fin.Qtr!Q43 -> 532.36893 | Q40: =Fin.Qtr!R43 -> 614.32893 | R40: =Fin.Qtr!S43 -> 706.21648 | T40: =Fin.Qtr!U43 -> 1918.9315 | U40: =Fin.Qtr!V43 -> 2432.5891
G41: Total Revenue | K41: =Fin.Qtr!L44 -> 468.61453 | L41: =Fin.Qtr!M44 -> 697.54207 | M41: =Fin.Qtr!N44 -> 703.13388 | N41: =Fin.Qtr!O44 -> 768.39983 | O41: =Fin.Qtr!P44 -> 637.06934 | P41: =Fin.Qtr!Q44 -> 567.61636 | Q41: =Fin.Qtr!R44 -> 635.97525 | R41: =Fin.Qtr!S44 -> 719.51004 | T41: =Fin.Qtr!U44 -> 2637.6903 | U41: =Fin.Qtr!V44 -> 2560.171
G42: % growth | L42: =L41/K41-1 -> 0.48851993 | M42: =M41/L41-1 -> 0.0080164478 | N42: =N41/M41-1 -> 0.092821515 | O42: =O41/N41-1 -> -0.17091426 | P42: =P41/O41-1 -> -0.1090195 | Q42: =Q41/P41-1 -> 0.1204315 | R42: =R41/Q41-1 -> 0.13134911 | U42: =U41/T41-1 -> -0.029389088
G43: Gross Profit | K43: =Fin.Qtr!L46 -> 344.97771 | L43: =Fin.Qtr!M46 -> 585.43666 | M43: =Fin.Qtr!N46 -> 595.36963 | N43: =Fin.Qtr!O46 -> 651.2591 | O43: =Fin.Qtr!P46 -> 553.26127 | P43: =Fin.Qtr!Q46 -> 490.05692 | Q43: =Fin.Qtr!R46 -> 548.52869 | R43: =Fin.Qtr!S46 -> 619.83157 | T43: =Fin.Qtr!U46 -> 2177.0431 | U43: =Fin.Qtr!V46 -> 2211.6785
G44: % margin | K44: =K43/K41 -> 0.73616519 | L44: =L43/L41 -> 0.83928509 | M44: =M43/M41 -> 0.84673723 | N44: =N43/N41 -> 0.84755237 | O44: =O43/O41 -> 0.86844748 | P44: =P43/P41 -> 0.8633594 | Q44: =Q43/Q41 -> 0.86250006 | R44: =R43/R41 -> 0.86146341 | T44: =T43/T41 -> 0.82535963 | U44: =U43/U41 -> 0.86387919 | X44: Dollar Retention & Payback by Plan | AE44: Churn Reduction | AG44: Base | AH44: Inc | AI44: End | AJ44: ARR
AE45: Base Case ARR | AI45: =AJ45 -> 2999.7355 | AJ45: =Ctrl!I20 -> 2999.7355
G46: =Fin.Qtr!B48 -> Headcount Costs | K46: =Fin.Qtr!L48 -> -284.625 | L46: =Fin.Qtr!M48 -> -414 | M46: =Fin.Qtr!N48 -> -465.75 | N46: =Fin.Qtr!O48 -> -562.12 | O46: =Fin.Qtr!P48 -> -599.265 | P46: =Fin.Qtr!Q48 -> -692.415 | Q46: =Fin.Qtr!R48 -> -776.25 | R46: =Fin.Qtr!S48 -> -869.4 | T46: =Fin.Qtr!U48 -> -1726.495 | U46: =Fin.Qtr!V48 -> -2937.33 | AE46: Add: ARR from Monthly Churn Reduction | AG46: =AI45 -> 2999.7355 | AH46: =AJ46-AI45 -> 460.00491 | AJ46: =Ctrl!K20 -> 3459.7404
G47: =Fin.Qtr!B49 -> G&A | K47: =Fin.Qtr!L49 -> -61.4 | L47: =Fin.Qtr!M49 -> -65.698 | M47: =Fin.Qtr!N49 -> -70.29686 | N47: =Fin.Qtr!O49 -> -75.21764 | O47: =Fin.Qtr!P49 -> -80.482875 | P47: =Fin.Qtr!Q49 -> -86.116676 | Q47: =Fin.Qtr!R49 -> -92.144844 | R47: =Fin.Qtr!S49 -> -98.594983 | T47: =Fin.Qtr!U49 -> -272.6125 | U47: =Fin.Qtr!V49 -> -357.33938 | AE47: Add: ARR from Annual Churn Reduction | AG47: =AJ46 -> 3459.7404 | AH47: =AJ47-AG47 -> 187.66476 | AJ47: =Ctrl!L20 -> 3647.4052
G48: =Fin.Qtr!B50 -> S&M | K48: =Fin.Qtr!L50 -> -1966 | L48: =Fin.Qtr!M50 -> -399.81147 | M48: =Fin.Qtr!N50 -> -380.67983 | N48: =Fin.Qtr!O50 -> -399.34419 | O48: =Fin.Qtr!P50 -> -415.9129 | P48: =Fin.Qtr!Q50 -> -433.67216 | Q48: =Fin.Qtr!R50 -> -497.1321 | R48: =Fin.Qtr!S50 -> -576.67254 | T48: =Fin.Qtr!U50 -> -3145.8355 | U48: =Fin.Qtr!V50 -> -1923.3897 | AE48: Revised ARR | AI48: =AJ47 -> 3647.4052
G49: =Fin.Qtr!B51 -> Facilities Expense | K49: =Fin.Qtr!L51 -> -42 | L49: =Fin.Qtr!M51 -> -42 | M49: =Fin.Qtr!N51 -> -42 | N49: =Fin.Qtr!O51 -> -42 | O49: =Fin.Qtr!P51 -> -42 | P49: =Fin.Qtr!Q51 -> -42 | Q49: =Fin.Qtr!R51 -> -42 | R49: =Fin.Qtr!S51 -> -56 | T49: =Fin.Qtr!U51 -> -168 | U49: =Fin.Qtr!V51 -> -182
G50: =Fin.Qtr!B52 -> Miscellaneous | K50: =Fin.Qtr!L52 -> -23.430727 | L50: =Fin.Qtr!M52 -> -34.877103 | M50: =Fin.Qtr!N52 -> -35.156694 | N50: =Fin.Qtr!O52 -> -38.419991 | O50: =Fin.Qtr!P52 -> -31.853467 | P50: =Fin.Qtr!Q52 -> -28.380818 | Q50: =Fin.Qtr!R52 -> -31.798763 | R50: =Fin.Qtr!S52 -> -35.975502 | T50: =Fin.Qtr!U52 -> -131.88452 | U50: =Fin.Qtr!V52 -> -128.00855
G51: EBITDA | K51: =Fin.Qtr!L53 -> -2032.478 | L51: =Fin.Qtr!M53 -> -370.94992 | M51: =Fin.Qtr!N53 -> -398.51376 | N51: =Fin.Qtr!O53 -> -465.84272 | O51: =Fin.Qtr!P53 -> -616.25297 | P51: =Fin.Qtr!Q53 -> -792.52773 | Q51: =Fin.Qtr!R53 -> -890.79701 | R51: =Fin.Qtr!S53 -> -1016.8115 | T51: =Fin.Qtr!U53 -> -3267.7844 | U51: =Fin.Qtr!V53 -> -3316.3892
G53: Cash Accrual / (Burn) | K53: =Fin.Qtr!L66 -> -477.65009 | L53: =Fin.Qtr!M66 -> -354.48793 | M53: =Fin.Qtr!N66 -> -508.98632 | N53: =Fin.Qtr!O66 -> -576.76677 | O53: =Fin.Qtr!P66 -> -704.15206 | P53: =Fin.Qtr!Q66 -> -657.26964 | Q53: =Fin.Qtr!R66 -> -702.83171 | R53: =Fin.Qtr!S66 -> -777.77556 | T53: =Fin.Qtr!U66 -> -1917.8911 | U53: =Fin.Qtr!V66 -> -2842.029
G55: BALANCE SHEET AND OTHER KEY METRICS
G56: Cash | K56: =Fin.Qtr!L74 -> 2509.1941 | L56: =Fin.Qtr!M74 -> 2336.3746 | M56: =Fin.Qtr!N74 -> 1834.1073 | N56: =Fin.Qtr!O74 -> 3463.641 | O56: =Fin.Qtr!P74 -> 3871.1409 | P56: =Fin.Qtr!Q74 -> 3207.4491 | Q56: =Fin.Qtr!R74 -> 2522.0975 | R56: =Fin.Qtr!S74 -> 1773.8555 | T56: =Fin.Qtr!U74 -> 2535.8293 | U56: =Fin.Qtr!V74 -> 2843.6357
G57: Deferred Revenue | K57: =Fin.Qtr!L81 -> 840.26021 | L57: =Fin.Qtr!M81 -> 1262.6064 | M57: =Fin.Qtr!N81 -> 1151.7558 | N57: =Fin.Qtr!O81 -> 1015.959 | O57: =Fin.Qtr!P81 -> 968.61197 | P57: =Fin.Qtr!Q81 -> 1080.6422 | Q57: =Fin.Qtr!R81 -> 1227.0365 | R57: =Fin.Qtr!S81 -> 1415.7039 | T57: =Fin.Qtr!U81 -> 1067.6453 | U57: =Fin.Qtr!V81 -> 1172.9987
G58: Net Working Capital | K58: =SUM(Fin.Qtr!L75)-SUM(Fin.Qtr!L80:L82) -> -1078.7283 | L58: =SUM(Fin.Qtr!M75)-SUM(Fin.Qtr!M80:M82) -> -1612.8136 | M58: =SUM(Fin.Qtr!N75)-SUM(Fin.Qtr!N80:N82) -> -1499.0866 | N58: =SUM(Fin.Qtr!O75)-SUM(Fin.Qtr!O80:O82) -> -1389.3385 | O58: =SUM(Fin.Qtr!P75)-SUM(Fin.Qtr!P80:P82) -> -1273.3603 | P58: =SUM(Fin.Qtr!Q75)-SUM(Fin.Qtr!Q80:Q82) -> -1347.3832 | Q58: =SUM(Fin.Qtr!R75)-SUM(Fin.Qtr!R80:R82) -> -1520.8059 | R58: =SUM(Fin.Qtr!S75)-SUM(Fin.Qtr!S80:S82) -> -1742.3001 | T58: =SUM(Fin.Qtr!U75)-SUM(Fin.Qtr!U80:U82) -> -1394.9918 | U58: =SUM(Fin.Qtr!V75)-SUM(Fin.Qtr!V80:V82) -> -1470.9624
A60: X | B60: END OF SHEET

Sheet Calc>
B9: Project Eagle
B10: Operating Model
B11: Operating Calculations

Sheet Calc.Mth
B3: Project Eagle
B4: Calculations | Monthly | G4: Runway | H4: Fundraise | I4: Fund. Date | J4: End. ARR | K4: Deferred Rev.
B5: =Ctrl!$B$5 -> CASE 1: BASE CASE | G5: =Sum!$E$19 -> 16 | H5: =Sum!$E$28 -> 3259.9201 | I5: =Sum!$E$21 -> 45626 | J5: ='Calc.Mth'!$AI$57 -> 2999.7355 | K5: =Fin.Mth!$AI$81 -> 1487.7626
B7: Period End | L7: 45322 | M7: =EOMONTH(M8,0) -> 45351 | N7: =EOMONTH(N8,0) -> 45382 | O7: =EOMONTH(O8,0) -> 45412 | P7: =EOMONTH(P8,0) -> 45443 | Q7: =EOMONTH(Q8,0) -> 45473 | R7: =EOMONTH(R8,0) -> 45504 | S7: =EOMONTH(S8,0) -> 45535 | T7: =EOMONTH(T8,0) -> 45565 | ... AI7: =EOMONTH(AI8,0) -> 46022
B8: Period Start | L8: 45292 | M8: =L7+1 -> 45323 | N8: =M7+1 -> 45352 | O8: =N7+1 -> 45383 | P8: =O7+1 -> 45413 | Q8: =P7+1 -> 45444 | R8: =Q7+1 -> 45474 | S8: =R7+1 -> 45505 | T8: =S7+1 -> 45536 | ... AI8: =AH7+1 -> 45992
B9: Calendar Year | L9: =YEAR(L7) -> 2024 | M9: =YEAR(M7) -> 2024 | N9: =YEAR(N7) -> 2024 | O9: =YEAR(O7) -> 2024 | P9: =YEAR(P7) -> 2024 | Q9: =YEAR(Q7) -> 2024 | R9: =YEAR(R7) -> 2024 | S9: =YEAR(S7) -> 2024 | ... AI9: =YEAR(AI7) -> 2025
B10: Period Number | L10: 1 | M10: =L10+1 -> 2 | N10: =M10+1 -> 3 | O10: =N10+1 -> 4 | P10: =O10+1 -> 5 | Q10: =P10+1 -> 6 | R10: =Q10+1 -> 7 | S10: =R10+1 -> 8 | T10: =S10+1 -> 9 | ... AI10: =AH10+1 -> 24
B11: Days in Period | F11: Units | H11: Input I | I11: Input II | J11: Input III | K11: Total / Out | L11: =L7-L8+1 -> 31 | M11: =M7-M8+1 -> 29 | N11: =N7-N8+1 -> 31 | O11: =O7-O8+1 -> 30 | P11: =P7-P8+1 -> 31 | Q11: =Q7-Q8+1 -> 30 | R11: =R7-R8+1 -> 31 | S11: =S7-S8+1 -> 31 | ... AI11: =AI7-AI8+1 -> 31
A15: X | B15: TIMING & FLAGS
B17: January Point-to-Point | F17: # | H17: 12 | L17: =(MONTH(L7)=$H17)*1 -> 0 | M17: =(MONTH(M7)=$H17)*1 -> 0 | N17: =(MONTH(N7)=$H17)*1 -> 0 | O17: =(MONTH(O7)=$H17)*1 -> 0 | P17: =(MONTH(P7)=$H17)*1 -> 0 | Q17: =(MONTH(Q7)=$H17)*1 -> 0 | R17: =(MONTH(R7)=$H17)*1 -> 0 | S17: =(MONTH(S7)=$H17)*1 -> 0 | ... AI17: =(MONTH(AI7)=$H17)*1 -> 1
B18: Quarterly Point-to-Point | F18: # | L18: =(MOD(L10,3)=0)*1 -> 0 | M18: =(MOD(M10,3)=0)*1 -> 0 | N18: =(MOD(N10,3)=0)*1 -> 1 | O18: =(MOD(O10,3)=0)*1 -> 0 | P18: =(MOD(P10,3)=0)*1 -> 0 | Q18: =(MOD(Q10,3)=0)*1 -> 1 | R18: =(MOD(R10,3)=0)*1 -> 0 | S18: =(MOD(S10,3)=0)*1 -> 0 | ... AI18: =(MOD(AI10,3)=0)*1 -> 1
B19: Annual Plan - Rolling LTM Counter | F19: # | L19: =MIN(L10,$H17) -> 1 | M19: =MIN(M10,$H17) -> 2 | N19: =MIN(N10,$H17) -> 3 | O19: =MIN(O10,$H17) -> 4 | P19: =MIN(P10,$H17) -> 5 | Q19: =MIN(Q10,$H17) -> 6 | R19: =MIN(R10,$H17) -> 7 | S19: =MIN(S10,$H17) -> 8 | ... AI19: =MIN(AI10,$H17) -> 12
B21: MILESTONE FLAGS
B22: ARR Milestone? | F22: # | H22: =Ctrl!H56 -> 750 | L22: =ROUNDDOWN(L57/$H22,0) -> 1 | M22: =ROUNDDOWN(M57/$H22,0) -> 2 | N22: =ROUNDDOWN(N57/$H22,0) -> 3 | O22: =ROUNDDOWN(O57/$H22,0) -> 3 | P22: =ROUNDDOWN(P57/$H22,0) -> 3 | Q22: =ROUNDDOWN(Q57/$H22,0) -> 3 | R22: =ROUNDDOWN(R57/$H22,0) -> 3 | S22: =ROUNDDOWN(S57/$H22,0) -> 3 | ... AI22: =ROUNDDOWN(AI57/$H22,0) -> 3
B23: Customer Milestone | F23: # | H23: =Ctrl!H57 -> 2500 | L23: =ROUNDDOWN(L30/$H23,0) -> 1 | M23: =ROUNDDOWN(M30/$H23,0) -> 2 | N23: =ROUNDDOWN(N30/$H23,0) -> 3 | O23: =ROUNDDOWN(O30/$H23,0) -> 3 | P23: =ROUNDDOWN(P30/$H23,0) -> 3 | Q23: =ROUNDDOWN(Q30/$H23,0) -> 3 | R23: =ROUNDDOWN(R30/$H23,0) -> 3 | S23: =ROUNDDOWN(S30/$H23,0) -> 3 | ... AI23: =ROUNDDOWN(AI30/$H23,0) -> 6
B24: Headcount Milestone | F24: # | H24: =Ctrl!H58 -> 20 | K24: 1 | L24: =K24+(MOD(L98,20)=0) -> 1 | M24: =L24+(MOD(M98,20)=0) -> 1 | N24: =M24+(MOD(N98,20)=0) -> 1 | O24: =N24+(MOD(O98,20)=0) -> 1 | P24: =O24+(MOD(P98,20)=0) -> 1 | Q24: =P24+(MOD(Q98,20)=0) -> 1 | R24: =Q24+(MOD(R98,20)=0) -> 1 | S24: =R24+(MOD(S98,20)=0) -> 1 | ... AI24: =AH24+(MOD(AI98,20)=0) -> 2
B26: Launch Phasing | F26: # | L26: =Ctrl!H34 -> 0.5 | M26: =Ctrl!H35 -> 0.3 | N26: =Ctrl!H36 -> 0.2
A28: X | B28: SUBSCRIBERS
B30: Total Customers | F30: # | L30: =SUM(L38,L48) -> 4915 | M30: =SUM(M38,M48) -> 7249.625 | N30: =SUM(N38,N48) -> 8386.2188 | O30: =SUM(O38,O48) -> 8209.5859 | P30: =SUM(P38,P48) -> 8135.139 | Q30: =SUM(Q38,Q48) -> 8152.8486 | R30: =SUM(R38,R48) -> 8254.5603 | S30: =SUM(S38,S48) -> 8433.74 | ... AI30: =SUM(AI38,AI48) -> 15144.973
B32: MONTHLY PLAN
B33: Opening | F33: # | L33: =K38 -> 0 | M33: =L38 -> 2457.5 | N33: =M38 -> 3317.625 | O33: =N38 -> 3471.2188 | P33: =O38 -> 2950.5359 | Q33: =P38 -> 2507.9555 | R33: =Q38 -> 2131.7622 | S33: =R38 -> 1811.9979 | ... AI33: =AH38 -> 134.54281
B34: Additions | F34: # | L34: =Ctrl!$H$31/2*L26 -> 2457.5 | M34: =Ctrl!$H$31/2*M26 -> 1474.5 | N34: =Ctrl!$H$31/2*N26 -> 983 | O34: =O35*O33 -> 347.12188 | P34: =P35*P33 -> 295.05359 | Q34: =Q35*Q33 -> 250.79555 | R34: =R35*R33 -> 213.17622 | S34: =S35*S33 -> 181.19979 | T34: =T35*T33 -> 154.01982 | U34: =U35*U33 -> 130.91685 | V34: =V35*V33 -> 111.27932 | ... AI34: =AI35*AI33 -> 13.454281
B35: % adds | F35: % | L35: =Ctrl!H39 -> 0.1 | M35: =L35 -> 0.1 | N35: =M35 -> 0.1 | O35: =N35 -> 0.1 | P35: =O35 -> 0.1 | Q35: =P35 -> 0.1 | R35: =Q35 -> 0.1 | S35: =R35 -> 0.1 | T35: =S35 -> 0.1 | ... AI35: =AH35 -> 0.1
B36: Churn | F36: # | L36: =-L33*L37 -> 0 | M36: =-M33*M37 -> -614.375 | N36: =-N33*N37 -> -829.40625 | O36: =-O33*O37 -> -867.80469 | P36: =-P33*P37 -> -737.63398 | Q36: =-Q33*Q37 -> -626.98889 | R36: =-R33*R37 -> -532.94055 | S36: =-S33*S37 -> -452.99947 | ... AI36: =-AI33*AI37 -> -33.635703
B37: % churn | F37: % | L37: =Ctrl!H43 -> 0.25 | M37: =L37 -> 0.25 | N37: =M37 -> 0.25 | O37: =N37 -> 0.25 | P37: =O37 -> 0.25 | Q37: =P37 -> 0.25 | R37: =Q37 -> 0.25 | S37: =R37 -> 0.25 | T37: =S37 -> 0.25 | ... AI37: =AH37 -> 0.25
B38: CLOSING | F38: # | K38: 0 | L38: =SUM(L33:L34,L36) -> 2457.5 | M38: =SUM(M33:M34,M36) -> 3317.625 | N38: =SUM(N33:N34,N36) -> 3471.2188 | O38: =SUM(O33:O34,O36) -> 2950.5359 | P38: =SUM(P33:P34,P36) -> 2507.9555 | Q38: =SUM(Q33:Q34,Q36) -> 2131.7622 | R38: =SUM(R33:R34,R36) -> 1811.9979 | S38: =SUM(S33:S34,S36) -> 1540.1982 | ... AI38: =SUM(AI33:AI34,AI36) -> 114.36139
B39: % net adds - MoM | F39: % | M39: =M38/L38-1 -> 0.35 | N39: =N38/M38-1 -> 0.046296296 | O39: =O38/N38-1 -> -0.15 | P39: =P38/O38-1 -> -0.15 | Q39: =Q38/P38-1 -> -0.15 | R39: =R38/Q38-1 -> -0.15 | S39: =S38/R38-1 -> -0.15 | T39: =T38/S38-1 -> -0.15 | ... AI39: =AI38/AH38-1 -> -0.15
B40: % net adds - YoY | F40: % | X40: =X38/L38-1 -> -0.7219149 | Y40: =Y38/M38-1 -> -0.82490938 | Z40: =Z38/N38-1 -> -0.85775824 | AA40: =AA38/O38-1 -> -0.85775824 | AB40: =AB38/P38-1 -> -0.85775824 | AC40: =AC38/Q38-1 -> -0.85775824 | AD40: =AD38/R38-1 -> -0.85775824 | AE40: =AE38/S38-1 -> -0.85775824 | ... AI40: =AI38/W38-1 -> -0.85775824
B42: ANNUAL PLAN
B43: Opening | F43: # | K43: =K48-K44 -> 0 | L43: =K48 -> 0 | M43: =L48 -> 2457.5 | N43: =M48 -> 3932 | O43: =N48 -> 4915 | P43: =O48 -> 5259.05 | Q43: =P48 -> 5627.1835 | R43: =Q48 -> 6021.0863 | S43: =R48 -> 6442.5624 | ... AI43: =AH48 -> 14240.665
B44: Additions | F44: # | K44: =K48 -> 0 | L44: =Ctrl!$H$31/2*L26 -> 2457.5 | M44: =Ctrl!$H$31/2*M26 -> 1474.5 | N44: =Ctrl!$H$31/2*N26 -> 983 | O44: =O45*O43 -> 344.05 | P44: =P45*P43 -> 368.1335 | Q44: =Q45*Q43 -> 393.90285 | R44: =R45*R43 -> 421.47604 | S44: =S45*S43 -> 450.97937 | T44: =T45*T43 -> 482.54792 | U44: =U45*U43 -> 516.32628 | V44: =V45*V43 -> 552.46912 | ... AI44: =AI45*AI43 -> 996.84653
B45: % adds | F45: % | L45: =Ctrl!H40 -> 0.07 | M45: =L45 -> 0.07 | N45: =M45 -> 0.07 | O45: =N45 -> 0.07 | P45: =O45 -> 0.07 | Q45: =P45 -> 0.07 | R45: =Q45 -> 0.07 | S45: =R45 -> 0.07 | T45: =S45 -> 0.07 | ... AI45: =AH45 -> 0.07
B46: Churn | F46: # | L46: =IF(SUM($L17:L17)>0,-OFFSET(L44,,-$H$17)*L47,0) -> 0 | M46: =IF(SUM($L17:M17)>0,-OFFSET(M44,,-$H$17)*M47,0) -> 0 | N46: =IF(SUM($L17:N17)>0,-OFFSET(N44,,-$H$17)*N47,0) -> 0 | O46: =IF(SUM($L17:O17)>0,-OFFSET(O44,,-$H$17)*O47,0) -> 0 | P46: =IF(SUM($L17:P17)>0,-OFFSET(P44,,-$H$17)*P47,0) -> 0 | Q46: =IF(SUM($L17:Q17)>0,-OFFSET(Q44,,-$H$17)*Q47,0) -> 0 | R46: =IF(SUM($L17:R17)>0,-OFFSET(R44,,-$H$17)*R47,0) -> 0 | S46: =IF(SUM($L17:S17)>0,-OFFSET(S44,,-$H$17)*S47,0) -> 0 | ... AI46: =IF(SUM($L17:AI17)>0,-OFFSET(AI44,,-$H$17)*AI47,0) -> -206.89968
B47: % churn | F47: % | H47: =Ctrl!H44 -> 0.35 | L47: =$H47*(SUM($L17:L17)>0) -> 0 | M47: =$H47*(SUM($L17:M17)>0) -> 0 | N47: =$H47*(SUM($L17:N17)>0) -> 0 | O47: =$H47*(SUM($L17:O17)>0) -> 0 | P47: =$H47*(SUM($L17:P17)>0) -> 0 | Q47: =$H47*(SUM($L17:Q17)>0) -> 0 | R47: =$H47*(SUM($L17:R17)>0) -> 0 | S47: =$H47*(SUM($L17:S17)>0) -> 0 | ... AI47: =$H47*(SUM($L17:AI17)>0) -> 0.35
B48: CLOSING | F48: # | K48: 0 | L48: =SUM(L43:L44,L46) -> 2457.5 | M48: =SUM(M43:M44,M46) -> 3932 | N48: =SUM(N43:N44,N46) -> 4915 | O48: =SUM(O43:O44,O46) -> 5259.05 | P48: =SUM(P43:P44,P46) -> 5627.1835 | Q48: =SUM(Q43:Q44,Q46) -> 6021.0863 | R48: =SUM(R43:R44,R46) -> 6442.5624 | S48: =SUM(S43:S44,S46) -> 6893.5418 | ... AI48: =SUM(AI43:AI44,AI46) -> 15030.612
B49: % net adds - MoM | F49: % | M49: =M48/L48-1 -> 0.6 | N49: =N48/M48-1 -> 0.25 | O49: =O48/N48-1 -> 0.07 | P49: =P48/O48-1 -> 0.07 | Q49: =Q48/P48-1 -> 0.07 | R49: =R48/Q48-1 -> 0.07 | S49: =S48/R48-1 -> 0.07 | T49: =T48/S48-1 -> 0.07 | ... AI49: =AI48/AH48-1 -> 0.055471206
B50: % net adds - YoY | F50: % | X50: =X48/L48-1 -> 2.5843027 | Y50: =Y48/M48-1 -> 1.2657524 | Z50: =Z48/N48-1 -> 0.86948409 | AA50: =AA48/O48-1 -> 0.84658689 | AB50: =AB48/P48-1 -> 0.8236897 | AC50: =AC48/Q48-1 -> 0.8007925 | AD50: =AD48/R48-1 -> 0.7778953 | AE50: =AE48/S48-1 -> 0.75499811 | ... AI50: =AI48/W48-1 -> 0.66340932
A52: X | B52: REVENUE
B54: SUMMARY
B55: Revenue | F55: $k | L55: =SUM(L62,L70) -> 70.653125 | M55: =SUM(M62,M70) -> 174.4825 | N55: =SUM(N62,N70) -> 223.47891 | O55: =SUM(O62,O70) -> 236.21951 | P55: =SUM(P62,P70) -> 231.56308 | Q55: =SUM(Q62,Q70) -> 229.75948 | R55: =SUM(R62,R70) -> 230.53157 | S55: =SUM(S62,S70) -> 233.65437 | ... AI55: =SUM(AI62,AI70) -> 249.97796
B56: Bookings | F56: $k | L56: =SUM(L62,L68) -> 442.35 | M56: =SUM(M62,M68) -> 735.40688 | N56: =SUM(N62,N68) -> 507.32016 | O56: =SUM(O62,O68) -> 315.28957 | P56: =SUM(P62,P68) -> 199.38765 | Q56: =SUM(Q62,Q68) -> 195.33176 | R56: =SUM(R62,R68) -> 193.69392 | S56: =SUM(S62,S68) -> 194.23808 | ... AI56: =SUM(AI62,AI68) -> 324.01981
B57: ARR | F57: $k | L57: =SUM(L63,L71) -> 847.8375 | M57: =SUM(M63,M71) -> 2093.79 | N57: =SUM(N63,N71) -> 2681.7469 | O57: =SUM(O63,O71) -> 2834.6341 | P57: =SUM(P63,P71) -> 2778.757 | Q57: =SUM(Q63,Q71) -> 2757.1137 | R57: =SUM(R63,R71) -> 2766.3789 | S57: =SUM(S63,S71) -> 2803.8525 | ... AI57: =SUM(AI63,AI71) -> 2999.7355
B59: =B32 -> MONTHLY PLAN
B60: Subscribers | F60: # | L60: =AVERAGE(L33,L38) -> 1228.75 | M60: =AVERAGE(M33,M38) -> 2887.5625 | N60: =AVERAGE(N33,N38) -> 3394.4219 | O60: =AVERAGE(O33,O38) -> 3210.8773 | P60: =AVERAGE(P33,P38) -> 2729.2457 | Q60: =AVERAGE(Q33,Q38) -> 2319.8589 | R60: =AVERAGE(R33,R38) -> 1971.88 | S60: =AVERAGE(S33,S38) -> 1676.098 | ... AI60: =AVERAGE(AI33,AI38) -> 124.4521
B61: ARPU | F61: $/user | H61: =Ctrl!H51 -> 0 | L61: =Ctrl!H47 -> 30 | M61: =L61*(1+$H61*M$17) -> 30 | N61: =M61*(1+$H61*N$17) -> 30 | O61: =N61*(1+$H61*O$17) -> 30 | P61: =O61*(1+$H61*P$17) -> 30 | Q61: =P61*(1+$H61*Q$17) -> 30 | R61: =Q61*(1+$H61*R$17) -> 30 | S61: =R61*(1+$H61*S$17) -> 30 | T61: =S61*(1+$H61*T$17) -> 30 | ... AI61: =AH61*(1+$H61*AI$17) -> 30
B62: Revenue / Bookings | F62: $k | L62: =L60*L61/10^3 -> 36.8625 | M62: =M60*M61/10^3 -> 86.626875 | N62: =N60*N61/10^3 -> 101.83266 | O62: =O60*O61/10^3 -> 96.32632 | P62: =P60*P61/10^3 -> 81.877372 | Q62: =Q60*Q61/10^3 -> 69.595766 | R62: =R60*R61/10^3 -> 59.156401 | S62: =S60*S61/10^3 -> 50.282941 | ... AI62: =AI60*AI61/10^3 -> 3.733563
B63: ARR | F63: $k | L63: =L62*12 -> 442.35 | M63: =M62*12 -> 1039.5225 | N63: =N62*12 -> 1221.9919 | O63: =O62*12 -> 1155.9158 | P63: =P62*12 -> 982.52847 | Q63: =Q62*12 -> 835.1492 | R63: =R62*12 -> 709.87682 | S63: =S62*12 -> 603.39529 | ... AI63: =AI62*12 -> 44.802756
B65: ANNUAL PLAN
B66: New Subscribers | F66: # | L66: =AVERAGE(K44:L44) -> 1228.75 | M66: =AVERAGE(L44:M44) -> 1966 | N66: =AVERAGE(M44:N44) -> 1228.75 | O66: =AVERAGE(N44:O44) -> 663.525 | P66: =AVERAGE(O44:P44) -> 356.09175 | Q66: =AVERAGE(P44:Q44) -> 381.01817 | R66: =AVERAGE(Q44:R44) -> 407.68944 | S66: =AVERAGE(R44:S44) -> 436.22771 | ... AI66: =AVERAGE(AH44:AI44) -> 970.5644
B67: ARPU | F67: $/user | H67: =Ctrl!H52 -> 0 | L67: =Ctrl!H48 -> 330 | M67: =L67*(1+$H67*M$17) -> 330 | N67: =M67*(1+$H67*N$17) -> 330 | O67: =N67*(1+$H67*O$17) -> 330 | P67: =O67*(1+$H67*P$17) -> 330 | Q67: =P67*(1+$H67*Q$17) -> 330 | R67: =Q67*(1+$H67*R$17) -> 330 | S67: =R67*(1+$H67*S$17) -> 330 | T67: =S67*(1+$H67*T$17) -> 330 | ... AI67: =AH67*(1+$H67*AI$17) -> 330
B68: Bookings | F68: $k | L68: =L66*L67/10^3 -> 405.4875 | M68: =M66*M67/10^3 -> 648.78 | N68: =N66*N67/10^3 -> 405.4875 | O68: =O66*O67/10^3 -> 218.96325 | P68: =P66*P67/10^3 -> 117.51028 | Q68: =Q66*Q67/10^3 -> 125.736 | R68: =R66*R67/10^3 -> 134.53752 | S68: =S66*S67/10^3 -> 143.95514 | ... AI68: =AI66*AI67/10^3 -> 320.28625
B69: Monthly Revenue Contribution | F69: $k | L69: =L68/12 -> 33.790625 | M69: =M68/12 -> 54.065 | N69: =N68/12 -> 33.790625 | O69: =O68/12 -> 18.246937 | P69: =P68/12 -> 9.7925231 | Q69: =Q68/12 -> 10.478 | R69: =R68/12 -> 11.21146 | S69: =S68/12 -> 11.996262 | ... AI69: =AI68/12 -> 26.690521
B70: LTM Monthly Revenue Contribution | F70: $k | L70: =SUM(OFFSET(L69,,,,-L19)) -> 33.790625 | M70: =SUM(OFFSET(M69,,,,-M19)) -> 87.855625 | N70: =SUM(OFFSET(N69,,,,-N19)) -> 121.64625 | O70: =SUM(OFFSET(O69,,,,-O19)) -> 139.89319 | P70: =SUM(OFFSET(P69,,,,-P19)) -> 149.68571 | Q70: =SUM(OFFSET(Q69,,,,-Q19)) -> 160.16371 | R70: =SUM(OFFSET(R69,,,,-R19)) -> 171.37517 | S70: =SUM(OFFSET(S69,,,,-S19)) -> 183.37143 | ... AI70: =SUM(OFFSET(AI69,,,,-AI19)) -> 246.2444
B71: ARR | F71: $k | L71: =L70*12 -> 405.4875 | M71: =M70*12 -> 1054.2675 | N71: =N70*12 -> 1459.755 | O71: =O70*12 -> 1678.7183 | P71: =P70*12 -> 1796.2285 | Q71: =Q70*12 -> 1921.9645 | R71: =R70*12 -> 2056.502 | S71: =S70*12 -> 2200.4572 | ... AI71: =AI70*12 -> 2954.9328
A73: X | B73: COGS
B75: COGS | F75: $k | L75: =SUM(L81,L86) -> -26.172375 | M75: =SUM(M81,M86) -> -50.354175 | N75: =SUM(N81,N86) -> -47.110275 | O75: =SUM(O81,O86) -> -40.957924 | P75: =SUM(P81,P86) -> -35.763076 | Q75: =SUM(Q81,Q86) -> -35.384408 | R75: =SUM(R81,R86) -> -35.411545 | S75: =SUM(S81,S86) -> -35.808048 | ... AI75: =SUM(AI81,AI86) -> -34.718391
B78: PAYMENT PROCESSING FEES
B79: 2024 | F79: $k | H79: 0.04 | L79: =-$H79*L$56*(L$9=$B79) -> -17.694 | M79: =-$H79*M$56*(M$9=$B79) -> -29.416275 | N79: =-$H79*N$56*(N$9=$B79) -> -20.292806 | O79: =-$H79*O$56*(O$9=$B79) -> -12.611583 | P79: =-$H79*P$56*(P$9=$B79) -> -7.975506 | Q79: =-$H79*Q$56*(Q$9=$B79) -> -7.8132705 | R79: =-$H79*R$56*(R$9=$B79) -> -7.7477567 | S79: =-$H79*S$56*(S$9=$B79) -> -7.7695234 | ... AI79: =-$H79*AI$56*(AI$9=$B79) -> 0
B80: 2025 | F80: $k | H80: 0.03 | L80: =-$H80*L$56*(L$9=$B80) -> 0 | M80: =-$H80*M$56*(M$9=$B80) -> 0 | N80: =-$H80*N$56*(N$9=$B80) -> 0 | O80: =-$H80*O$56*(O$9=$B80) -> 0 | P80: =-$H80*P$56*(P$9=$B80) -> 0 | Q80: =-$H80*Q$56*(Q$9=$B80) -> 0 | R80: =-$H80*R$56*(R$9=$B80) -> 0 | S80: =-$H80*S$56*(S$9=$B80) -> 0 | ... AI80: =-$H80*AI$56*(AI$9=$B80) -> -9.7205944
B81: TOTAL | F81: $k | L81: =SUM(L79:L80) -> -17.694 | M81: =SUM(M79:M80) -> -29.416275 | N81: =SUM(N79:N80) -> -20.292806 | O81: =SUM(O79:O80) -> -12.611583 | P81: =SUM(P79:P80) -> -7.975506 | Q81: =SUM(Q79:Q80) -> -7.8132705 | R81: =SUM(R79:R80) -> -7.7477567 | S81: =SUM(S79:S80) -> -7.7695234 | ... AI81: =SUM(AI79:AI80) -> -9.7205944
B83: HOSTING FEES
B84: 2024 | F84: $k | H84: 0.12 | L84: =-$H84*L$55*(L$9=$B84) -> -8.478375 | M84: =-$H84*M$55*(M$9=$B84) -> -20.9379 | N84: =-$H84*N$55*(N$9=$B84) -> -26.817469 | O84: =-$H84*O$55*(O$9=$B84) -> -28.346341 | P84: =-$H84*P$55*(P$9=$B84) -> -27.78757 | Q84: =-$H84*Q$55*(Q$9=$B84) -> -27.571137 | R84: =-$H84*R$55*(R$9=$B84) -> -27.663789 | S84: =-$H84*S$55*(S$9=$B84) -> -28.038525 | ... AI84: =-$H84*AI$55*(AI$9=$B84) -> 0
B85: 2025 | F85: $k | H85: 0.1 | L85: =-$H85*L$55*(L$9=$B85) -> 0 | M85: =-$H85*M$55*(M$9=$B85) -> 0 | N85: =-$H85*N$55*(N$9=$B85) -> 0 | O85: =-$H85*O$55*(O$9=$B85) -> 0 | P85: =-$H85*P$55*(P$9=$B85) -> 0 | Q85: =-$H85*Q$55*(Q$9=$B85) -> 0 | R85: =-$H85*R$55*(R$9=$B85) -> 0 | S85: =-$H85*S$55*(S$9=$B85) -> 0 | ... AI85: =-$H85*AI$55*(AI$9=$B85) -> -24.997796
B86: TOTAL | F86: $k | L86: =SUM(L84:L85) -> -8.478375 | M86: =SUM(M84:M85) -> -20.9379 | N86: =SUM(N84:N85) -> -26.817469 | O86: =SUM(O84:O85) -> -28.346341 | P86: =SUM(P84:P85) -> -27.78757 | Q86: =SUM(Q84:Q85) -> -27.571137 | R86: =SUM(R84:R85) -> -27.663789 | S86: =SUM(S84:S85) -> -28.038525 | ... AI86: =SUM(AI84:AI85) -> -24.997796
A88: X | B88: HEADCOUNT COSTS
B90: SUMMARY
B91: Core Executives | F91: $k | L91: =L105 -> 30 | M91: =M105 -> 30 | N91: =N105 -> 30 | O91: =O105 -> 30 | P91: =P105 -> 30 | Q91: =Q105 -> 30 | R91: =R105 -> 30 | S91: =S105 -> 30 | ... AI91: =AI105 -> 32.4
B92: New Executives | F92: $k | L92: =L110 -> 0 | M92: =M110 -> 12.5 | N92: =N110 -> 25 | O92: =O110 -> 25 | P92: =P110 -> 25 | Q92: =Q110 -> 25 | R92: =R110 -> 25 | S92: =S110 -> 25 | ... AI92: =AI110 -> 27
B93: Engineers | F93: $k | L93: =L116 -> 15 | M93: =M116 -> 15 | N93: =N116 -> 30 | O93: =O116 -> 30 | P93: =P116 -> 30 | Q93: =Q116 -> 45 | R93: =R116 -> 45 | S93: =S116 -> 45 | ... AI93: =AI116 -> 145.8
B94: Customer Support Representatives | F94: $k | L94: =L122 -> 10 | M94: =M122 -> 20 | N94: =N122 -> 30 | O94: =O122 -> 30 | P94: =P122 -> 30 | Q94: =Q122 -> 30 | R94: =R122 -> 30 | S94: =S122 -> 30 | ... AI94: =AI122 -> 64.8
B95: Subtotal | F95: $k | L95: =SUM(L91:L94) -> 55 | M95: =SUM(M91:M94) -> 77.5 | N95: =SUM(N91:N94) -> 115 | O95: =SUM(O91:O94) -> 115 | P95: =SUM(P91:P94) -> 115 | Q95: =SUM(Q91:Q94) -> 130 | R95: =SUM(R91:R94) -> 130 | S95: =SUM(S91:S94) -> 130 | ... AI95: =SUM(AI91:AI94) -> 270
B96: Fringe Costs | F96: $k | H96: 0.15 | L96: =$H96*L95 -> 8.25 | M96: =$H96*M95 -> 11.625 | N96: =$H96*N95 -> 17.25 | O96: =$H96*O95 -> 17.25 | P96: =$H96*P95 -> 17.25 | Q96: =$H96*Q95 -> 19.5 | R96: =$H96*R95 -> 19.5 | S96: =$H96*S95 -> 19.5 | ... AI96: =$H96*AI95 -> 40.5
B97: TOTAL | F97: $k | L97: =SUM(L95:L96) -> 63.25 | M97: =SUM(M95:M96) -> 89.125 | N97: =SUM(N95:N96) -> 132.25 | O97: =SUM(O95:O96) -> 132.25 | P97: =SUM(P95:P96) -> 132.25 | Q97: =SUM(Q95:Q96) -> 149.5 | R97: =SUM(R95:R96) -> 149.5 | S97: =SUM(S95:S96) -> 149.5 | ... AI97: =SUM(AI95:AI96) -> 310.5
B98: # FTEs | F98: # | L98: =SUM(L103,L108,L113,L119) -> 5 | M98: =SUM(M103,M108,M113,M119) -> 7 | N98: =SUM(N103,N108,N113,N119) -> 10 | O98: =SUM(O103,O108,O113,O119) -> 10 | P98: =SUM(P103,P108,P113,P119) -> 10 | Q98: =SUM(Q103,Q108,Q113,Q119) -> 11 | R98: =SUM(R103,R108,R113,R119) -> 11 | S98: =SUM(S103,S108,S113,S119) -> 11 | ... AI98: =SUM(AI103,AI108,AI113,AI119) -> 20
B100: Salary Increase | F100: % | H100: =Ctrl!H63 -> 0.08 | I100: 12 | L100: =$H100*(L$10=$I100) -> 0 | M100: =$H100*(M$10=$I100) -> 0 | N100: =$H100*(N$10=$I100) -> 0 | O100: =$H100*(O$10=$I100) -> 0 | P100: =$H100*(P$10=$I100) -> 0 | Q100: =$H100*(Q$10=$I100) -> 0 | R100: =$H100*(R$10=$I100) -> 0 | S100: =$H100*(S$10=$I100) -> 0 | ... AI100: =$H100*(AI$10=$I100) -> 0
B102: CORE EXECUTIVES
B103: # FTEs | F103: # | L103: 3 | M103: =L103 -> 3 | N103: =M103 -> 3 | O103: =N103 -> 3 | P103: =O103 -> 3 | Q103: =P103 -> 3 | R103: =Q103 -> 3 | S103: =R103 -> 3 | T103: =S103 -> 3 | ... AI103: =AH103 -> 3
B104: $/FTE | F104: $k | H104: =Ctrl!H66 -> 120 | L104: =$H104 -> 120 | M104: =L104*(1+M$100) -> 120 | N104: =M104*(1+N$100) -> 120 | O104: =N104*(1+O$100) -> 120 | P104: =O104*(1+P$100) -> 120 | Q104: =P104*(1+Q$100) -> 120 | R104: =Q104*(1+R$100) -> 120 | S104: =R104*(1+S$100) -> 120 | T104: =S104*(1+T$100) -> 120 | ... AI104: =AH104*(1+AI$100) -> 129.6
B105: TOTAL | F105: $k | L105: =L103*L104/12 -> 30 | M105: =M103*M104/12 -> 30 | N105: =N103*N104/12 -> 30 | O105: =O103*O104/12 -> 30 | P105: =P103*P104/12 -> 30 | Q105: =Q103*Q104/12 -> 30 | R105: =R103*R104/12 -> 30 | S105: =S103*S104/12 -> 30 | ... AI105: =AI103*AI104/12 -> 32.4
B107: NEW EXECUTIVES
B108: # FTEs | F108: # | L108: =L22-$L$22 -> 0 | M108: =M22-$L$22 -> 1 | N108: =N22-$L$22 -> 2 | O108: =O22-$L$22 -> 2 | P108: =P22-$L$22 -> 2 | Q108: =Q22-$L$22 -> 2 | R108: =R22-$L$22 -> 2 | S108: =S22-$L$22 -> 2 | ... AI108: =AI22-$L$22 -> 2
B109: $/FTE | F109: $k | H109: =Ctrl!H67 -> 150 | L109: =$H109 -> 150 | M109: =L109*(1+M$100) -> 150 | N109: =M109*(1+N$100) -> 150 | O109: =N109*(1+O$100) -> 150 | P109: =O109*(1+P$100) -> 150 | Q109: =P109*(1+Q$100) -> 150 | R109: =Q109*(1+R$100) -> 150 | S109: =R109*(1+S$100) -> 150 | T109: =S109*(1+T$100) -> 150 | ... AI109: =AH109*(1+AI$100) -> 162
B110: TOTAL | F110: $k | L110: =L108*L109/12 -> 0 | M110: =M108*M109/12 -> 12.5 | N110: =N108*N109/12 -> 25 | O110: =O108*O109/12 -> 25 | P110: =P108*P109/12 -> 25 | Q110: =Q108*Q109/12 -> 25 | R110: =R108*R109/12 -> 25 | S110: =S108*S109/12 -> 25 | ... AI110: =AI108*AI109/12 -> 27
B112: ENGINEERS
B113: # FTEs | F113: # | L113: 1 | M113: =L113+M114 -> 1 | N113: =M113+N114 -> 2 | O113: =N113+O114 -> 2 | P113: =O113+P114 -> 2 | Q113: =P113+Q114 -> 3 | R113: =Q113+R114 -> 3 | S113: =R113+S114 -> 3 | T113: =S113+T114 -> 4 | ... AI113: =AH113+AI114 -> 9
B114: New Engineer Added? | F114: # | M114: =M18 -> 0 | N114: =N18 -> 1 | O114: =O18 -> 0 | P114: =P18 -> 0 | Q114: =Q18 -> 1 | R114: =R18 -> 0 | S114: =S18 -> 0 | T114: =T18 -> 1 | ... AI114: =AI18 -> 1
B115: $/FTE | F115: $k | H115: =Ctrl!H68 -> 180 | L115: =$H115 -> 180 | M115: =L115*(1+M$100) -> 180 | N115: =M115*(1+N$100) -> 180 | O115: =N115*(1+O$100) -> 180 | P115: =O115*(1+P$100) -> 180 | Q115: =P115*(1+Q$100) -> 180 | R115: =Q115*(1+R$100) -> 180 | S115: =R115*(1+S$100) -> 180 | T115: =S115*(1+T$100) -> 180 | ... AI115: =AH115*(1+AI$100) -> 194.4
B116: TOTAL | F116: $k | L116: =L113*L115/12 -> 15 | M116: =M113*M115/12 -> 15 | N116: =N113*N115/12 -> 30 | O116: =O113*O115/12 -> 30 | P116: =P113*P115/12 -> 30 | Q116: =Q113*Q115/12 -> 45 | R116: =R113*R115/12 -> 45 | S116: =S113*S115/12 -> 45 | ... AI116: =AI113*AI115/12 -> 145.8
B118: CUSTOMER SUPPORT REPRESENTATIVE
B119: # FTEs | F119: # | L119: 1 | M119: =MAX(L119+M120,0) -> 2 | N119: =MAX(M119+N120,0) -> 3 | O119: =MAX(N119+O120,0) -> 3 | P119: =MAX(O119+P120,0) -> 3 | Q119: =MAX(P119+Q120,0) -> 3 | R119: =MAX(Q119+R120,0) -> 3 | S119: =MAX(R119+S120,0) -> 3 | T119: =MAX(S119+T120,0) -> 3 | ... AI119: =MAX(AH119+AI120,0) -> 6
B120: New Customer Support Added? | F120: # | M120: =M23-L23 -> 1 | N120: =N23-M23 -> 1 | O120: =O23-N23 -> 0 | P120: =P23-O23 -> 0 | Q120: =Q23-P23 -> 0 | R120: =R23-Q23 -> 0 | S120: =S23-R23 -> 0 | T120: =T23-S23 -> 0 | ... AI120: =AI23-AH23 -> 1
B121: $/FTE | F121: $k | H121: =Ctrl!H69 -> 120 | L121: =$H121 -> 120 | M121: =L121*(1+M$100) -> 120 | N121: =M121*(1+N$100) -> 120 | O121: =N121*(1+O$100) -> 120 | P121: =O121*(1+P$100) -> 120 | Q121: =P121*(1+Q$100) -> 120 | R121: =Q121*(1+R$100) -> 120 | S121: =R121*(1+S$100) -> 120 | T121: =S121*(1+T$100) -> 120 | ... AI121: =AH121*(1+AI$100) -> 129.6
B122: TOTAL | F122: $k | L122: =L119*L121/12 -> 10 | M122: =M119*M121/12 -> 20 | N122: =N119*N121/12 -> 30 | O122: =O119*O121/12 -> 30 | P122: =P119*P121/12 -> 30 | Q122: =Q119*Q121/12 -> 30 | R122: =R119*R121/12 -> 30 | S122: =S119*S121/12 -> 30 | ... AI122: =AI119*AI121/12 -> 64.8
A124: X | B124: OTHER OPEX
B126: G&A | F126: $k | L126: 20 | M126: =L126*(1+M127) -> 20 | N126: =M126*(1+N127) -> 21.4 | O126: =N126*(1+O127) -> 21.4 | P126: =O126*(1+P127) -> 21.4 | Q126: =P126*(1+Q127) -> 22.898 | R126: =Q126*(1+R127) -> 22.898 | S126: =R126*(1+S127) -> 22.898 | T126: =S126*(1+T127) -> 24.50086 | ... AI126: =AH126*(1+AI127) -> 34.363724
B127: % growth | F127: % | H127: =Ctrl!H73 -> 0.07 | L127: =$H127*L18 -> 0 | M127: =$H127*M18 -> 0 | N127: =$H127*N18 -> 0.07 | O127: =$H127*O18 -> 0 | P127: =$H127*P18 -> 0 | Q127: =$H127*Q18 -> 0.07 | R127: =$H127*R18 -> 0 | S127: =$H127*S18 -> 0 | ... AI127: =$H127*AI18 -> 0.07
B128: S&M | F128: $k | H128: =Ctrl!H74 -> 200 | L128: =$H128/10^3*(L34+L44) -> 983 | M128: =$H128/10^3*(M34+M44) -> 589.8 | N128: =$H128/10^3*(N34+N44) -> 393.2 | O128: =$H128/10^3*(O34+O44) -> 138.23438 | P128: =$H128/10^3*(P34+P44) -> 132.63742 | Q128: =$H128/10^3*(Q34+Q44) -> 128.93968 | R128: =$H128/10^3*(R34+R44) -> 126.93045 | S128: =$H128/10^3*(S34+S44) -> 126.43583 | ... AI128: =$H128/10^3*(AI34+AI44) -> 202.06016
B129: S&M/customer | F129: $/customer | L129: =L128/SUM(L34,L44)*10^3 -> 200 | M129: =M128/SUM(M34,M44)*10^3 -> 200 | N129: =N128/SUM(N34,N44)*10^3 -> 200 | O129: =O128/SUM(O34,O44)*10^3 -> 200 | P129: =P128/SUM(P34,P44)*10^3 -> 200 | Q129: =Q128/SUM(Q34,Q44)*10^3 -> 200 | R129: =R128/SUM(R34,R44)*10^3 -> 200 | S129: =S128/SUM(S34,S44)*10^3 -> 200 | ... AI129: =AI128/SUM(AI34,AI44)*10^3 -> 200
B131: Facilities
B132: # offices | F132: # | H132: 20 | L132: =L24 -> 1 | M132: =M24 -> 1 | N132: =N24 -> 1 | O132: =O24 -> 1 | P132: =P24 -> 1 | Q132: =Q24 -> 1 | R132: =R24 -> 1 | S132: =S24 -> 1 | ... AI132: =AI24 -> 2
...

Sheet Fin>
B9: Project Eagle
B10: Operating Model
B11: Summary Financials

Sheet Fin.Mth
B3: ='Calc.Mth'!B3 -> Project Eagle
B4: Summary Financials | Monthly | G4: Runway | H4: Fundraise | I4: Fund. Date | J4: End. ARR | K4: Deferred Rev.
B5: =Ctrl!$B$5 -> CASE 1: BASE CASE | G5: =Sum!$E$19 -> 16 | H5: =Sum!$E$28 -> 3259.9201 | I5: =Sum!$E$21 -> 45626 | J5: ='Calc.Mth'!$AI$57 -> 2999.7355 | K5: =Fin.Mth!$AI$81 -> 1487.7626
B7: ='Calc.Mth'!B7 -> Period End | L7: ='Calc.Mth'!L7 -> 45322 | M7: ='Calc.Mth'!M7 -> 45351 | N7: ='Calc.Mth'!N7 -> 45382 | O7: ='Calc.Mth'!O7 -> 45412 | P7: ='Calc.Mth'!P7 -> 45443 | Q7: ='Calc.Mth'!Q7 -> 45473 | R7: ='Calc.Mth'!R7 -> 45504 | S7: ='Calc.Mth'!S7 -> 45535 | ... AI7: ='Calc.Mth'!AI7 -> 46022
B8: ='Calc.Mth'!B8 -> Period Start | L8: ='Calc.Mth'!L8 -> 45292 | M8: ='Calc.Mth'!M8 -> 45323 | N8: ='Calc.Mth'!N8 -> 45352 | O8: ='Calc.Mth'!O8 -> 45383 | P8: ='Calc.Mth'!P8 -> 45413 | Q8: ='Calc.Mth'!Q8 -> 45444 | R8: ='Calc.Mth'!R8 -> 45474 | S8: ='Calc.Mth'!S8 -> 45505 | ... AI8: ='Calc.Mth'!AI8 -> 45992
B9: ='Calc.Mth'!B9 -> Calendar Year | L9: ='Calc.Mth'!L9 -> 2024 | M9: ='Calc.Mth'!M9 -> 2024 | N9: ='Calc.Mth'!N9 -> 2024 | O9: ='Calc.Mth'!O9 -> 2024 | P9: ='Calc.Mth'!P9 -> 2024 | Q9: ='Calc.Mth'!Q9 -> 2024 | R9: ='Calc.Mth'!R9 -> 2024 | S9: ='Calc.Mth'!S9 -> 2024 | ... AI9: ='Calc.Mth'!AI9 -> 2025
B10: ='Calc.Mth'!B10 -> Period Number | L10: ='Calc.Mth'!L10 -> 1 | M10: ='Calc.Mth'!M10 -> 2 | N10: ='Calc.Mth'!N10 -> 3 | O10: ='Calc.Mth'!O10 -> 4 | P10: ='Calc.Mth'!P10 -> 5 | Q10: ='Calc.Mth'!Q10 -> 6 | R10: ='Calc.Mth'!R10 -> 7 | S10: ='Calc.Mth'!S10 -> 8 | ... AI10: ='Calc.Mth'!AI10 -> 24
B11: ='Calc.Mth'!B11 -> Days in Period | F11: ='Calc.Mth'!F11 -> Units | H11: ='Calc.Mth'!H11 -> Input I | I11: ='Calc.Mth'!I11 -> Input II | J11: ='Calc.Mth'!J11 -> Input III | K11: ='Calc.Mth'!K11 -> Total / Out | L11: ='Calc.Mth'!L11 -> 31 | M11: ='Calc.Mth'!M11 -> 29 | N11: ='Calc.Mth'!N11 -> 31 | O11: ='Calc.Mth'!O11 -> 30 | ... AI11: ='Calc.Mth'!AI11 -> 31
A15: X | B15: OPERATING METRICS
B17: # CUSTOMERS
B18: Monthly Plan | F18: # | L18: ='Calc.Mth'!L38 -> 2457.5 | M18: ='Calc.Mth'!M38 -> 3317.625 | N18: ='Calc.Mth'!N38 -> 3471.2188 | O18: ='Calc.Mth'!O38 -> 2950.5359 | P18: ='Calc.Mth'!P38 -> 2507.9555 | Q18: ='Calc.Mth'!Q38 -> 2131.7622 | R18: ='Calc.Mth'!R38 -> 1811.9979 | S18: ='Calc.Mth'!S38 -> 1540.1982 | ... AI18: ='Calc.Mth'!AI38 -> 114.36139
B19: Annual Plan | F19: # | L19: ='Calc.Mth'!L48 -> 2457.5 | M19: ='Calc.Mth'!M48 -> 3932 | N19: ='Calc.Mth'!N48 -> 4915 | O19: ='Calc.Mth'!O48 -> 5259.05 | P19: ='Calc.Mth'!P48 -> 5627.1835 | Q19: ='Calc.Mth'!Q48 -> 6021.0863 | R19: ='Calc.Mth'!R48 -> 6442.5624 | S19: ='Calc.Mth'!S48 -> 6893.5418 | ... AI19: ='Calc.Mth'!AI48 -> 15030.612
B20: TOTAL | F20: # | L20: =SUM(L18:L19) -> 4915 | M20: =SUM(M18:M19) -> 7249.625 | N20: =SUM(N18:N19) -> 8386.2188 | O20: =SUM(O18:O19) -> 8209.5859 | P20: =SUM(P18:P19) -> 8135.139 | Q20: =SUM(Q18:Q19) -> 8152.8486 | R20: =SUM(R18:R19) -> 8254.5603 | S20: =SUM(S18:S19) -> 8433.74 | ... AI20: =SUM(AI18:AI19) -> 15144.973
B22: PRICING
B23: Monthly | F23: $k | L23: ='Calc.Mth'!L61 -> 30 | M23: ='Calc.Mth'!M61 -> 30 | N23: ='Calc.Mth'!N61 -> 30 | O23: ='Calc.Mth'!O61 -> 30 | P23: ='Calc.Mth'!P61 -> 30 | Q23: ='Calc.Mth'!Q61 -> 30 | R23: ='Calc.Mth'!R61 -> 30 | S23: ='Calc.Mth'!S61 -> 30 | ... AI23: ='Calc.Mth'!AI61 -> 30
B24: Annual | F24: $k | L24: ='Calc.Mth'!L67 -> 330 | M24: ='Calc.Mth'!M67 -> 330 | N24: ='Calc.Mth'!N67 -> 330 | O24: ='Calc.Mth'!O67 -> 330 | P24: ='Calc.Mth'!P67 -> 330 | Q24: ='Calc.Mth'!Q67 -> 330 | R24: ='Calc.Mth'!R67 -> 330 | S24: ='Calc.Mth'!S67 -> 330 | ... AI24: ='Calc.Mth'!AI67 -> 330
B25: TOTAL | F25: $k | L25: =L29/L20*10^3 -> 14.375 | M25: =M29/M20*10^3 -> 24.067797 | N25: =N29/N20*10^3 -> 26.648352 | O25: =O29/O20*10^3 -> 28.77362 | P25: =P29/P20*10^3 -> 28.464551 | Q25: =Q29/Q20*10^3 -> 28.181497 | R25: =R29/R20*10^3 -> 27.927783 | S25: =S29/S20*10^3 -> 27.704716 | ... AI25: =AI29/AI20*10^3 -> 16.505672
B27: REVENUE METRICS
B28: Bookings | F28: $k | L28: ='Calc.Mth'!L56 -> 442.35 | M28: ='Calc.Mth'!M56 -> 735.40688 | N28: ='Calc.Mth'!N56 -> 507.32016 | O28: ='Calc.Mth'!O56 -> 315.28957 | P28: ='Calc.Mth'!P56 -> 199.38765 | Q28: ='Calc.Mth'!Q56 -> 195.33176 | R28: ='Calc.Mth'!R56 -> 193.69392 | S28: ='Calc.Mth'!S56 -> 194.23808 | ... AI28: ='Calc.Mth'!AI56 -> 324.01981
B29: Revenue | F29: $k | L29: ='Calc.Mth'!L55 -> 70.653125 | M29: ='Calc.Mth'!M55 -> 174.4825 | N29: ='Calc.Mth'!N55 -> 223.47891 | O29: ='Calc.Mth'!O55 -> 236.21951 | P29: ='Calc.Mth'!P55 -> 231.56308 | Q29: ='Calc.Mth'!Q55 -> 229.75948 | R29: ='Calc.Mth'!R55 -> 230.53157 | S29: ='Calc.Mth'!S55 -> 233.65437 | ... AI29: ='Calc.Mth'!AI55 -> 249.97796
B30: ARR | F30: $k | L30: ='Calc.Mth'!L57 -> 847.8375 | M30: ='Calc.Mth'!M57 -> 2093.79 | N30: ='Calc.Mth'!N57 -> 2681.7469 | O30: ='Calc.Mth'!O57 -> 2834.6341 | P30: ='Calc.Mth'!P57 -> 2778.757 | Q30: ='Calc.Mth'!Q57 -> 2757.1137 | R30: ='Calc.Mth'!R57 -> 2766.3789 | S30: ='Calc.Mth'!S57 -> 2803.8525 | ... AI30: ='Calc.Mth'!AI57 -> 2999.7355
B32: SaaS METRICS
B33: CAC Payback (Monthly Plan) | F33: months | M33: ='Calc.Mth'!M129/('Calc.Mth'!M61*M47) -> 9.3710816 | N33: ='Calc.Mth'!N129/('Calc.Mth'!N61*N47) -> 8.447417 | O33: ='Calc.Mth'!O129/('Calc.Mth'!O61*O47) -> 8.0650617 | P33: ='Calc.Mth'!P129/('Calc.Mth'!P61*P47) -> 7.8843403 | Q33: ='Calc.Mth'!Q129/('Calc.Mth'!Q61*Q47) -> 7.8802794 | R33: ='Calc.Mth'!R129/('Calc.Mth'!R61*R47) -> 7.8765731 | S33: ='Calc.Mth'!S129/('Calc.Mth'!S61*S47) -> 7.8732613 | T33: ='Calc.Mth'!T129/('Calc.Mth'!T61*T47) -> 7.8703577 | ... AI33: ='Calc.Mth'!AI129/('Calc.Mth'!AI61*AI47) -> 7.7419078
B34: CAC Payback (Annual Plan) | F34: months | M34: ='Calc.Mth'!M129/('Calc.Mth'!M67*M47) -> 0.85191651 | N34: ='Calc.Mth'!N129/('Calc.Mth'!N67*N47) -> 0.767947 | O34: ='Calc.Mth'!O129/('Calc.Mth'!O67*O47) -> 0.73318743 | P34: ='Calc.Mth'!P129/('Calc.Mth'!P67*P47) -> 0.71675821 | Q34: ='Calc.Mth'!Q129/('Calc.Mth'!Q67*Q47) -> 0.71638903 | R34: ='Calc.Mth'!R129/('Calc.Mth'!R67*R47) -> 0.7160521 | S34: ='Calc.Mth'!S129/('Calc.Mth'!S67*S47) -> 0.71575103 | T34: ='Calc.Mth'!T129/('Calc.Mth'!T67*T47) -> 0.71548706 | ... AI34: ='Calc.Mth'!AI129/('Calc.Mth'!AI67*AI47) -> 0.7038098
B35: Gross Dollar Retention (Monthly Plan) | F35: % | M35: =1-'Calc.Mth'!M37 -> 0.75 | N35: =1-'Calc.Mth'!N37 -> 0.75 | O35: =1-'Calc.Mth'!O37 -> 0.75 | P35: =1-'Calc.Mth'!P37 -> 0.75 | Q35: =1-'Calc.Mth'!Q37 -> 0.75 | R35: =1-'Calc.Mth'!R37 -> 0.75 | S35: =1-'Calc.Mth'!S37 -> 0.75 | T35: =1-'Calc.Mth'!T37 -> 0.75 | ... AI35: =1-'Calc.Mth'!AI37 -> 0.75
B36: Gross Dollar Retention (Annual Plan) | F36: % | M36: =1+'Calc.Mth'!M46/'Calc.Mth'!M43 -> 1 | N36: =1+'Calc.Mth'!N46/'Calc.Mth'!N43 -> 1 | O36: =1+'Calc.Mth'!O46/'Calc.Mth'!O43 -> 1 | P36: =1+'Calc.Mth'!P46/'Calc.Mth'!P43 -> 1 | Q36: =1+'Calc.Mth'!Q46/'Calc.Mth'!Q43 -> 1 | R36: =1+'Calc.Mth'!R46/'Calc.Mth'!R43 -> 1 | S36: =1+'Calc.Mth'!S46/'Calc.Mth'!S43 -> 1 | T36: =1+'Calc.Mth'!T46/'Calc.Mth'!T43 -> 1 | ... AI36: =1+'Calc.Mth'!AI46/'Calc.Mth'!AI43 -> 0.98547121
B38: Headcount | F38: # | L38: ='Calc.Mth'!L98 -> 5 | M38: ='Calc.Mth'!M98 -> 7 | N38: ='Calc.Mth'!N98 -> 10 | O38: ='Calc.Mth'!O98 -> 10 | P38: ='Calc.Mth'!P98 -> 10 | Q38: ='Calc.Mth'!Q98 -> 11 | R38: ='Calc.Mth'!R98 -> 11 | S38: ='Calc.Mth'!S98 -> 11 | ... AI38: ='Calc.Mth'!AI98 -> 20
A40: X | B40: PROFIT & LOSS
B42: Monthly Plan | F42: $k | L42: ='Calc.Mth'!L62 -> 36.8625 | M42: ='Calc.Mth'!M62 -> 86.626875 | N42: ='Calc.Mth'!N62 -> 101.83266 | O42: ='Calc.Mth'!O62 -> 96.32632 | P42: ='Calc.Mth'!P62 -> 81.877372 | Q42: ='Calc.Mth'!Q62 -> 69.595766 | R42: ='Calc.Mth'!R62 -> 59.156401 | S42: ='Calc.Mth'!S62 -> 50.282941 | ... AI42: ='Calc.Mth'!AI62 -> 3.733563
B43: Annual Plan | F43: $k | L43: ='Calc.Mth'!L70 -> 33.790625 | M43: ='Calc.Mth'!M70 -> 87.855625 | N43: ='Calc.Mth'!N70 -> 121.64625 | O43: ='Calc.Mth'!O70 -> 139.89319 | P43: ='Calc.Mth'!P70 -> 149.68571 | Q43: ='Calc.Mth'!Q70 -> 160.16371 | R43: ='Calc.Mth'!R70 -> 171.37517 | S43: ='Calc.Mth'!S70 -> 183.37143 | ... AI43: ='Calc.Mth'!AI70 -> 246.2444
B44: Total Revenue | F44: $k | L44: =SUM(L42:L43) -> 70.653125 | M44: =SUM(M42:M43) -> 174.4825 | N44: =SUM(N42:N43) -> 223.47891 | O44: =SUM(O42:O43) -> 236.21951 | P44: =SUM(P42:P43) -> 231.56308 | Q44: =SUM(Q42:Q43) -> 229.75948 | R44: =SUM(R42:R43) -> 230.53157 | S44: =SUM(S42:S43) -> 233.65437 | ... AI44: =SUM(AI42:AI43) -> 249.97796
B45: COGS | F45: $k | L45: ='Calc.Mth'!L75 -> -26.172375 | M45: ='Calc.Mth'!M75 -> -50.354175 | N45: ='Calc.Mth'!N75 -> -47.110275 | O45: ='Calc.Mth'!O75 -> -40.957924 | P45: ='Calc.Mth'!P75 -> -35.763076 | Q45: ='Calc.Mth'!Q75 -> -35.384408 | R45: ='Calc.Mth'!R75 -> -35.411545 | S45: ='Calc.Mth'!S75 -> -35.808048 | ... AI45: ='Calc.Mth'!AI75 -> -34.718391
B46: Gross Profit | F46: $k | L46: =SUM(L44:L45) -> 44.48075 | M46: =SUM(M44:M45) -> 124.12833 | N46: =SUM(N44:N45) -> 176.36863 | O46: =SUM(O44:O45) -> 195.26158 | P46: =SUM(P44:P45) -> 195.80001 | Q46: =SUM(Q44:Q45) -> 194.37507 | R46: =SUM(R44:R45) -> 195.12003 | S46: =SUM(S44:S45) -> 197.84633 | ... AI46: =SUM(AI44:AI45) -> 215.25957
B47: % margin | F47: % | L47: =L46/L44 -> 0.62956522 | M47: =M46/M44 -> 0.71140845 | N47: =N46/N44 -> 0.78919588 | O47: =O46/O44 -> 0.82661075 | P47: =P46/P44 -> 0.84555796 | Q47: =Q46/Q44 -> 0.8459937 | R47: =R46/R44 -> 0.84639178 | S47: =S46/S44 -> 0.84674779 | ... AI47: =AI46/AI44 -> 0.86111419
B48: Headcount Costs | F48: $k | L48: =-'Calc.Mth'!L97 -> -63.25 | M48: =-'Calc.Mth'!M97 -> -89.125 | N48: =-'Calc.Mth'!N97 -> -132.25 | O48: =-'Calc.Mth'!O97 -> -132.25 | P48: =-'Calc.Mth'!P97 -> -132.25 | Q48: =-'Calc.Mth'!Q97 -> -149.5 | R48: =-'Calc.Mth'!R97 -> -149.5 | S48: =-'Calc.Mth'!S97 -> -149.5 | ... AI48: =-'Calc.Mth'!AI97 -> -310.5
B49: G&A | F49: $k | L49: =-'Calc.Mth'!L126 -> -20 | M49: =-'Calc.Mth'!M126 -> -20 | N49: =-'Calc.Mth'!N126 -> -21.4 | O49: =-'Calc.Mth'!O126 -> -21.4 | P49: =-'Calc.Mth'!P126 -> -21.4 | Q49: =-'Calc.Mth'!Q126 -> -22.898 | R49: =-'Calc.Mth'!R126 -> -22.898 | S49: =-'Calc.Mth'!S126 -> -22.898 | ... AI49: =-'Calc.Mth'!AI126 -> -34.363724
B50: S&M | F50: $k | L50: =-'Calc.Mth'!L128 -> -983 | M50: =-'Calc.Mth'!M128 -> -589.8 | N50: =-'Calc.Mth'!N128 -> -393.2 | O50: =-'Calc.Mth'!O128 -> -138.23438 | P50: =-'Calc.Mth'!P128 -> -132.63742 | Q50: =-'Calc.Mth'!Q128 -> -128.93968 | R50: =-'Calc.Mth'!R128 -> -126.93045 | S50: =-'Calc.Mth'!S128 -> -126.43583 | ... AI50: =-'Calc.Mth'!AI128 -> -202.06016
B51: Facilities Expense | F51: $k | L51: =-'Calc.Mth'!L135 -> -14 | M51: =-'Calc.Mth'!M135 -> -14 | N51: =-'Calc.Mth'!N135 -> -14 | O51: =-'Calc.Mth'!O135 -> -14 | P51: =-'Calc.Mth'!P135 -> -14 | Q51: =-'Calc.Mth'!Q135 -> -14 | R51: =-'Calc.Mth'!R135 -> -14 | S51: =-'Calc.Mth'!S135 -> -14 | ... AI51: =-'Calc.Mth'!AI135 -> -28
B52: Miscellaneous | F52: $k | L52: =-'Calc.Mth'!L137 -> -3.5326562 | M52: =-'Calc.Mth'!M137 -> -8.724125 | N52: =-'Calc.Mth'!N137 -> -11.173945 | O52: =-'Calc.Mth'!O137 -> -11.810975 | P52: =-'Calc.Mth'!P137 -> -11.578154 | Q52: =-'Calc.Mth'!Q137 -> -11.487974 | R52: =-'Calc.Mth'!R137 -> -11.526579 | S52: =-'Calc.Mth'!S137 -> -11.682719 | ... AI52: =-'Calc.Mth'!AI137 -> -12.498898
B53: EBITDA | F53: $k | L53: =SUM(L48:L52,L46) -> -1039.3019 | M53: =SUM(M48:M52,M46) -> -597.5208 | N53: =SUM(N48:N52,N46) -> -395.65531 | O53: =SUM(O48:O52,O46) -> -122.43377 | P53: =SUM(P48:P52,P46) -> -116.06557 | Q53: =SUM(Q48:Q52,Q46) -> -132.45058 | R53: =SUM(R48:R52,R46) -> -129.73501 | S53: =SUM(S48:S52,S46) -> -126.67022 | ... AI53: =SUM(AI48:AI52,AI46) -> -372.16321
B54: % margin | F54: % | L54: =L53/L44 -> -14.709921 | M54: =M53/M44 -> -3.4245314 | N54: =N53/N44 -> -1.770437 | O54: =O53/O44 -> -0.51830506 | P54: =P53/P44 -> -0.50122655 | Q54: =Q53/Q44 -> -0.57647496 | R54: =R53/R44 -> -0.56276459 | S54: =S53/S44 -> -0.54212649 | ... AI54: =AI53/AI44 -> -1.4887841
A56: X | B56: CASH FLOW STATEMENT
B58: EBITDA | F58: $k | L58: =L53 -> -1039.3019 | M58: =M53 -> -597.5208 | N58: =N53 -> -395.65531 | O58: =O53 -> -122.43377 | P58: =P53 -> -116.06557 | Q58: =Q53 -> -132.45058 | R58: =R53 -> -129.73501 | S58: =S53 -> -126.67022 | ... AI58: =AI53 -> -372.16321
B59: Less: Change in NWC | F59: $k | L59: =-'Calc.Mth'!L147 -> 108.67031 | M59: =-'Calc.Mth'!M147 -> 159.69811 | N59: =-'Calc.Mth'!N147 -> 69.997006 | O59: =-'Calc.Mth'!O147 -> 19.290318 | P59: =-'Calc.Mth'!P147 -> -7.0502101 | Q59: =-'Calc.Mth'!Q147 -> -8.2450353 | R59: =-'Calc.Mth'!R147 -> 1.1504847 | S59: =-'Calc.Mth'!S147 -> 4.6532312 | ... AI59: =-'Calc.Mth'!AI147 -> 8.1219725
B60: Less: Cash Tax Paid | F60: $k
B61: Change in Deferred Revenues | F61: $k | L61: =L81-K81 -> 371.69688 | M61: =M81-L81 -> 560.92438 | N61: =N81-M81 -> 283.84125 | O61: =O81-N81 -> 79.070062 | P61: =P81-O81 -> -32.175433 | Q61: =Q81-P81 -> -34.427713 | R61: =R81-Q81 -> -36.837653 | S61: =S81-R81 -> -39.416289 | ... AI61: =AI81-AH81 -> 74.041854
B62: CASH ACCRUAL / BURN | F62: $k | L62: =SUM(L58:L61) -> -558.93472 | M62: =SUM(M58:M61) -> 123.10169 | N62: =SUM(N58:N61) -> -41.817058 | O62: =SUM(O58:O61) -> -24.073386 | P62: =SUM(P58:P61) -> -155.29121 | Q62: =SUM(Q58:Q61) -> -175.12333 | R62: =SUM(R58:R61) -> -165.42217 | S62: =SUM(S58:S61) -> -161.43328 | ... AI62: =SUM(AI58:AI61) -> -289.99939
B64: CASH AND CASH EQUIVALENTS
B65: Opening | F65: $k | L65: =K68 -> 3000 | M65: =L68 -> 2441.0653 | N65: =M68 -> 2564.167 | O65: =N68 -> 2522.3499 | P65: =O68 -> 2498.2765 | Q65: =P68 -> 2342.9853 | R65: =Q68 -> 2167.862 | S65: =R68 -> 2002.4398 | ... AI65: =AH68 -> 1789.9994
B66: Accrual / Burn | F66: $k | K66: =SUM(L66:AI66) -> -4759.9201 | L66: =L62 -> -558.93472 | M66: =M62 -> 123.10169 | N66: =N62 -> -41.817058 | O66: =O62 -> -24.073386 | P66: =P62 -> -155.29121 | Q66: =Q62 -> -175.12333 | R66: =R62 -> -165.42217 | S66: =S62 -> -161.43328 | ... AI66: =AI62 -> -289.99939
B67: Add: Fundraise | F67: $k | H67: =Sum!E21 -> 45626 | I67: =Sum!E28 -> 3259.9201 | L67: =$I67*(L$7=$H67)*1 -> 0 | M67: =$I67*(M$7=$H67)*1 -> 0 | N67: =$I67*(N$7=$H67)*1 -> 0 | O67: =$I67*(O$7=$H67)*1 -> 0 | P67: =$I67*(P$7=$H67)*1 -> 0 | Q67: =$I67*(Q$7=$H67)*1 -> 0 | R67: =$I67*(R$7=$H67)*1 -> 0 | S67: =$I67*(S$7=$H67)*1 -> 0 | ... AI67: =$I67*(AI$7=$H67)*1 -> 0
B68: CLOSING | F68: $k | K68: 3000 | L68: =SUM(L65:L67) -> 2441.0653 | M68: =SUM(M65:M67) -> 2564.167 | N68: =SUM(N65:N67) -> 2522.3499 | O68: =SUM(O65:O67) -> 2498.2765 | P68: =SUM(P65:P67) -> 2342.9853 | Q68: =SUM(Q65:Q67) -> 2167.862 | R68: =SUM(R65:R67) -> 2002.4398 | S68: =SUM(S65:S67) -> 1841.0065 | ... AI68: =SUM(AI65:AI67) -> 1500
B69: Cumulative Burn | F69: $k | K69: =COUNTIF(L69:AI69,"<"&K68) -> 16 | L69: =-SUM($L66:L66) -> 558.93472 | M69: =-SUM($L66:M66) -> 435.83303 | N69: =-SUM($L66:N66) -> 477.65009 | O69: =-SUM($L66:O66) -> 501.72347 | P69: =-SUM($L66:P66) -> 657.01468 | Q69: =-SUM($L66:Q66) -> 832.13802 | R69: =-SUM($L66:R66) -> 997.56019 | S69: =-SUM($L66:S66) -> 1158.9935 | ... AI69: =-SUM($L66:AI66) -> 4759.9201
A71: X | B71: BALANCE SHEET
B73: ASSETS
B74: Cash | F74: $k | L74: =L68 -> 2441.0653 | M74: =M68 -> 2564.167 | N74: =N68 -> 2522.3499 | O74: =O68 -> 2498.2765 | P74: =P68 -> 2342.9853 | Q74: =Q68 -> 2167.862 | R74: =R68 -> 2002.4398 | S74: =S68 -> 1841.0065 | ... AI74: =AI68 -> 1500
B75: Receivables | F75: $k | L75: ='Calc.Mth'!L142 -> 1.5485616 | M75: ='Calc.Mth'!M142 -> 3.824274 | N75: ='Calc.Mth'!N142 -> 4.8981678 | O75: ='Calc.Mth'!O142 -> 5.1774139 | P75: ='Calc.Mth'!P142 -> 5.0753552 | Q75: ='Calc.Mth'!Q142 -> 5.0358241 | R75: ='Calc.Mth'!R142 -> 5.0527468 | S75: ='Calc.Mth'!S142 -> 5.1211917 | ... AI75: ='Calc.Mth'!AI142 -> 5.478969
B76: Other | F76: $k
B77: TOTAL | F77: $k | L77: =SUM(L74:L76) -> 2442.6138 | M77: =SUM(M74:M76) -> 2567.9912 | N77: =SUM(N74:N76) -> 2527.2481 | O77: =SUM(O74:O76) -> 2503.4539 | P77: =SUM(P74:P76) -> 2348.0607 | Q77: =SUM(Q74:Q76) -> 2172.8978 | R77: =SUM(R74:R76) -> 2007.4926 | S77: =SUM(S74:S76) -> 1846.1277 | ... AI77: =SUM(AI74:AI76) -> 1505.479
B79: LIABILITIES
B80: Payables | F80: $k | L80: ='Calc.Mth'!L143 -> 42.391875 | M80: ='Calc.Mth'!M143 -> 104.6895 | N80: ='Calc.Mth'!N143 -> 134.08734 | O80: ='Calc.Mth'!O143 -> 141.7317 | P80: ='Calc.Mth'!P143 -> 138.93785 | Q80: ='Calc.Mth'!Q143 -> 137.85569 | R80: ='Calc.Mth'!R143 -> 138.31894 | S80: ='Calc.Mth'!S143 -> 140.19262 | ... AI80: ='Calc.Mth'!AI143 -> 149.98678
B81: Deferred Revenue | F81: $k | L81: ='Calc.Mth'!L152 -> 371.69688 | M81: ='Calc.Mth'!M152 -> 932.62125 | N81: ='Calc.Mth'!N152 -> 1216.4625 | O81: ='Calc.Mth'!O152 -> 1295.5326 | P81: ='Calc.Mth'!P152 -> 1263.3571 | Q81: ='Calc.Mth'!Q152 -> 1228.9294 | R81: ='Calc.Mth'!R152 -> 1192.0918 | S81: ='Calc.Mth'!S152 -> 1152.6755 | ... AI81: ='Calc.Mth'!AI152 -> 1487.7626
B82: Other Current Liabilities | F82: $k | L82: ='Calc.Mth'!L144 -> 67.827 | M82: ='Calc.Mth'!M144 -> 167.5032 | N82: ='Calc.Mth'!N144 -> 209.17626 | O82: ='Calc.Mth'!O144 -> 221.10146 | P82: ='Calc.Mth'!P144 -> 216.74305 | Q82: ='Calc.Mth'!Q144 -> 209.54064 | R82: ='Calc.Mth'!R144 -> 210.24479 | S82: ='Calc.Mth'!S144 -> 213.09279 | ... AI82: ='Calc.Mth'!AI144 -> 191.98307
B83: TOTAL | F83: $k | L83: =SUM(L80:L82) -> 481.91575 | M83: =SUM(M80:M82) -> 1204.814 | N83: =SUM(N80:N82) -> 1559.7261 | O83: =SUM(O80:O82) -> 1658.3657 | P83: =SUM(P80:P82) -> 1619.038 | Q83: =SUM(Q80:Q82) -> 1576.3257 | R83: =SUM(R80:R82) -> 1540.6555 | S83: =SUM(S80:S82) -> 1505.9609 | ... AI83: =SUM(AI80:AI82) -> 1829.7325
B85: NET ASSETS | F85: $k | L85: =SUM(L77,-L83) -> 1960.6981 | M85: =SUM(M77,-M83) -> 1363.1773 | N85: =SUM(N77,-N83) -> 967.52198 | O85: =SUM(O77,-O83) -> 845.08821 | P85: =SUM(P77,-P83) -> 729.02265 | Q85: =SUM(Q77,-Q83) -> 596.57206 | R85: =SUM(R77,-R83) -> 466.83706 | S85: =SUM(S77,-S83) -> 340.16683 | ... AI85: =SUM(AI77,-AI83) -> -324.2535
B87: EQUITY
B88: Contributed Equity | F88: $k | L88: =K68 -> 3000 | M88: =L88+M67 -> 3000 | N88: =M88+N67 -> 3000 | O88: =N88+O67 -> 3000 | P88: =O88+P67 -> 3000 | Q88: =P88+Q67 -> 3000 | R88: =Q88+R67 -> 3000 | S88: =R88+S67 -> 3000 | T88: =S88+T67 -> 3000 | ... AI88: =AH88+AI67 -> 6259.9201
B89: Retained Profits / (Accumulated Losses) | F89: $k | L89: =L58+K89 -> -1039.3019 | M89: =M58+L89 -> -1636.8227 | N89: =N58+M89 -> -2032.478 | O89: =O58+N89 -> -2154.9118 | P89: =P58+O89 -> -2270.9774 | Q89: =Q58+P89 -> -2403.4279 | R89: =R58+Q89 -> -2533.1629 | S89: =S58+R89 -> -2659.8332 | ... AI89: =AI58+AH89 -> -6584.1736
B90: TOTAL | F90: $k | L90: =SUM(L88:L89) -> 1960.6981 | M90: =SUM(M88:M89) -> 1363.1773 | N90: =SUM(N88:N89) -> 967.52198 | O90: =SUM(O88:O89) -> 845.08821 | P90: =SUM(P88:P89) -> 729.02265 | Q90: =SUM(Q88:Q89) -> 596.57206 | R90: =SUM(R88:R89) -> 466.83706 | S90: =SUM(S88:S89) -> 340.16683 | ... AI90: =SUM(AI88:AI89) -> -324.2535
B91: CHECK | F91: $k | K91: =SUM(L91:AI91) -> 0 | L91: =ROUND(L90-L85,5) -> 0 | M91: =ROUND(M90-M85,5) -> 0 | N91: =ROUND(N90-N85,5) -> 0 | O91: =ROUND(O90-O85,5) -> 0 | P91: =ROUND(P90-P85,5) -> 0 | Q91: =ROUND(Q90-Q85,5) -> 0 | R91: =ROUND(R90-R85,5) -> 0 | S91: =ROUND(S90-S85,5) -> 0 | ... AI91: =ROUND(AI90-AI85,5) -> 0
A93: X | B93: END OF SHEET

Sheet Fin.Qtr
B3: ='Calc.Mth'!B3 -> Project Eagle
B4: Summary Financials | Quarterly | G4: Runway | H4: Fundraise | I4: Fund. Date | J4: End. ARR | K4: Deferred Rev.
B5: =Ctrl!$B$5 -> CASE 1: BASE CASE | G5: =Sum!$E$19 -> 16 | H5: =Sum!$E$28 -> 3259.9201 | I5: =Sum!$E$21 -> 45626 | J5: ='Calc.Mth'!$AI$57 -> 2999.7355 | K5: =Fin.Mth!$AI$81 -> 1487.7626 | L5: QUARTERLY | U5: ANNUAL
B7: ='Calc.Mth'!B7 -> Period End | L7: 45382 | M7: =EOMONTH(M8,2) -> 45473 | N7: =EOMONTH(N8,2) -> 45565 | O7: =EOMONTH(O8,2) -> 45657 | P7: =EOMONTH(P8,2) -> 45747 | Q7: =EOMONTH(Q8,2) -> 45838 | R7: =EOMONTH(R8,2) -> 45930 | S7: =EOMONTH(S8,2) -> 46022 | U7: =O7 -> 45657 | V7: =S7 -> 46022
B8: ='Calc.Mth'!B8 -> Period Start | L8: ='Calc.Mth'!L8 -> 45292 | M8: =L7+1 -> 45383 | N8: =M7+1 -> 45474 | O8: =N7+1 -> 45566 | P8: =O7+1 -> 45658 | Q8: =P7+1 -> 45748 | R8: =Q7+1 -> 45839 | S8: =R7+1 -> 45931 | U8: =L8 -> 45292 | V8: =U7+1 -> 45658
B9: ='Calc.Mth'!B9 -> Calendar Year | L9: =YEAR(L7) -> 2024 | M9: =YEAR(M7) -> 2024 | N9: =YEAR(N7) -> 2024 | O9: =YEAR(O7) -> 2024 | P9: =YEAR(P7) -> 2025 | Q9: =YEAR(Q7) -> 2025 | R9: =YEAR(R7) -> 2025 | S9: =YEAR(S7) -> 2025 | U9: =YEAR(U7) -> 2024 | V9: =YEAR(V7) -> 2025
B10: ='Calc.Mth'!B10 -> Period Number | L10: ='Calc.Mth'!L10 -> 1 | M10: ='Calc.Mth'!M10 -> 2 | N10: ='Calc.Mth'!N10 -> 3 | O10: ='Calc.Mth'!O10 -> 4 | P10: ='Calc.Mth'!P10 -> 5 | Q10: ='Calc.Mth'!Q10 -> 6 | R10: ='Calc.Mth'!R10 -> 7 | S10: ='Calc.Mth'!S10 -> 8 | U10: ='Calc.Mth'!U10 -> 10 | V10: ='Calc.Mth'!V10 -> 11
B11: ='Calc.Mth'!B11 -> Days in Period | F11: ='Calc.Mth'!F11 -> Units | H11: ='Calc.Mth'!H11 -> Input I | I11: ='Calc.Mth'!I11 -> Input II | J11: ='Calc.Mth'!J11 -> Input III | K11: ='Calc.Mth'!K11 -> Total / Out | L11: =L7-L8+1 -> 91 | M11: =M7-M8+1 -> 91 | N11: =N7-N8+1 -> 92 | O11: =O7-O8+1 -> 92 | P11: =P7-P8+1 -> 90 | Q11: =Q7-Q8+1 -> 91 | R11: =R7-R8+1 -> 92 | S11: =S7-S8+1 -> 92 | U11: =U7-U8+1 -> 366 | V11: =V7-V8+1 -> 365
A15: X | B15: OPERATING METRICS
B17: # CUSTOMERS
B18: Monthly Plan | F18: # | L18: =SUMIFS(Fin.Mth!$L18:$AI18,Fin.Mth!$L$7:$AI$7,"="&Fin.Qtr!L$7) -> 3471.2188 | M18: =SUMIFS(Fin.Mth!$L18:$AI18,Fin.Mth!$L$7:$AI$7,"="&Fin.Qtr!M$7) -> 2131.7622 | N18: =SUMIFS(Fin.Mth!$L18:$AI18,Fin.Mth!$L$7:$AI$7,"="&Fin.Qtr!N$7) -> 1309.1685 | O18: =SUMIFS(Fin.Mth!$L18:$AI18,Fin.Mth!$L$7:$AI$7,"="&Fin.Qtr!O$7) -> 803.99309 | P18: =SUMIFS(Fin.Mth!$L18:$AI18,Fin.Mth!$L$7:$AI$7,"="&Fin.Qtr!P$7) -> 493.75225 | Q18: =SUMIFS(Fin.Mth!$L18:$AI18,Fin.Mth!$L$7:$AI$7,"="&Fin.Qtr!Q$7) -> 303.2256 | R18: =SUMIFS(Fin.Mth!$L18:$AI18,Fin.Mth!$L$7:$AI$7,"="&Fin.Qtr!R$7) -> 186.21842 | S18: =SUMIFS(Fin.Mth!$L18:$AI18,Fin.Mth!$L$7:$AI$7,"="&Fin.Qtr!S$7) -> 114.36139 | U18: =AVERAGE(L18:O18) -> 1929.0356 | V18: =AVERAGE(P18:S18) -> 274.38942
B19: Annual Plan | F19: # | L19: =SUMIFS(Fin.Mth!$L19:$AI19,Fin.Mth!$L$7:$AI$7,"="&Fin.Qtr!L$7) -> 4915 | M19: =SUMIFS(Fin.Mth!$L19:$AI19,Fin.Mth!$L$7:$AI$7,"="&Fin.Qtr!M$7) -> 6021.0863 | N19: =SUMIFS(Fin.Mth!$L19:$AI19,Fin.Mth!$L$7:$AI$7,"="&Fin.Qtr!N$7) -> 7376.0897 | O19: =SUMIFS(Fin.Mth!$L19:$AI19,Fin.Mth!$L$7:$AI$7,"="&Fin.Qtr!O$7) -> 9036.027 | P19: =SUMIFS(Fin.Mth!$L19:$AI19,Fin.Mth!$L$7:$AI$7,"="&Fin.Qtr!P$7) -> 9188.5143 | Q19: =SUMIFS(Fin.Mth!$L19:$AI19,Fin.Mth!$L$7:$AI$7,"="&Fin.Qtr!Q$7) -> 10842.727 | R19: =SUMIFS(Fin.Mth!$L19:$AI19,Fin.Mth!$L$7:$AI$7,"="&Fin.Qtr!R$7) -> 12776.132 | S19: =SUMIFS(Fin.Mth!$L19:$AI19,Fin.Mth!$L$7:$AI$7,"="&Fin.Qtr!S$7) -> 15030.612 | U19: =AVERAGE(L19:O19) -> 6837.0508 | V19: =AVERAGE(P19:S19) -> 11959.496
B20: TOTAL | F20: # | L20: =SUMIFS(Fin.Mth!$L20:$AI20,Fin.Mth!$L$7:$AI$7,"="&Fin.Qtr!L$7) -> 8386.2188 | M20: =SUMIFS(Fin.Mth!$L20:$AI20,Fin.Mth!$L$7:$AI$7,"="&Fin.Qtr!M$7) -> 8152.8486 | N20: =SUMIFS(Fin.Mth!$L20:$AI20,Fin.Mth!$L$7:$AI$7,"="&Fin.Qtr!N$7) -> 8685.2581 | O20: =SUMIFS(Fin.Mth!$L20:$AI20,Fin.Mth!$L$7:$AI$7,"="&Fin.Qtr!O$7) -> 9840.0201 | P20: =SUMIFS(Fin.Mth!$L20:$AI20,Fin.Mth!$L$7:$AI$7,"="&Fin.Qtr!P$7) -> 9682.2666 | Q20: =SUMIFS(Fin.Mth!$L20:$AI20,Fin.Mth!$L$7:$AI$7,"="&Fin.Qtr!Q$7) -> 11145.953 | R20: =SUMIFS(Fin.Mth!$L20:$AI20,Fin.Mth!$L$7:$AI$7,"="&Fin.Qtr!R$7) -> 12962.35 | S20: =SUMIFS(Fin.Mth!$L20:$AI20,Fin.Mth!$L$7:$AI$7,"="&Fin.Qtr!S$7) -> 15144.973 | U20: =AVERAGE(L20:O20) -> 8766.0864 | V20: =AVERAGE(P20:S20) -> 12233.886
B22: PRICING
B23: Monthly | F23: $k | L23: =AVERAGEIFS(Fin.Mth!$L23:$AI23,Fin.Mth!$L$7:$AI$7,">="&Fin.Qtr!L$8,Fin.Mth!$L$7:$AI$7,"<="&Fin.Qtr!L$7) -> 30 | M23: =AVERAGEIFS(Fin.Mth!$L23:$AI23,Fin.Mth!$L$7:$AI$7,">="&Fin.Qtr!M$8,Fin.Mth!$L$7:$AI$7,"<="&Fin.Qtr!M$7) -> 30 | N23: =AVERAGEIFS(Fin.Mth!$L23:$AI23,Fin.Mth!$L$7:$AI$7,">="&Fin.Qtr!N$8,Fin.Mth!$L$7:$AI$7,"<="&Fin.Qtr!N$7) -> 30 | O23: =AVERAGEIFS(Fin.Mth!$L23:$AI23,Fin.Mth!$L$7:$AI$7,">="&Fin.Qtr!O$8,Fin.Mth!$L$7:$AI$7,"<="&Fin.Qtr!O$7) -> 30 | P23: =AVERAGEIFS(Fin.Mth!$L23:$AI23,Fin.Mth!$L$7:$AI$7,">="&Fin.Qtr!P$8,Fin.Mth!$L$7:$AI$7,"<="&Fin.Qtr!P$7) -> 30 | Q23: =AVERAGEIFS(Fin.Mth!$L23:$AI23,Fin.Mth!$L$7:$AI$7,">="&Fin.Qtr!Q$8,Fin.Mth!$L$7:$AI$7,"<="&Fin.Qtr!Q$7) -> 30 | R23: =AVERAGEIFS(Fin.Mth!$L23:$AI23,Fin.Mth!$L$7:$AI$7,">="&Fin.Qtr!R$8,Fin.Mth!$L$7:$AI$7,"<="&Fin.Qtr!R$7) -> 30 | S23: =AVERAGEIFS(Fin.Mth!$L23:$AI23,Fin.Mth!$L$7:$AI$7,">="&Fin.Qtr!S$8,Fin.Mth!$L$7:$AI$7,"<="&Fin.Qtr!S$7) -> 30 | U23: =AVERAGE(L23:O23) -> 30 | V23: =AVERAGE(P23:S23) -> 30
B24: Annual | F24: $k | L24: =AVERAGEIFS(Fin.Mth!$L24:$AI24,Fin.Mth!$L$7:$AI$7,">="&Fin.Qtr!L$8,Fin.Mth!$L$7:$AI$7,"<="&Fin.Qtr!L$7) -> 330 | M24: =AVERAGEIFS(Fin.Mth!$L24:$AI24,Fin.Mth!$L$7:$AI$7,">="&Fin.Qtr!M$8,Fin.Mth!$L$7:$AI$7,"<="&Fin.Qtr!M$7) -> 330 | N24: =AVERAGEIFS(Fin.Mth!$L24:$AI24,Fin.Mth!$L$7:$AI$7,">="&Fin.Qtr!N$8,Fin.Mth!$L$7:$AI$7,"<="&Fin.Qtr!N$7) -> 330 | O24: =AVERAGEIFS(Fin.Mth!$L24:$AI24,Fin.Mth!$L$7:$AI$7,">="&Fin.Qtr!O$8,Fin.Mth!$L$7:$AI$7,"<="&Fin.Qtr!O$7) -> 330 | P24: =AVERAGEIFS(Fin.Mth!$L24:$AI24,Fin.Mth!$L$7:$AI$7,">="&Fin.Qtr!P$8,Fin.Mth!$L$7:$AI$7,"<="&Fin.Qtr!P$7) -> 330 | Q24: =AVERAGEIFS(Fin.Mth!$L24:$AI24,Fin.Mth!$L$7:$AI$7,">="&Fin.Qtr!Q$8,Fin.Mth!$L$7:$AI$7,"<="&Fin.Qtr!Q$7) -> 330 | R24: =AVERAGEIFS(Fin.Mth!$L24:$AI24,Fin.Mth!$L$7:$AI$7,">="&Fin.Qtr!R$8,Fin.Mth!$L$7:$AI$7,"<="&Fin.Qtr!R$7) -> 330 | S24: =AVERAGEIFS(Fin.Mth!$L24:$AI24,Fin.Mth!$L$7:$AI$7,">="&Fin.Qtr!S$8,Fin.Mth!$L$7:$AI$7,"<="&Fin.Qtr!S$7) -> 330 | U24: =AVERAGE(L24:O24) -> 330 | V24: =AVERAGE(P24:S24) -> 330
B25: TOTAL | F25: $k | L25: =AVERAGEIFS(Fin.Mth!$L25:$AI25,Fin.Mth!$L$7:$AI$7,">="&Fin.Qtr!L$8,Fin.Mth!$L$7:$AI$7,"<="&Fin.Qtr!L$7) -> 21.697049 | M25: =AVERAGEIFS(Fin.Mth!$L25:$AI25,Fin.Mth!$L$7:$AI$7,">="&Fin.Qtr!M$8,Fin.Mth!$L$7:$AI$7,"<="&Fin.Qtr!M$7) -> 28.473223 | N25: =AVERAGEIFS(Fin.Mth!$L25:$AI25,Fin.Mth!$L$7:$AI$7,">="&Fin.Qtr!N$8,Fin.Mth!$L$7:$AI$7,"<="&Fin.Qtr!N$7) -> 27.714799 | O25: =AVERAGEIFS(Fin.Mth!$L25:$AI25,Fin.Mth!$L$7:$AI$7,">="&Fin.Qtr!O$8,Fin.Mth!$L$7:$AI$7,"<="&Fin.Qtr!O$7) -> 27.217225 | P25: =AVERAGEIFS(Fin.Mth!$L25:$AI25,Fin.Mth!$L$7:$AI$7,">="&Fin.Qtr!P$8,Fin.Mth!$L$7:$AI$7,"<="&Fin.Qtr!P$7) -> 22.245689 | Q25: =AVERAGEIFS(Fin.Mth!$L25:$AI25,Fin.Mth!$L$7:$AI$7,">="&Fin.Qtr!Q$8,Fin.Mth!$L$7:$AI$7,"<="&Fin.Qtr!Q$7) -> 17.802969 | R25: =AVERAGEIFS(Fin.Mth!$L25:$AI25,Fin.Mth!$L$7:$AI$7,">="&Fin.Qtr!R$8,Fin.Mth!$L$7:$AI$7,"<="&Fin.Qtr!R$7) -> 17.198682 | S25: =AVERAGEIFS(Fin.Mth!$L25:$AI25,Fin.Mth!$L$7:$AI$7,">="&Fin.Qtr!S$8,Fin.Mth!$L$7:$AI$7,"<="&Fin.Qtr!S$7) -> 16.673421 | U25: =AVERAGE(L25:O25) -> 26.275574 | V25: =AVERAGE(P25:S25) -> 18.48019
B27: REVENUE METRICS
B28: Bookings | F28: $k | L28: =SUMIFS(Fin.Mth!$L28:$AI28,Fin.Mth!$L$7:$AI$7,">="&Fin.Qtr!L$8,Fin.Mth!$L$7:$AI$7,"<="&Fin.Qtr!L$7) -> 1685.077 | M28: =SUMIFS(Fin.Mth!$L28:$AI28,Fin.Mth!$L$7:$AI$7,">="&Fin.Qtr!M$8,Fin.Mth!$L$7:$AI$7,"<="&Fin.Qtr!M$7) -> 710.00898 | N28: =SUMIFS(Fin.Mth!$L28:$AI28,Fin.Mth!$L$7:$AI$7,">="&Fin.Qtr!N$8,Fin.Mth!$L$7:$AI$7,"<="&Fin.Qtr!N$7) -> 584.70451 | O28: =SUMIFS(Fin.Mth!$L28:$AI28,Fin.Mth!$L$7:$AI$7,">="&Fin.Qtr!O$8,Fin.Mth!$L$7:$AI$7,"<="&Fin.Qtr!O$7) -> 623.31876 | P28: =SUMIFS(Fin.Mth!$L28:$AI28,Fin.Mth!$L$7:$AI$7,">="&Fin.Qtr!P$8,Fin.Mth!$L$7:$AI$7,"<="&Fin.Qtr!P$7) -> 670.03803 | Q28: =SUMIFS(Fin.Mth!$L28:$AI28,Fin.Mth!$L$7:$AI$7,">="&Fin.Qtr!Q$8,Fin.Mth!$L$7:$AI$7,"<="&Fin.Qtr!Q$7) -> 693.26005 | R28: =SUMIFS(Fin.Mth!$L28:$AI28,Fin.Mth!$L$7:$AI$7,">="&Fin.Qtr!R$8,Fin.Mth!$L$7:$AI$7,"<="&Fin.Qtr!R$7) -> 794.96787 | S28: =SUMIFS(Fin.Mth!$L28:$AI28,Fin.Mth!$L$7:$AI$7,">="&Fin.Qtr!S$8,Fin.Mth!$L$7:$AI$7,"<="&Fin.Qtr!S$7) -> 924.24868 | U28: =AVERAGE(L28:O28) -> 900.77732 | V28: =AVERAGE(P28:S28) -> 770.62866
B29: Revenue | F29: $k | L29: =SUMIFS(Fin.Mth!$L29:$AI29,Fin.Mth!$L$7:$AI$7,">="&Fin.Qtr!L$8,Fin.Mth!$L$7:$AI$7,"<="&Fin.Qtr!L$7) -> 468.61453 | M29: =SUMIFS(Fin.Mth!$L29:$AI29,Fin.Mth!$L$7:$AI$7,">="&Fin.Qtr!M$8,Fin.Mth!$L$7:$AI$7,"<="&Fin.Qtr!M$7) -> 697.54207 | N29: =SUMIFS(Fin.Mth!$L29:$AI29,Fin.Mth!$L$7:$AI$7,">="&Fin.Qtr!N$8,Fin.Mth!$L$7:$AI$7,"<="&Fin.Qtr!N$7) -> 703.13388 | O29: =SUMIFS(Fin.Mth!$L29:$AI29,Fin.Mth!$L$7:$AI$7,">="&Fin.Qtr!O$8,Fin.Mth!$L$7:$AI$7,"<="&Fin.Qtr!O$7) -> 768.39983 | P29: =SUMIFS(Fin.Mth!$L29:$AI29,Fin.Mth!$L$7:$AI$7,">="&Fin.Qtr!P$8,Fin.Mth!$L$7:$AI$7,"<="&Fin.Qtr!P$7) -> 637.06934 | Q29: =SUMIFS(Fin.Mth!$L29:$AI29,Fin.Mth!$L$7:$AI$7,">="&Fin.Qtr!Q$8,Fin.Mth!$L$7:$AI$7,"<="&Fin.Qtr!Q$7) -> 567.61636 | R29: =SUMIFS(Fin.Mth!$L29:$AI29,Fin.Mth!$L$7:$AI$7,">="&Fin.Qtr!R$8,Fin.Mth!$L$7:$AI$7,"<="&Fin.Qtr!R$7) -> 635.97525 | S29: =SUMIFS(Fin.Mth!$L29:$AI29,Fin.Mth!$L$7:$AI$7,">="&Fin.Qtr!S$8,Fin.Mth!$L$7:$AI$7,"<="&Fin.Qtr!S$7) -> 719.51004 | U29: =AVERAGE(L29:O29) -> 659.42258 | V29: =AVERAGE(P29:S29) -> 640.04275
B30: ARR | F30: $k | L30: =SUMIFS(Fin.Mth!$L30:$AI30,Fin.Mth!$L$7:$AI$7,"="&Fin.Qtr!L$7) -> 2681.7469 | M30: =SUMIFS(Fin.Mth!$L30:$AI30,Fin.Mth!$L$7:$AI$7,"="&Fin.Qtr!M$7) -> 2757.1137 | N30: =SUMIFS(Fin.Mth!$L30:$AI30,Fin.Mth!$L$7:$AI$7,"="&Fin.Qtr!N$7) -> 2867.3752 | O30: =SUMIFS(Fin.Mth!$L30:$AI30,Fin.Mth!$L$7:$AI$7,"="&Fin.Qtr!O$7) -> 3199.3266 | P30: =SUMIFS(Fin.Mth!$L30:$AI30,Fin.Mth!$L$7:$AI$7,"="&Fin.Qtr!P$7) -> 2230.6737 | Q30: =SUMIFS(Fin.Mth!$L30:$AI30,Fin.Mth!$L$7:$AI$7,"="&Fin.Qtr!Q$7) -> 2351.8352 | R30: =SUMIFS(Fin.Mth!$L30:$AI30,Fin.Mth!$L$7:$AI$7,"="&Fin.Qtr!R$7) -> 2646.7928 | S30: =SUMIFS(Fin.Mth!$L30:$AI30,Fin.Mth!$L$7:$AI$7,"="&Fin.Qtr!S$7) -> 2999.7355 | U30: =AVERAGE(L30:O30) -> 2876.3906 | V30: =AVERAGE(P30:S30) -> 2557.2593
B32: SaaS METRICS
B33: CAC Payback (Monthly) | F33: months | M33: =AVERAGEIFS(Fin.Mth!$L33:$AI33,Fin.Mth!$L$7:$AI$7,">="&Fin.Qtr!M$8,Fin.Mth!$L$7:$AI$7,"<="&Fin.Qtr!M$7) -> 7.9432271 | N33: =AVERAGEIFS(Fin.Mth!$L33:$AI33,Fin.Mth!$L$7:$AI$7,">="&Fin.Qtr!N$8,Fin.Mth!$L$7:$AI$7,"<="&Fin.Qtr!N$7) -> 7.8733974 | O33: =AVERAGEIFS(Fin.Mth!$L33:$AI33,Fin.Mth!$L$7:$AI$7,">="&Fin.Qtr!O$8,Fin.Mth!$L$7:$AI$7,"<="&Fin.Qtr!O$7) -> 7.8658393 | P33: =AVERAGEIFS(Fin.Mth!$L33:$AI33,Fin.Mth!$L$7:$AI$7,">="&Fin.Qtr!P$8,Fin.Mth!$L$7:$AI$7,"<="&Fin.Qtr!P$7) -> 7.6802094 | Q33: =AVERAGEIFS(Fin.Mth!$L33:$AI33,Fin.Mth!$L$7:$AI$7,">="&Fin.Qtr!Q$8,Fin.Mth!$L$7:$AI$7,"<="&Fin.Qtr!Q$7) -> 7.7217484 | R33: =AVERAGEIFS(Fin.Mth!$L33:$AI33,Fin.Mth!$L$7:$AI$7,">="&Fin.Qtr!R$8,Fin.Mth!$L$7:$AI$7,"<="&Fin.Qtr!R$7) -> 7.7293888 | S33: =AVERAGEIFS(Fin.Mth!$L33:$AI33,Fin.Mth!$L$7:$AI$7,">="&Fin.Qtr!S$8,Fin.Mth!$L$7:$AI$7,"<="&Fin.Qtr!S$7) -> 7.7386804 | U33: =AVERAGE(L33:O33) -> 7.8941546 | V33: =AVERAGE(P33:S33) -> 7.7175067
B34: CAC Payback (Annual) | F34: months | M34: =AVERAGEIFS(Fin.Mth!$L34:$AI34,Fin.Mth!$L$7:$AI$7,">="&Fin.Qtr!M$8,Fin.Mth!$L$7:$AI$7,"<="&Fin.Qtr!M$7) -> 0.72211156 | N34: =AVERAGEIFS(Fin.Mth!$L34:$AI34,Fin.Mth!$L$7:$AI$7,">="&Fin.Qtr!N$8,Fin.Mth!$L$7:$AI$7,"<="&Fin.Qtr!N$7) -> 0.7157634 | O34: =AVERAGEIFS(Fin.Mth!$L34:$AI34,Fin.Mth!$L$7:$AI$7,">="&Fin.Qtr!O$8,Fin.Mth!$L$7:$AI$7,"<="&Fin.Qtr!O$7) -> 0.7150763 | P34: =AVERAGEIFS(Fin.Mth!$L34:$AI34,Fin.Mth!$L$7:$AI$7,">="&Fin.Qtr!P$8,Fin.Mth!$L$7:$AI$7,"<="&Fin.Qtr!P$7) -> 0.69820085 | Q34: =AVERAGEIFS(Fin.Mth!$L34:$AI34,Fin.Mth!$L$7:$AI$7,">="&Fin.Qtr!Q$8,Fin.Mth!$L$7:$AI$7,"<="&Fin.Qtr!Q$7) -> 0.70197712 | R34: =AVERAGEIFS(Fin.Mth!$L34:$AI34,Fin.Mth!$L$7:$AI$7,">="&Fin.Qtr!R$8,Fin.Mth!$L$7:$AI$7,"<="&Fin.Qtr!R$7) -> 0.70267171 | S34: =AVERAGEIFS(Fin.Mth!$L34:$AI34,Fin.Mth!$L$7:$AI$7,">="&Fin.Qtr!S$8,Fin.Mth!$L$7:$AI$7,"<="&Fin.Qtr!S$7) -> 0.7035164 | U34: =AVERAGE(L34:O34) -> 0.71765042 | V34: =AVERAGE(P34:S34) -> 0.70159152
B35: GDR (Monthly) | F35: % | M35: =AVERAGEIFS(Fin.Mth!$L35:$AI35,Fin.Mth!$L$7:$AI$7,">="&Fin.Qtr!M$8,Fin.Mth!$L$7:$AI$7,"<="&Fin.Qtr!M$7) -> 0.75 | N35: =AVERAGEIFS(Fin.Mth!$L35:$AI35,Fin.Mth!$L$7:$AI$7,">="&Fin.Qtr!N$8,Fin.Mth!$L$7:$AI$7,"<="&Fin.Qtr!N$7) -> 0.75 | O35: =AVERAGEIFS(Fin.Mth!$L35:$AI35,Fin.Mth!$L$7:$AI$7,">="&Fin.Qtr!O$8,Fin.Mth!$L$7:$AI$7,"<="&Fin.Qtr!O$7) -> 0.75 | P35: =AVERAGEIFS(Fin.Mth!$L35:$AI35,Fin.Mth!$L$7:$AI$7,">="&Fin.Qtr!P$8,Fin.Mth!$L$7:$AI$7,"<="&Fin.Qtr!P$7) -> 0.75 | Q35: =AVERAGEIFS(Fin.Mth!$L35:$AI35,Fin.Mth!$L$7:$AI$7,">="&Fin.Qtr!Q$8,Fin.Mth!$L$7:$AI$7,"<="&Fin.Qtr!Q$7) -> 0.75 | R35: =AVERAGEIFS(Fin.Mth!$L35:$AI35,Fin.Mth!$L$7:$AI$7,">="&Fin.Qtr!R$8,Fin.Mth!$L$7:$AI$7,"<="&Fin.Qtr!R$7) -> 0.75 | S35: =AVERAGEIFS(Fin.Mth!$L35:$AI35,Fin.Mth!$L$7:$AI$7,">="&Fin.Qtr!S$8,Fin.Mth!$L$7:$AI$7,"<="&Fin.Qtr!S$7) -> 0.75 | U35: =AVERAGE(L35:O35) -> 0.75 | V35: =AVERAGE(P35:S35) -> 0.75
B36: GDR (Annual) | F36: % | M36: =AVERAGEIFS(Fin.Mth!$L36:$AI36,Fin.Mth!$L$7:$AI$7,">="&Fin.Qtr!M$8,Fin.Mth!$L$7:$AI$7,"<="&Fin.Qtr!M$7) -> 1 | N36: =AVERAGEIFS(Fin.Mth!$L36:$AI36,Fin.Mth!$L$7:$AI$7,">="&Fin.Qtr!N$8,Fin.Mth!$L$7:$AI$7,"<="&Fin.Qtr!N$7) -> 1 | O36: =AVERAGEIFS(Fin.Mth!$L36:$AI36,Fin.Mth!$L$7:$AI$7,">="&Fin.Qtr!O$8,Fin.Mth!$L$7:$AI$7,"<="&Fin.Qtr!O$7) -> 1 | P36: =AVERAGEIFS(Fin.Mth!$L36:$AI36,Fin.Mth!$L$7:$AI$7,">="&Fin.Qtr!P$8,Fin.Mth!$L$7:$AI$7,"<="&Fin.Qtr!P$7) -> 0.93586809 | Q36: =AVERAGEIFS(Fin.Mth!$L36:$AI36,Fin.Mth!$L$7:$AI$7,">="&Fin.Qtr!Q$8,Fin.Mth!$L$7:$AI$7,"<="&Fin.Qtr!Q$7) -> 0.98673092 | R36: =AVERAGEIFS(Fin.Mth!$L36:$AI36,Fin.Mth!$L$7:$AI$7,">="&Fin.Qtr!R$8,Fin.Mth!$L$7:$AI$7,"<="&Fin.Qtr!R$7) -> 0.98621814 | S36: =AVERAGEIFS(Fin.Mth!$L36:$AI36,Fin.Mth!$L$7:$AI$7,">="&Fin.Qtr!S$8,Fin.Mth!$L$7:$AI$7,"<="&Fin.Qtr!S$7) -> 0.98566412 | U36: =AVERAGE(L36:O36) -> 1 | V36: =AVERAGE(P36:S36) -> 0.97362032
B38: Headcount | F38: $k | L38: =AVERAGEIFS(Fin.Mth!$L38:$AI38,Fin.Mth!$L$7:$AI$7,">="&Fin.Qtr!L$8,Fin.Mth!$L$7:$AI$7,"<="&Fin.Qtr!L$7) -> 7.3333333 | M38: =AVERAGEIFS(Fin.Mth!$L38:$AI38,Fin.Mth!$L$7:$AI$7,">="&Fin.Qtr!M$8,Fin.Mth!$L$7:$AI$7,"<="&Fin.Qtr!M$7) -> 10.333333 | N38: =AVERAGEIFS(Fin.Mth!$L38:$AI38,Fin.Mth!$L$7:$AI$7,">="&Fin.Qtr!N$8,Fin.Mth!$L$7:$AI$7,"<="&Fin.Qtr!N$7) -> 11.333333 | O38: =AVERAGEIFS(Fin.Mth!$L38:$AI38,Fin.Mth!$L$7:$AI$7,">="&Fin.Qtr!O$8,Fin.Mth!$L$7:$AI$7,"<="&Fin.Qtr!O$7) -> 13 | P38: =AVERAGEIFS(Fin.Mth!$L38:$AI38,Fin.Mth!$L$7:$AI$7,">="&Fin.Qtr!P$8,Fin.Mth!$L$7:$AI$7,"<="&Fin.Qtr!P$7) -> 13 | Q38: =AVERAGEIFS(Fin.Mth!$L38:$AI38,Fin.Mth!$L$7:$AI$7,">="&Fin.Qtr!Q$8,Fin.Mth!$L$7:$AI$7,"<="&Fin.Qtr!Q$7) -> 15 | R38: =AVERAGEIFS(Fin.Mth!$L38:$AI38,Fin.Mth!$L$7:$AI$7,">="&Fin.Qtr!R$8,Fin.Mth!$L$7:$AI$7,"<="&Fin.Qtr!R$7) -> 16.666667 | S38: =AVERAGEIFS(Fin.Mth!$L38:$AI38,Fin.Mth!$L$7:$AI$7,">="&Fin.Qtr!S$8,Fin.Mth!$L$7:$AI$7,"<="&Fin.Qtr!S$7) -> 18.666667 | U38: =AVERAGE(L38:O38) -> 10.5 | V38: =AVERAGE(P38:S38) -> 15.833333
A40: X | B40: PROFIT & LOSS
B42: =Fin.Mth!B42 -> Monthly Plan | L42: =SUMIFS(Fin.Mth!$L42:$AI42,Fin.Mth!$L$7:$AI$7,">="&Fin.Qtr!L$8,Fin.Mth!$L$7:$AI$7,"<="&Fin.Qtr!L$7) -> 225.32203 | M42: =SUMIFS(Fin.Mth!$L42:$AI42,Fin.Mth!$L$7:$AI$7,">="&Fin.Qtr!M$8,Fin.Mth!$L$7:$AI$7,"<="&Fin.Qtr!M$7) -> 247.79946 | N42: =SUMIFS(Fin.Mth!$L42:$AI42,Fin.Mth!$L$7:$AI$7,">="&Fin.Qtr!N$8,Fin.Mth!$L$7:$AI$7,"<="&Fin.Qtr!N$7) -> 152.17984 | O42: =SUMIFS(Fin.Mth!$L42:$AI42,Fin.Mth!$L$7:$AI$7,">="&Fin.Qtr!O$8,Fin.Mth!$L$7:$AI$7,"<="&Fin.Qtr!O$7) -> 93.457446 | P42: =SUMIFS(Fin.Mth!$L42:$AI42,Fin.Mth!$L$7:$AI$7,">="&Fin.Qtr!P$8,Fin.Mth!$L$7:$AI$7,"<="&Fin.Qtr!P$7) -> 57.394554 | Q42: =SUMIFS(Fin.Mth!$L42:$AI42,Fin.Mth!$L$7:$AI$7,">="&Fin.Qtr!Q$8,Fin.Mth!$L$7:$AI$7,"<="&Fin.Qtr!Q$7) -> 35.24743 | R42: =SUMIFS(Fin.Mth!$L42:$AI42,Fin.Mth!$L$7:$AI$7,">="&Fin.Qtr!R$8,Fin.Mth!$L$7:$AI$7,"<="&Fin.Qtr!R$7) -> 21.646328 | S42: =SUMIFS(Fin.Mth!$L42:$AI42,Fin.Mth!$L$7:$AI$7,">="&Fin.Qtr!S$8,Fin.Mth!$L$7:$AI$7,"<="&Fin.Qtr!S$7) -> 13.293551 | U42: =SUM(L42:O42) -> 718.75878 | V42: =SUM(P42:S42) -> 127.58186
B43: =Fin.Mth!B43 -> Annual Plan | L43: =SUMIFS(Fin.Mth!$L43:$AI43,Fin.Mth!$L$7:$AI$7,">="&Fin.Qtr!L$8,Fin.Mth!$L$7:$AI$7,"<="&Fin.Qtr!L$7) -> 243.2925 | M43: =SUMIFS(Fin.Mth!$L43:$AI43,Fin.Mth!$L$7:$AI$7,">="&Fin.Qtr!M$8,Fin.Mth!$L$7:$AI$7,"<="&Fin.Qtr!M$7) -> 449.74261 | N43: =SUMIFS(Fin.Mth!$L43:$AI43,Fin.Mth!$L$7:$AI$7,">="&Fin.Qtr!N$8,Fin.Mth!$L$7:$AI$7,"<="&Fin.Qtr!N$7) -> 550.95403 | O43: =SUMIFS(Fin.Mth!$L43:$AI43,Fin.Mth!$L$7:$AI$7,">="&Fin.Qtr!O$8,Fin.Mth!$L$7:$AI$7,"<="&Fin.Qtr!O$7) -> 674.94238 | P43: =SUMIFS(Fin.Mth!$L43:$AI43,Fin.Mth!$L$7:$AI$7,">="&Fin.Qtr!P$8,Fin.Mth!$L$7:$AI$7,"<="&Fin.Qtr!P$7) -> 579.67479 | Q43: =SUMIFS(Fin.Mth!$L43:$AI43,Fin.Mth!$L$7:$AI$7,">="&Fin.Qtr!Q$8,Fin.Mth!$L$7:$AI$7,"<="&Fin.Qtr!Q$7) -> 532.36893 | R43: =SUMIFS(Fin.Mth!$L43:$AI43,Fin.Mth!$L$7:$AI$7,">="&Fin.Qtr!R$8,Fin.Mth!$L$7:$AI$7,"<="&Fin.Qtr!R$7) -> 614.32893 | S43: =SUMIFS(Fin.Mth!$L43:$AI43,Fin.Mth!$L$7:$AI$7,">="&Fin.Qtr!S$8,Fin.Mth!$L$7:$AI$7,"<="&Fin.Qtr!S$7) -> 706.21648 | U43: =SUM(L43:O43) -> 1918.9315 | V43: =SUM(P43:S43) -> 2432.5891
B44: =Fin.Mth!B44 -> Total Revenue | F44: $k | L44: =SUMIFS(Fin.Mth!$L44:$AI44,Fin.Mth!$L$7:$AI$7,">="&Fin.Qtr!L$8,Fin.Mth!$L$7:$AI$7,"<="&Fin.Qtr!L$7) -> 468.61453 | M44: =SUMIFS(Fin.Mth!$L44:$AI44,Fin.Mth!$L$7:$AI$7,">="&Fin.Qtr!M$8,Fin.Mth!$L$7:$AI$7,"<="&Fin.Qtr!M$7) -> 697.54207 | N44: =SUMIFS(Fin.Mth!$L44:$AI44,Fin.Mth!$L$7:$AI$7,">="&Fin.Qtr!N$8,Fin.Mth!$L$7:$AI$7,"<="&Fin.Qtr!N$7) -> 703.13388 | O44: =SUMIFS(Fin.Mth!$L44:$AI44,Fin.Mth!$L$7:$AI$7,">="&Fin.Qtr!O$8,Fin.Mth!$L$7:$AI$7,"<="&Fin.Qtr!O$7) -> 768.39983 | P44: =SUMIFS(Fin.Mth!$L44:$AI44,Fin.Mth!$L$7:$AI$7,">="&Fin.Qtr!P$8,Fin.Mth!$L$7:$AI$7,"<="&Fin.Qtr!P$7) -> 637.06934 | Q44: =SUMIFS(Fin.Mth!$L44:$AI44,Fin.Mth!$L$7:$AI$7,">="&Fin.Qtr!Q$8,Fin.Mth!$L$7:$AI$7,"<="&Fin.Qtr!Q$7) -> 567.61636 | R44: =SUMIFS(Fin.Mth!$L44:$AI44,Fin.Mth!$L$7:$AI$7,">="&Fin.Qtr!R$8,Fin.Mth!$L$7:$AI$7,"<="&Fin.Qtr!R$7) -> 635.97525 | S44: =SUMIFS(Fin.Mth!$L44:$AI44,Fin.Mth!$L$7:$AI$7,">="&Fin.Qtr!S$8,Fin.Mth!$L$7:$AI$7,"<="&Fin.Qtr!S$7) -> 719.51004 | U44: =SUM(L44:O44) -> 2637.6903 | V44: =SUM(P44:S44) -> 2560.171
B45: =Fin.Mth!B45 -> COGS | F45: $k | L45: =SUMIFS(Fin.Mth!$L45:$AI45,Fin.Mth!$L$7:$AI$7,">="&Fin.Qtr!L$8,Fin.Mth!$L$7:$AI$7,"<="&Fin.Qtr!L$7) -> -123.63683 | M45: =SUMIFS(Fin.Mth!$L45:$AI45,Fin.Mth!$L$7:$AI$7,">="&Fin.Qtr!M$8,Fin.Mth!$L$7:$AI$7,"<="&Fin.Qtr!M$7) -> -112.10541 | N45: =SUMIFS(Fin.Mth!$L45:$AI45,Fin.Mth!$L$7:$AI$7,">="&Fin.Qtr!N$8,Fin.Mth!$L$7:$AI$7,"<="&Fin.Qtr!N$7) -> -107.76425 | O45: =SUMIFS(Fin.Mth!$L45:$AI45,Fin.Mth!$L$7:$AI$7,">="&Fin.Qtr!O$8,Fin.Mth!$L$7:$AI$7,"<="&Fin.Qtr!O$7) -> -117.14073 | P45: =SUMIFS(Fin.Mth!$L45:$AI45,Fin.Mth!$L$7:$AI$7,">="&Fin.Qtr!P$8,Fin.Mth!$L$7:$AI$7,"<="&Fin.Qtr!P$7) -> -83.808075 | Q45: =SUMIFS(Fin.Mth!$L45:$AI45,Fin.Mth!$L$7:$AI$7,">="&Fin.Qtr!Q$8,Fin.Mth!$L$7:$AI$7,"<="&Fin.Qtr!Q$7) -> -77.559438 | R45: =SUMIFS(Fin.Mth!$L45:$AI45,Fin.Mth!$L$7:$AI$7,">="&Fin.Qtr!R$8,Fin.Mth!$L$7:$AI$7,"<="&Fin.Qtr!R$7) -> -87.446562 | S45: =SUMIFS(Fin.Mth!$L45:$AI45,Fin.Mth!$L$7:$AI$7,">="&Fin.Qtr!S$8,Fin.Mth!$L$7:$AI$7,"<="&Fin.Qtr!S$7) -> -99.678464 | U45: =SUM(L45:O45) -> -460.64721 | V45: =SUM(P45:S45) -> -348.49254
B46: =Fin.Mth!B46 -> Gross Profit | F46: $k | L46: =SUMIFS(Fin.Mth!$L46:$AI46,Fin.Mth!$L$7:$AI$7,">="&Fin.Qtr!L$8,Fin.Mth!$L$7:$AI$7,"<="&Fin.Qtr!L$7) -> 344.97771 | M46: =SUMIFS(Fin.Mth!$L46:$AI46,Fin.Mth!$L$7:$AI$7,">="&Fin.Qtr!M$8,Fin.Mth!$L$7:$AI$7,"<="&Fin.Qtr!M$7) -> 585.43666 | N46: =SUMIFS(Fin.Mth!$L46:$AI46,Fin.Mth!$L$7:$AI$7,">="&Fin.Qtr!N$8,Fin.Mth!$L$7:$AI$7,"<="&Fin.Qtr!N$7) -> 595.36963 | O46: =SUMIFS(Fin.Mth!$L46:$AI46,Fin.Mth!$L$7:$AI$7,">="&Fin.Qtr!O$8,Fin.Mth!$L$7:$AI$7,"<="&Fin.Qtr!O$7) -> 651.2591 | P46: =SUMIFS(Fin.Mth!$L46:$AI46,Fin.Mth!$L$7:$AI$7,">="&Fin.Qtr!P$8,Fin.Mth!$L$7:$AI$7,"<="&Fin.Qtr!P$7) -> 553.26127 | Q46: =SUMIFS(Fin.Mth!$L46:$AI46,Fin.Mth!$L$7:$AI$7,">="&Fin.Qtr!Q$8,Fin.Mth!$L$7:$AI$7,"<="&Fin.Qtr!Q$7) -> 490.05692 | R46: =SUMIFS(Fin.Mth!$L46:$AI46,Fin.Mth!$L$7:$AI$7,">="&Fin.Qtr!R$8,Fin.Mth!$L$7:$AI$7,"<="&Fin.Qtr!R$7) -> 548.52869 | S46: =SUMIFS(Fin.Mth!$L46:$AI46,Fin.Mth!$L$7:$AI$7,">="&Fin.Qtr!S$8,Fin.Mth!$L$7:$AI$7,"<="&Fin.Qtr!S$7) -> 619.83157 | U46: =SUM(L46:O46) -> 2177.0431 | V46: =SUM(P46:S46) -> 2211.6785
B47: =Fin.Mth!B47 -> % margin | F47: % | L47: =L46/L44 -> 0.73616519 | M47: =M46/M44 -> 0.83928509 | N47: =N46/N44 -> 0.84673723 | O47: =O46/O44 -> 0.84755237 | P47: =P46/P44 -> 0.86844748 | Q47: =Q46/Q44 -> 0.8633594 | R47: =R46/R44 -> 0.86250006 | S47: =S46/S44 -> 0.86146341 | U47: =U46/U44 -> 0.82535963 | V47: =V46/V44 -> 0.86387919
B48: =Fin.Mth!B48 -> Headcount Costs | F48: $k | L48: =SUMIFS(Fin.Mth!$L48:$AI48,Fin.Mth!$L$7:$AI$7,">="&Fin.Qtr!L$8,Fin.Mth!$L$7:$AI$7,"<="&Fin.Qtr!L$7) -> -284.625 | M48: =SUMIFS(Fin.Mth!$L48:$AI48,Fin.Mth!$L$7:$AI$7,">="&Fin.Qtr!M$8,Fin.Mth!$L$7:$AI$7,"<="&Fin.Qtr!M$7) -> -414 | N48: =SUMIFS(Fin.Mth!$L48:$AI48,Fin.Mth!$L$7:$AI$7,">="&Fin.Qtr!N$8,Fin.Mth!$L$7:$AI$7,"<="&Fin.Qtr!N$7) -> -465.75 | O48: =SUMIFS(Fin.Mth!$L48:$AI48,Fin.Mth!$L$7:$AI$7,">="&Fin.Qtr!O$8,Fin.Mth!$L$7:$AI$7,"<="&Fin.Qtr!O$7) -> -562.12 | P48: =SUMIFS(Fin.Mth!$L48:$AI48,Fin.Mth!$L$7:$AI$7,">="&Fin.Qtr!P$8,Fin.Mth!$L$7:$AI$7,"<="&Fin.Qtr!P$7) -> -599.265 | Q48: =SUMIFS(Fin.Mth!$L48:$AI48,Fin.Mth!$L$7:$AI$7,">="&Fin.Qtr!Q$8,Fin.Mth!$L$7:$AI$7,"<="&Fin.Qtr!Q$7) -> -692.415 | R48: =SUMIFS(Fin.Mth!$L48:$AI48,Fin.Mth!$L$7:$AI$7,">="&Fin.Qtr!R$8,Fin.Mth!$L$7:$AI$7,"<="&Fin.Qtr!R$7) -> -776.25 | S48: =SUMIFS(Fin.Mth!$L48:$AI48,Fin.Mth!$L$7:$AI$7,">="&Fin.Qtr!S$8,Fin.Mth!$L$7:$AI$7,"<="&Fin.Qtr!S$7) -> -869.4 | U48: =SUM(L48:O48) -> -1726.495 | V48: =SUM(P48:S48) -> -2937.33
B49: =Fin.Mth!B49 -> G&A | F49: $k | L49: =SUMIFS(Fin.Mth!$L49:$AI49,Fin.Mth!$L$7:$AI$7,">="&Fin.Qtr!L$8,Fin.Mth!$L$7:$AI$7,"<="&Fin.Qtr!L$7) -> -61.4 | M49: =SUMIFS(Fin.Mth!$L49:$AI49,Fin.Mth!$L$7:$AI$7,">="&Fin.Qtr!M$8,Fin.Mth!$L$7:$AI$7,"<="&Fin.Qtr!M$7) -> -65.698 | N49: =SUMIFS(Fin.Mth!$L49:$AI49,Fin.Mth!$L$7:$AI$7,">="&Fin.Qtr!N$8,Fin.Mth!$L$7:$AI$7,"<="&Fin.Qtr!N$7) -> -70.29686 | O49: =SUMIFS(Fin.Mth!$L49:$AI49,Fin.Mth!$L$7:$AI$7,">="&Fin.Qtr!O$8,Fin.Mth!$L$7:$AI$7,"<="&Fin.Qtr!O$7) -> -75.21764 | P49: =SUMIFS(Fin.Mth!$L49:$AI49,Fin.Mth!$L$7:$AI$7,">="&Fin.Qtr!P$8,Fin.Mth!$L$7:$AI$7,"<="&Fin.Qtr!P$7) -> -80.482875 | Q49: =SUMIFS(Fin.Mth!$L49:$AI49,Fin.Mth!$L$7:$AI$7,">="&Fin.Qtr!Q$8,Fin.Mth!$L$7:$AI$7,"<="&Fin.Qtr!Q$7) -> -86.116676 | R49: =SUMIFS(Fin.Mth!$L49:$AI49,Fin.Mth!$L$7:$AI$7,">="&Fin.Qtr!R$8,Fin.Mth!$L$7:$AI$7,"<="&Fin.Qtr!R$7) -> -92.144844 | S49: =SUMIFS(Fin.Mth!$L49:$AI49,Fin.Mth!$L$7:$AI$7,">="&Fin.Qtr!S$8,Fin.Mth!$L$7:$AI$7,"<="&Fin.Qtr!S$7) -> -98.594983 | U49: =SUM(L49:O49) -> -272.6125 | V49: =SUM(P49:S49) -> -357.33938
B50: =Fin.Mth!B50 -> S&M | F50: $k | L50: =SUMIFS(Fin.Mth!$L50:$AI50,Fin.Mth!$L$7:$AI$7,">="&Fin.Qtr!L$8,Fin.Mth!$L$7:$AI$7,"<="&Fin.Qtr!L$7) -> -1966 | M50: =SUMIFS(Fin.Mth!$L50:$AI50,Fin.Mth!$L$7:$AI$7,">="&Fin.Qtr!M$8,Fin.Mth!$L$7:$AI$7,"<="&Fin.Qtr!M$7) -> -399.81147 | N50: =SUMIFS(Fin.Mth!$L50:$AI50,Fin.Mth!$L$7:$AI$7,">="&Fin.Qtr!N$8,Fin.Mth!$L$7:$AI$7,"<="&Fin.Qtr!N$7) -> -380.67983 | O50: =SUMIFS(Fin.Mth!$L50:$AI50,Fin.Mth!$L$7:$AI$7,">="&Fin.Qtr!O$8,Fin.Mth!$L$7:$AI$7,"<="&Fin.Qtr!O$7) -> -399.34419 | P50: =SUMIFS(Fin.Mth!$L50:$AI50,Fin.Mth!$L$7:$AI$7,">="&Fin.Qtr!P$8,Fin.Mth!$L$7:$AI$7,"<="&Fin.Qtr!P$7) -> -415.9129 | Q50: =SUMIFS(Fin.Mth!$L50:$AI50,Fin.Mth!$L$7:$AI$7,">="&Fin.Qtr!Q$8,Fin.Mth!$L$7:$AI$7,"<="&Fin.Qtr!Q$7) -> -433.67216 | R50: =SUMIFS(Fin.Mth!$L50:$AI50,Fin.Mth!$L$7:$AI$7,">="&Fin.Qtr!R$8,Fin.Mth!$L$7:$AI$7,"<="&Fin.Qtr!R$7) -> -497.1321 | S50: =SUMIFS(Fin.Mth!$L50:$AI50,Fin.Mth!$L$7:$AI$7,">="&Fin.Qtr!S$8,Fin.Mth!$L$7:$AI$7,"<="&Fin.Qtr!S$7) -> -576.67254 | U50: =SUM(L50:O50) -> -3145.8355 | V50: =SUM(P50:S50) -> -1923.3897
B51: =Fin.Mth!B51 -> Facilities Expense | F51: $k | L51: =SUMIFS(Fin.Mth!$L51:$AI51,Fin.Mth!$L$7:$AI$7,">="&Fin.Qtr!L$8,Fin.Mth!$L$7:$AI$7,"<="&Fin.Qtr!L$7) -> -42 | M51: =SUMIFS(Fin.Mth!$L51:$AI51,Fin.Mth!$L$7:$AI$7,">="&Fin.Qtr!M$8,Fin.Mth!$L$7:$AI$7,"<="&Fin.Qtr!M$7) -> -42 | N51: =SUMIFS(Fin.Mth!$L51:$AI51,Fin.Mth!$L$7:$AI$7,">="&Fin.Qtr!N$8,Fin.Mth!$L$7:$AI$7,"<="&Fin.Qtr!N$7) -> -42 | O51: =SUMIFS(Fin.Mth!$L51:$AI51,Fin.Mth!$L$7:$AI$7,">="&Fin.Qtr!O$8,Fin.Mth!$L$7:$AI$7,"<="&Fin.Qtr!O$7) -> -42 | P51: =SUMIFS(Fin.Mth!$L51:$AI51,Fin.Mth!$L$7:$AI$7,">="&Fin.Qtr!P$8,Fin.Mth!$L$7:$AI$7,"<="&Fin.Qtr!P$7) -> -42 | Q51: =SUMIFS(Fin.Mth!$L51:$AI51,Fin.Mth!$L$7:$AI$7,">="&Fin.Qtr!Q$8,Fin.Mth!$L$7:$AI$7,"<="&Fin.Qtr!Q$7) -> -42 | R51: =SUMIFS(Fin.Mth!$L51:$AI51,Fin.Mth!$L$7:$AI$7,">="&Fin.Qtr!R$8,Fin.Mth!$L$7:$AI$7,"<="&Fin.Qtr!R$7) -> -42 | S51: =SUMIFS(Fin.Mth!$L51:$AI51,Fin.Mth!$L$7:$AI$7,">="&Fin.Qtr!S$8,Fin.Mth!$L$7:$AI$7,"<="&Fin.Qtr!S$7) -> -56 | U51: =SUM(L51:O51) -> -168 | V51: =SUM(P51:S51) -> -182
B52: =Fin.Mth!B52 -> Miscellaneous | F52: $k | L52: =SUMIFS(Fin.Mth!$L52:$AI52,Fin.Mth!$L$7:$AI$7,">="&Fin.Qtr!L$8,Fin.Mth!$L$7:$AI$7,"<="&Fin.Qtr!L$7) -> -23.430727 | M52: =SUMIFS(Fin.Mth!$L52:$AI52,Fin.Mth!$L$7:$AI$7,">="&Fin.Qtr!M$8,Fin.Mth!$L$7:$AI$7,"<="&Fin.Qtr!M$7) -> -34.877103 | N52: =SUMIFS(Fin.Mth!$L52:$AI52,Fin.Mth!$L$7:$AI$7,">="&Fin.Qtr!N$8,Fin.Mth!$L$7:$AI$7,"<="&Fin.Qtr!N$7) -> -35.156694 | O52: =SUMIFS(Fin.Mth!$L52:$AI52,Fin.Mth!$L$7:$AI$7,">="&Fin.Qtr!O$8,Fin.Mth!$L$7:$AI$7,"<="&Fin.Qtr!O$7) -> -38.419991 | P52: =SUMIFS(Fin.Mth!$L52:$AI52,Fin.Mth!$L$7:$AI$7,">="&Fin.Qtr!P$8,Fin.Mth!$L$7:$AI$7,"<="&Fin.Qtr!P$7) -> -31.853467 | Q52: =SUMIFS(Fin.Mth!$L52:$AI52,Fin.Mth!$L$7:$AI$7,">="&Fin.Qtr!Q$8,Fin.Mth!$L$7:$AI$7,"<="&Fin.Qtr!Q$7) -> -28.380818 | R52: =SUMIFS(Fin.Mth!$L52:$AI52,Fin.Mth!$L$7:$AI$7,">="&Fin.Qtr!R$8,Fin.Mth!$L$7:$AI$7,"<="&Fin.Qtr!R$7) -> -31.798763 | S52: =SUMIFS(Fin.Mth!$L52:$AI52,Fin.Mth!$L$7:$AI$7,">="&Fin.Qtr!S$8,Fin.Mth!$L$7:$AI$7,"<="&Fin.Qtr!S$7) -> -35.975502 | U52: =SUM(L52:O52) -> -131.88452 | V52: =SUM(P52:S52) -> -128.00855
B53: =Fin.Mth!B53 -> EBITDA | F53: $k | L53: =SUMIFS(Fin.Mth!$L53:$AI53,Fin.Mth!$L$7:$AI$7,">="&Fin.Qtr!L$8,Fin.Mth!$L$7:$AI$7,"<="&Fin.Qtr!L$7) -> -2032.478 | M53: =SUMIFS(Fin.Mth!$L53:$AI53,Fin.Mth!$L$7:$AI$7,">="&Fin.Qtr!M$8,Fin.Mth!$L$7:$AI$7,"<="&Fin.Qtr!M$7) -> -370.94992 | N53: =SUMIFS(Fin.Mth!$L53:$AI53,Fin.Mth!$L$7:$AI$7,">="&Fin.Qtr!N$8,Fin.Mth!$L$7:$AI$7,"<="&Fin.Qtr!N$7) -> -398.51376 | O53: =SUMIFS(Fin.Mth!$L53:$AI53,Fin.Mth!$L$7:$AI$7,">="&Fin.Qtr!O$8,Fin.Mth!$L$7:$AI$7,"<="&Fin.Qtr!O$7) -> -465.84272 | P53: =SUMIFS(Fin.Mth!$L53:$AI53,Fin.Mth!$L$7:$AI$7,">="&Fin.Qtr!P$8,Fin.Mth!$L$7:$AI$7,"<="&Fin.Qtr!P$7) -> -616.25297 | Q53: =SUMIFS(Fin.Mth!$L53:$AI53,Fin.Mth!$L$7:$AI$7,">="&Fin.Qtr!Q$8,Fin.Mth!$L$7:$AI$7,"<="&Fin.Qtr!Q$7) -> -792.52773 | R53: =SUMIFS(Fin.Mth!$L53:$AI53,Fin.Mth!$L$7:$AI$7,">="&Fin.Qtr!R$8,Fin.Mth!$L$7:$AI$7,"<="&Fin.Qtr!R$7) -> -890.79701 | S53: =SUMIFS(Fin.Mth!$L53:$AI53,Fin.Mth!$L$7:$AI$7,">="&Fin.Qtr!S$8,Fin.Mth!$L$7:$AI$7,"<="&Fin.Qtr!S$7) -> -1016.8115 | U53: =SUM(L53:O53) -> -3267.7844 | V53: =SUM(P53:S53) -> -3316.3892
B54: =Fin.Mth!B54 -> % margin | F54: % | L54: =L53/L44 -> -4.3372066 | M54: =M53/M44 -> -0.53179576 | N54: =N53/N44 -> -0.56676796 | O54: =O53/O44 -> -0.60625042 | P54: =P53/P44 -> -0.9673248 | Q54: =Q53/Q44 -> -1.3962384 | R54: =R53/R44 -> -1.4006787 | S54: =S53/S44 -> -1.4131998 | U54: =U53/U44 -> -1.238881 | V54: =V53/V44 -> -1.295378
A56: X | B56: CASH FLOW STATEMENT
B58: EBITDA | F58: $k | L58: =SUMIFS(Fin.Mth!$L58:$AI58,Fin.Mth!$L$7:$AI$7,">="&Fin.Qtr!L$8,Fin.Mth!$L$7:$AI$7,"<="&Fin.Qtr!L$7) -> -2032.478 | M58: =SUMIFS(Fin.Mth!$L58:$AI58,Fin.Mth!$L$7:$AI$7,">="&Fin.Qtr!M$8,Fin.Mth!$L$7:$AI$7,"<="&Fin.Qtr!M$7) -> -370.94992 | N58: =SUMIFS(Fin.Mth!$L58:$AI58,Fin.Mth!$L$7:$AI$7,">="&Fin.Qtr!N$8,Fin.Mth!$L$7:$AI$7,"<="&Fin.Qtr!N$7) -> -398.51376 | O58: =SUMIFS(Fin.Mth!$L58:$AI58,Fin.Mth!$L$7:$AI$7,">="&Fin.Qtr!O$8,Fin.Mth!$L$7:$AI$7,"<="&Fin.Qtr!O$7) -> -465.84272 | P58: =SUMIFS(Fin.Mth!$L58:$AI58,Fin.Mth!$L$7:$AI$7,">="&Fin.Qtr!P$8,Fin.Mth!$L$7:$AI$7,"<="&Fin.Qtr!P$7) -> -616.25297 | Q58: =SUMIFS(Fin.Mth!$L58:$AI58,Fin.Mth!$L$7:$AI$7,">="&Fin.Qtr!Q$8,Fin.Mth!$L$7:$AI$7,"<="&Fin.Qtr!Q$7) -> -792.52773 | R58: =SUMIFS(Fin.Mth!$L58:$AI58,Fin.Mth!$L$7:$AI$7,">="&Fin.Qtr!R$8,Fin.Mth!$L$7:$AI$7,"<="&Fin.Qtr!R$7) -> -890.79701 | S58: =SUMIFS(Fin.Mth!$L58:$AI58,Fin.Mth!$L$7:$AI$7,">="&Fin.Qtr!S$8,Fin.Mth!$L$7:$AI$7,"<="&Fin.Qtr!S$7) -> -1016.8115 | U58: =SUM(L58:O58) -> -3267.7844 | V58: =SUM(P58:S58) -> -3316.3892
B59: Less: Change in NWC | F59: $k | L59: =SUMIFS(Fin.Mth!$L59:$AI59,Fin.Mth!$L$7:$AI$7,">="&Fin.Qtr!L$8,Fin.Mth!$L$7:$AI$7,"<="&Fin.Qtr!L$7) -> 338.36543 | M59: =SUMIFS(Fin.Mth!$L59:$AI59,Fin.Mth!$L$7:$AI$7,">="&Fin.Qtr!M$8,Fin.Mth!$L$7:$AI$7,"<="&Fin.Qtr!M$7) -> 3.9950726 | N59: =SUMIFS(Fin.Mth!$L59:$AI59,Fin.Mth!$L$7:$AI$7,">="&Fin.Qtr!N$8,Fin.Mth!$L$7:$AI$7,"<="&Fin.Qtr!N$7) -> 7.9568035 | O59: =SUMIFS(Fin.Mth!$L59:$AI59,Fin.Mth!$L$7:$AI$7,">="&Fin.Qtr!O$8,Fin.Mth!$L$7:$AI$7,"<="&Fin.Qtr!O$7) -> 34.157019 | P59: =SUMIFS(Fin.Mth!$L59:$AI59,Fin.Mth!$L$7:$AI$7,">="&Fin.Qtr!P$8,Fin.Mth!$L$7:$AI$7,"<="&Fin.Qtr!P$7) -> -120.86778 | Q59: =SUMIFS(Fin.Mth!$L59:$AI59,Fin.Mth!$L$7:$AI$7,">="&Fin.Qtr!Q$8,Fin.Mth!$L$7:$AI$7,"<="&Fin.Qtr!Q$7) -> 9.6144072 | R59: =SUMIFS(Fin.Mth!$L59:$AI59,Fin.Mth!$L$7:$AI$7,">="&Fin.Qtr!R$8,Fin.Mth!$L$7:$AI$7,"<="&Fin.Qtr!R$7) -> 28.972676 | S59: =SUMIFS(Fin.Mth!$L59:$AI59,Fin.Mth!$L$7:$AI$7,">="&Fin.Qtr!S$8,Fin.Mth!$L$7:$AI$7,"<="&Fin.Qtr!S$7) -> 34.297246 | U59: =SUM(L59:O59) -> 384.47433 | V59: =SUM(P59:S59) -> -47.983446
B60: Less: Cash Tax Paid | F60: $k
B61: Change in Deferred Revenues | F61: $k | L61: =SUMIFS(Fin.Mth!$L61:$AI61,Fin.Mth!$L$7:$AI$7,">="&Fin.Qtr!L$8,Fin.Mth!$L$7:$AI$7,"<="&Fin.Qtr!L$7) -> 1216.4625 | M61: =SUMIFS(Fin.Mth!$L61:$AI61,Fin.Mth!$L$7:$AI$7,">="&Fin.Qtr!M$8,Fin.Mth!$L$7:$AI$7,"<="&Fin.Qtr!M$7) -> 12.466916 | N61: =SUMIFS(Fin.Mth!$L61:$AI61,Fin.Mth!$L$7:$AI$7,">="&Fin.Qtr!N$8,Fin.Mth!$L$7:$AI$7,"<="&Fin.Qtr!N$7) -> -118.42937 | O61: =SUMIFS(Fin.Mth!$L61:$AI61,Fin.Mth!$L$7:$AI$7,">="&Fin.Qtr!O$8,Fin.Mth!$L$7:$AI$7,"<="&Fin.Qtr!O$7) -> -145.08107 | P61: =SUMIFS(Fin.Mth!$L61:$AI61,Fin.Mth!$L$7:$AI$7,">="&Fin.Qtr!P$8,Fin.Mth!$L$7:$AI$7,"<="&Fin.Qtr!P$7) -> 32.968693 | Q61: =SUMIFS(Fin.Mth!$L61:$AI61,Fin.Mth!$L$7:$AI$7,">="&Fin.Qtr!Q$8,Fin.Mth!$L$7:$AI$7,"<="&Fin.Qtr!Q$7) -> 125.64369 | R61: =SUMIFS(Fin.Mth!$L61:$AI61,Fin.Mth!$L$7:$AI$7,">="&Fin.Qtr!R$8,Fin.Mth!$L$7:$AI$7,"<="&Fin.Qtr!R$7) -> 158.99262 | S61: =SUMIFS(Fin.Mth!$L61:$AI61,Fin.Mth!$L$7:$AI$7,">="&Fin.Qtr!S$8,Fin.Mth!$L$7:$AI$7,"<="&Fin.Qtr!S$7) -> 204.73865 | U61: =SUM(L61:O61) -> 965.41897 | V61: =SUM(P61:S61) -> 522.34365
B62: CASH ACCRUAL / BURN | F62: $k | L62: =SUMIFS(Fin.Mth!$L62:$AI62,Fin.Mth!$L$7:$AI$7,">="&Fin.Qtr!L$8,Fin.Mth!$L$7:$AI$7,"<="&Fin.Qtr!L$7) -> -477.65009 | M62: =SUMIFS(Fin.Mth!$L62:$AI62,Fin.Mth!$L$7:$AI$7,">="&Fin.Qtr!M$8,Fin.Mth!$L$7:$AI$7,"<="&Fin.Qtr!M$7) -> -354.48793 | N62: =SUMIFS(Fin.Mth!$L62:$AI62,Fin.Mth!$L$7:$AI$7,">="&Fin.Qtr!N$8,Fin.Mth!$L$7:$AI$7,"<="&Fin.Qtr!N$7) -> -508.98632 | O62: =SUMIFS(Fin.Mth!$L62:$AI62,Fin.Mth!$L$7:$AI$7,">="&Fin.Qtr!O$8,Fin.Mth!$L$7:$AI$7,"<="&Fin.Qtr!O$7) -> -576.76677 | P62: =SUMIFS(Fin.Mth!$L62:$AI62,Fin.Mth!$L$7:$AI$7,">="&Fin.Qtr!P$8,Fin.Mth!$L$7:$AI$7,"<="&Fin.Qtr!P$7) -> -704.15206 | Q62: =SUMIFS(Fin.Mth!$L62:$AI62,Fin.Mth!$L$7:$AI$7,">="&Fin.Qtr!Q$8,Fin.Mth!$L$7:$AI$7,"<="&Fin.Qtr!Q$7) -> -657.26964 | R62: =SUMIFS(Fin.Mth!$L62:$AI62,Fin.Mth!$L$7:$AI$7,">="&Fin.Qtr!R$8,Fin.Mth!$L$7:$AI$7,"<="&Fin.Qtr!R$7) -> -702.83171 | S62: =SUMIFS(Fin.Mth!$L62:$AI62,Fin.Mth!$L$7:$AI$7,">="&Fin.Qtr!S$8,Fin.Mth!$L$7:$AI$7,"<="&Fin.Qtr!S$7) -> -777.77556 | U62: =SUM(L62:O62) -> -1917.8911 | V62: =SUM(P62:S62) -> -2842.029
B64: CASH AND CASH EQUIVALENTS
B65: Opening | F65: $k | L65: =K68 -> 3000 | M65: =L68 -> 2522.3499 | N65: =M68 -> 2167.862 | O65: =N68 -> 1658.8757 | P65: =O68 -> 4342.029 | Q65: =P68 -> 3637.8769 | R65: =Q68 -> 2980.6073 | S65: =R68 -> 2277.7756 | U65: =K68 -> 3000 | V65: =U68 -> 1082.1089
B66: Accrual / Burn | F66: $k | L66: =SUMIFS(Fin.Mth!$L66:$AI66,Fin.Mth!$L$7:$AI$7,">="&Fin.Qtr!L$8,Fin.Mth!$L$7:$AI$7,"<="&Fin.Qtr!L$7) -> -477.65009 | M66: =SUMIFS(Fin.Mth!$L66:$AI66,Fin.Mth!$L$7:$AI$7,">="&Fin.Qtr!M$8,Fin.Mth!$L$7:$AI$7,"<="&Fin.Qtr!M$7) -> -354.48793 | N66: =SUMIFS(Fin.Mth!$L66:$AI66,Fin.Mth!$L$7:$AI$7,">="&Fin.Qtr!N$8,Fin.Mth!$L$7:$AI$7,"<="&Fin.Qtr!N$7) -> -508.98632 | O66: =SUMIFS(Fin.Mth!$L66:$AI66,Fin.Mth!$L$7:$AI$7,">="&Fin.Qtr!O$8,Fin.Mth!$L$7:$AI$7,"<="&Fin.Qtr!O$7) -> -576.76677 | P66: =SUMIFS(Fin.Mth!$L66:$AI66,Fin.Mth!$L$7:$AI$7,">="&Fin.Qtr!P$8,Fin.Mth!$L$7:$AI$7,"<="&Fin.Qtr!P$7) -> -704.15206 | Q66: =SUMIFS(Fin.Mth!$L66:$AI66,Fin.Mth!$L$7:$AI$7,">="&Fin.Qtr!Q$8,Fin.Mth!$L$7:$AI$7,"<="&Fin.Qtr!Q$7) -> -657.26964 | R66: =SUMIFS(Fin.Mth!$L66:$AI66,Fin.Mth!$L$7:$AI$7,">="&Fin.Qtr!R$8,Fin.Mth!$L$7:$AI$7,"<="&Fin.Qtr!R$7) -> -702.83171 | S66: =SUMIFS(Fin.Mth!$L66:$AI66,Fin.Mth!$L$7:$AI$7,">="&Fin.Qtr!S$8,Fin.Mth!$L$7:$AI$7,"<="&Fin.Qtr!S$7) -> -777.77556 | U66: =SUM(L66:O66) -> -1917.8911 | V66: =SUM(P66:S66) -> -2842.029
B67: Add: Fundraise | F67: $k | L67: =SUMIFS(Fin.Mth!$L67:$AI67,Fin.Mth!$L$7:$AI$7,">="&Fin.Qtr!L$8,Fin.Mth!$L$7:$AI$7,"<="&Fin.Qtr!L$7) -> 0 | M67: =SUMIFS(Fin.Mth!$L67:$AI67,Fin.Mth!$L$7:$AI$7,">="&Fin.Qtr!M$8,Fin.Mth!$L$7:$AI$7,"<="&Fin.Qtr!M$7) -> 0 | N67: =SUMIFS(Fin.Mth!$L67:$AI67,Fin.Mth!$L$7:$AI$7,">="&Fin.Qtr!N$8,Fin.Mth!$L$7:$AI$7,"<="&Fin.Qtr!N$7) -> 0 | O67: =SUMIFS(Fin.Mth!$L67:$AI67,Fin.Mth!$L$7:$AI$7,">="&Fin.Qtr!O$8,Fin.Mth!$L$7:$AI$7,"<="&Fin.Qtr!O$7) -> 3259.9201 | P67: =SUMIFS(Fin.Mth!$L67:$AI67,Fin.Mth!$L$7:$AI$7,">="&Fin.Qtr!P$8,Fin.Mth!$L$7:$AI$7,"<="&Fin.Qtr!P$7) -> 0 | Q67: =SUMIFS(Fin.Mth!$L67:$AI67,Fin.Mth!$L$7:$AI$7,">="&Fin.Qtr!Q$8,Fin.Mth!$L$7:$AI$7,"<="&Fin.Qtr!Q$7) -> 0 | R67: =SUMIFS(Fin.Mth!$L67:$AI67,Fin.Mth!$L$7:$AI$7,">="&Fin.Qtr!R$8,Fin.Mth!$L$7:$AI$7,"<="&Fin.Qtr!R$7) -> 0 | S67: =SUMIFS(Fin.Mth!$L67:$AI67,Fin.Mth!$L$7:$AI$7,">="&Fin.Qtr!S$8,Fin.Mth!$L$7:$AI$7,"<="&Fin.Qtr!S$7) -> 0 | U67: =SUM(L67:O67) -> 3259.9201 | V67: =SUM(P67:S67) -> 0
B68: CLOSING | F68: $k | K68: 3000 | L68: =SUM(L65:L67) -> 2522.3499 | M68: =SUM(M65:M67) -> 2167.862 | N68: =SUM(N65:N67) -> 1658.8757 | O68: =SUM(O65:O67) -> 4342.029 | P68: =SUM(P65:P67) -> 3637.8769 | Q68: =SUM(Q65:Q67) -> 2980.6073 | R68: =SUM(R65:R67) -> 2277.7756 | S68: =SUM(S65:S67) -> 1500 | U68: =SUM(U65:U66) -> 1082.1089 | V68: =SUM(V65:V66) -> -1759.9201
B69: Cumulative Burn | F69: $k
A71: X | B71: BALANCE SHEET
B73: ASSETS
B74: Cash | F74: $k | L74: =AVERAGEIFS(Fin.Mth!$L74:$AI74,Fin.Mth!$L$7:$AI$7,">="&Fin.Qtr!L$8,Fin.Mth!$L$7:$AI$7,"<="&Fin.Qtr!L$7) -> 2509.1941 | M74: =AVERAGEIFS(Fin.Mth!$L74:$AI74,Fin.Mth!$L$7:$AI$7,">="&Fin.Qtr!M$8,Fin.Mth!$L$7:$AI$7,"<="&Fin.Qtr!M$7) -> 2336.3746 | N74: =AVERAGEIFS(Fin.Mth!$L74:$AI74,Fin.Mth!$L$7:$AI$7,">="&Fin.Qtr!N$8,Fin.Mth!$L$7:$AI$7,"<="&Fin.Qtr!N$7) -> 1834.1073 | O74: =AVERAGEIFS(Fin.Mth!$L74:$AI74,Fin.Mth!$L$7:$AI$7,">="&Fin.Qtr!O$8,Fin.Mth!$L$7:$AI$7,"<="&Fin.Qtr!O$7) -> 3463.641 | P74: =AVERAGEIFS(Fin.Mth!$L74:$AI74,Fin.Mth!$L$7:$AI$7,">="&Fin.Qtr!P$8,Fin.Mth!$L$7:$AI$7,"<="&Fin.Qtr!P$7) -> 3871.1409 | Q74: =AVERAGEIFS(Fin.Mth!$L74:$AI74,Fin.Mth!$L$7:$AI$7,">="&Fin.Qtr!Q$8,Fin.Mth!$L$7:$AI$7,"<="&Fin.Qtr!Q$7) -> 3207.4491 | R74: =AVERAGEIFS(Fin.Mth!$L74:$AI74,Fin.Mth!$L$7:$AI$7,">="&Fin.Qtr!R$8,Fin.Mth!$L$7:$AI$7,"<="&Fin.Qtr!R$7) -> 2522.0975 | S74: =AVERAGEIFS(Fin.Mth!$L74:$AI74,Fin.Mth!$L$7:$AI$7,">="&Fin.Qtr!S$8,Fin.Mth!$L$7:$AI$7,"<="&Fin.Qtr!S$7) -> 1773.8555 | U74: =AVERAGE(L74:O74) -> 2535.8293 | V74: =AVERAGE(P74:S74) -> 2843.6357
B75: Receivables | F75: $k | L75: =AVERAGEIFS(Fin.Mth!$L75:$AI75,Fin.Mth!$L$7:$AI$7,">="&Fin.Qtr!L$8,Fin.Mth!$L$7:$AI$7,"<="&Fin.Qtr!L$7) -> 3.4236678 | M75: =AVERAGEIFS(Fin.Mth!$L75:$AI75,Fin.Mth!$L$7:$AI$7,">="&Fin.Qtr!M$8,Fin.Mth!$L$7:$AI$7,"<="&Fin.Qtr!M$7) -> 5.0961978 | N75: =AVERAGEIFS(Fin.Mth!$L75:$AI75,Fin.Mth!$L$7:$AI$7,">="&Fin.Qtr!N$8,Fin.Mth!$L$7:$AI$7,"<="&Fin.Qtr!N$7) -> 5.1370512 | O75: =AVERAGEIFS(Fin.Mth!$L75:$AI75,Fin.Mth!$L$7:$AI$7,">="&Fin.Qtr!O$8,Fin.Mth!$L$7:$AI$7,"<="&Fin.Qtr!O$7) -> 5.61388 | P75: =AVERAGEIFS(Fin.Mth!$L75:$AI75,Fin.Mth!$L$7:$AI$7,">="&Fin.Qtr!P$8,Fin.Mth!$L$7:$AI$7,"<="&Fin.Qtr!P$7) -> 4.6543879 | Q75: =AVERAGEIFS(Fin.Mth!$L75:$AI75,Fin.Mth!$L$7:$AI$7,">="&Fin.Qtr!Q$8,Fin.Mth!$L$7:$AI$7,"<="&Fin.Qtr!Q$7) -> 4.1469689 | R75: =AVERAGEIFS(Fin.Mth!$L75:$AI75,Fin.Mth!$L$7:$AI$7,">="&Fin.Qtr!R$8,Fin.Mth!$L$7:$AI$7,"<="&Fin.Qtr!R$7) -> 4.6463945 | S75: =AVERAGEIFS(Fin.Mth!$L75:$AI75,Fin.Mth!$L$7:$AI$7,">="&Fin.Qtr!S$8,Fin.Mth!$L$7:$AI$7,"<="&Fin.Qtr!S$7) -> 5.2566943 | U75: =AVERAGE(L75:O75) -> 4.8176992 | V75: =AVERAGE(P75:S75) -> 4.6761114
B76: Other | F76: $k
B77: TOTAL | F77: $k | L77: =SUM(L74:L76) -> 2512.6177 | M77: =SUM(M74:M76) -> 2341.4708 | N77: =SUM(N74:N76) -> 1839.2444 | O77: =SUM(O74:O76) -> 3469.2549 | P77: =SUM(P74:P76) -> 3875.7953 | Q77: =SUM(Q74:Q76) -> 3211.5961 | R77: =SUM(R74:R76) -> 2526.7439 | S77: =SUM(S74:S76) -> 1779.1122 | U77: =AVERAGE(L77:O77) -> 2540.647 | V77: =AVERAGE(P77:S77) -> 2848.3119
B79: LIABILITIES
B80: Payables | F80: $k | L80: =AVERAGEIFS(Fin.Mth!$L80:$AI80,Fin.Mth!$L$7:$AI$7,">="&Fin.Qtr!L$8,Fin.Mth!$L$7:$AI$7,"<="&Fin.Qtr!L$7) -> 93.722906 | M80: =AVERAGEIFS(Fin.Mth!$L80:$AI80,Fin.Mth!$L$7:$AI$7,">="&Fin.Qtr!M$8,Fin.Mth!$L$7:$AI$7,"<="&Fin.Qtr!M$7) -> 139.50841 | N80: =AVERAGEIFS(Fin.Mth!$L80:$AI80,Fin.Mth!$L$7:$AI$7,">="&Fin.Qtr!N$8,Fin.Mth!$L$7:$AI$7,"<="&Fin.Qtr!N$7) -> 140.62678 | O80: =AVERAGEIFS(Fin.Mth!$L80:$AI80,Fin.Mth!$L$7:$AI$7,">="&Fin.Qtr!O$8,Fin.Mth!$L$7:$AI$7,"<="&Fin.Qtr!O$7) -> 153.67997 | P80: =AVERAGEIFS(Fin.Mth!$L80:$AI80,Fin.Mth!$L$7:$AI$7,">="&Fin.Qtr!P$8,Fin.Mth!$L$7:$AI$7,"<="&Fin.Qtr!P$7) -> 127.41387 | Q80: =AVERAGEIFS(Fin.Mth!$L80:$AI80,Fin.Mth!$L$7:$AI$7,">="&Fin.Qtr!Q$8,Fin.Mth!$L$7:$AI$7,"<="&Fin.Qtr!Q$7) -> 113.52327 | R80: =AVERAGEIFS(Fin.Mth!$L80:$AI80,Fin.Mth!$L$7:$AI$7,">="&Fin.Qtr!R$8,Fin.Mth!$L$7:$AI$7,"<="&Fin.Qtr!R$7) -> 127.19505 | S80: =AVERAGEIFS(Fin.Mth!$L80:$AI80,Fin.Mth!$L$7:$AI$7,">="&Fin.Qtr!S$8,Fin.Mth!$L$7:$AI$7,"<="&Fin.Qtr!S$7) -> 143.90201 | U80: =AVERAGE(L80:O80) -> 131.88452 | V80: =AVERAGE(P80:S80) -> 128.00855
B81: Deferred Revenue | F81: $k | L81: =AVERAGEIFS(Fin.Mth!$L81:$AI81,Fin.Mth!$L$7:$AI$7,">="&Fin.Qtr!L$8,Fin.Mth!$L$7:$AI$7,"<="&Fin.Qtr!L$7) -> 840.26021 | M81: =AVERAGEIFS(Fin.Mth!$L81:$AI81,Fin.Mth!$L$7:$AI$7,">="&Fin.Qtr!M$8,Fin.Mth!$L$7:$AI$7,"<="&Fin.Qtr!M$7) -> 1262.6064 | N81: =AVERAGEIFS(Fin.Mth!$L81:$AI81,Fin.Mth!$L$7:$AI$7,">="&Fin.Qtr!N$8,Fin.Mth!$L$7:$AI$7,"<="&Fin.Qtr!N$7) -> 1151.7558 | O81: =AVERAGEIFS(Fin.Mth!$L81:$AI81,Fin.Mth!$L$7:$AI$7,">="&Fin.Qtr!O$8,Fin.Mth!$L$7:$AI$7,"<="&Fin.Qtr!O$7) -> 1015.959 | P81: =AVERAGEIFS(Fin.Mth!$L81:$AI81,Fin.Mth!$L$7:$AI$7,">="&Fin.Qtr!P$8,Fin.Mth!$L$7:$AI$7,"<="&Fin.Qtr!P$7) -> 968.61197 | Q81: =AVERAGEIFS(Fin.Mth!$L81:$AI81,Fin.Mth!$L$7:$AI$7,">="&Fin.Qtr!Q$8,Fin.Mth!$L$7:$AI$7,"<="&Fin.Qtr!Q$7) -> 1080.6422 | R81: =AVERAGEIFS(Fin.Mth!$L81:$AI81,Fin.Mth!$L$7:$AI$7,">="&Fin.Qtr!R$8,Fin.Mth!$L$7:$AI$7,"<="&Fin.Qtr!R$7) -> 1227.0365 | S81: =AVERAGEIFS(Fin.Mth!$L81:$AI81,Fin.Mth!$L$7:$AI$7,">="&Fin.Qtr!S$8,Fin.Mth!$L$7:$AI$7,"<="&Fin.Qtr!S$7) -> 1415.7039 | U81: =AVERAGE(L81:O81) -> 1067.6453 | V81: =AVERAGE(P81:S81) -> 1172.9987
B82: Other Current Liabilities | F82: $k | L82: =AVERAGEIFS(Fin.Mth!$L82:$AI82,Fin.Mth!$L$7:$AI$7,">="&Fin.Qtr!L$8,Fin.Mth!$L$7:$AI$7,"<="&Fin.Qtr!L$7) -> 148.16882 | M82: =AVERAGEIFS(Fin.Mth!$L82:$AI82,Fin.Mth!$L$7:$AI$7,">="&Fin.Qtr!M$8,Fin.Mth!$L$7:$AI$7,"<="&Fin.Qtr!M$7) -> 215.79505 | N82: =AVERAGEIFS(Fin.Mth!$L82:$AI82,Fin.Mth!$L$7:$AI$7,">="&Fin.Qtr!N$8,Fin.Mth!$L$7:$AI$7,"<="&Fin.Qtr!N$7) -> 211.84112 | O82: =AVERAGEIFS(Fin.Mth!$L82:$AI82,Fin.Mth!$L$7:$AI$7,">="&Fin.Qtr!O$8,Fin.Mth!$L$7:$AI$7,"<="&Fin.Qtr!O$7) -> 225.31346 | P82: =AVERAGEIFS(Fin.Mth!$L82:$AI82,Fin.Mth!$L$7:$AI$7,">="&Fin.Qtr!P$8,Fin.Mth!$L$7:$AI$7,"<="&Fin.Qtr!P$7) -> 181.98885 | Q82: =AVERAGEIFS(Fin.Mth!$L82:$AI82,Fin.Mth!$L$7:$AI$7,">="&Fin.Qtr!Q$8,Fin.Mth!$L$7:$AI$7,"<="&Fin.Qtr!Q$7) -> 157.36469 | R82: =AVERAGEIFS(Fin.Mth!$L82:$AI82,Fin.Mth!$L$7:$AI$7,">="&Fin.Qtr!R$8,Fin.Mth!$L$7:$AI$7,"<="&Fin.Qtr!R$7) -> 171.22074 | S82: =AVERAGEIFS(Fin.Mth!$L82:$AI82,Fin.Mth!$L$7:$AI$7,">="&Fin.Qtr!S$8,Fin.Mth!$L$7:$AI$7,"<="&Fin.Qtr!S$7) -> 187.95083 | U82: =AVERAGE(L82:O82) -> 200.27961 | V82: =AVERAGE(P82:S82) -> 174.63128
B83: TOTAL | F83: $k | L83: =AVERAGEIFS(Fin.Mth!$L83:$AI83,Fin.Mth!$L$7:$AI$7,">="&Fin.Qtr!L$8,Fin.Mth!$L$7:$AI$7,"<="&Fin.Qtr!L$7) -> 1082.1519 | M83: =AVERAGEIFS(Fin.Mth!$L83:$AI83,Fin.Mth!$L$7:$AI$7,">="&Fin.Qtr!M$8,Fin.Mth!$L$7:$AI$7,"<="&Fin.Qtr!M$7) -> 1617.9098 | N83: =AVERAGEIFS(Fin.Mth!$L83:$AI83,Fin.Mth!$L$7:$AI$7,">="&Fin.Qtr!N$8,Fin.Mth!$L$7:$AI$7,"<="&Fin.Qtr!N$7) -> 1504.2237 | O83: =AVERAGEIFS(Fin.Mth!$L83:$AI83,Fin.Mth!$L$7:$AI$7,">="&Fin.Qtr!O$8,Fin.Mth!$L$7:$AI$7,"<="&Fin.Qtr!O$7) -> 1394.9524 | P83: =AVERAGEIFS(Fin.Mth!$L83:$AI83,Fin.Mth!$L$7:$AI$7,">="&Fin.Qtr!P$8,Fin.Mth!$L$7:$AI$7,"<="&Fin.Qtr!P$7) -> 1278.0147 | Q83: =AVERAGEIFS(Fin.Mth!$L83:$AI83,Fin.Mth!$L$7:$AI$7,">="&Fin.Qtr!Q$8,Fin.Mth!$L$7:$AI$7,"<="&Fin.Qtr!Q$7) -> 1351.5302 | R83: =AVERAGEIFS(Fin.Mth!$L83:$AI83,Fin.Mth!$L$7:$AI$7,">="&Fin.Qtr!R$8,Fin.Mth!$L$7:$AI$7,"<="&Fin.Qtr!R$7) -> 1525.4523 | S83: =AVERAGEIFS(Fin.Mth!$L83:$AI83,Fin.Mth!$L$7:$AI$7,">="&Fin.Qtr!S$8,Fin.Mth!$L$7:$AI$7,"<="&Fin.Qtr!S$7) -> 1747.5568 | U83: =AVERAGE(L83:O83) -> 1399.8095 | V83: =AVERAGE(P83:S83) -> 1475.6385
B85: NET ASSETS | F85: $k | L85: =AVERAGEIFS(Fin.Mth!$L85:$AI85,Fin.Mth!$L$7:$AI$7,">="&Fin.Qtr!L$8,Fin.Mth!$L$7:$AI$7,"<="&Fin.Qtr!L$7) -> 1430.4658 | M85: =AVERAGEIFS(Fin.Mth!$L85:$AI85,Fin.Mth!$L$7:$AI$7,">="&Fin.Qtr!M$8,Fin.Mth!$L$7:$AI$7,"<="&Fin.Qtr!M$7) -> 723.56097 | N85: =AVERAGEIFS(Fin.Mth!$L85:$AI85,Fin.Mth!$L$7:$AI$7,">="&Fin.Qtr!N$8,Fin.Mth!$L$7:$AI$7,"<="&Fin.Qtr!N$7) -> 335.02073 | O85: =AVERAGEIFS(Fin.Mth!$L85:$AI85,Fin.Mth!$L$7:$AI$7,">="&Fin.Qtr!O$8,Fin.Mth!$L$7:$AI$7,"<="&Fin.Qtr!O$7) -> 2074.3025 | P85: =AVERAGEIFS(Fin.Mth!$L85:$AI85,Fin.Mth!$L$7:$AI$7,">="&Fin.Qtr!P$8,Fin.Mth!$L$7:$AI$7,"<="&Fin.Qtr!P$7) -> 2597.7806 | Q85: =AVERAGEIFS(Fin.Mth!$L85:$AI85,Fin.Mth!$L$7:$AI$7,">="&Fin.Qtr!Q$8,Fin.Mth!$L$7:$AI$7,"<="&Fin.Qtr!Q$7) -> 1860.0659 | R85: =AVERAGEIFS(Fin.Mth!$L85:$AI85,Fin.Mth!$L$7:$AI$7,">="&Fin.Qtr!R$8,Fin.Mth!$L$7:$AI$7,"<="&Fin.Qtr!R$7) -> 1001.2916 | S85: =AVERAGEIFS(Fin.Mth!$L85:$AI85,Fin.Mth!$L$7:$AI$7,">="&Fin.Qtr!S$8,Fin.Mth!$L$7:$AI$7,"<="&Fin.Qtr!S$7) -> 31.555439 | U85: =AVERAGE(L85:O85) -> 1140.8375 | V85: =AVERAGE(P85:S85) -> 1372.6734
B87: EQUITY
B88: Contributed Equity | F88: $k | L88: =AVERAGEIFS(Fin.Mth!$L88:$AI88,Fin.Mth!$L$7:$AI$7,">="&Fin.Qtr!L$8,Fin.Mth!$L$7:$AI$7,"<="&Fin.Qtr!L$7) -> 3000 | M88: =AVERAGEIFS(Fin.Mth!$L88:$AI88,Fin.Mth!$L$7:$AI$7,">="&Fin.Qtr!M$8,Fin.Mth!$L$7:$AI$7,"<="&Fin.Qtr!M$7) -> 3000 | N88: =AVERAGEIFS(Fin.Mth!$L88:$AI88,Fin.Mth!$L$7:$AI$7,">="&Fin.Qtr!N$8,Fin.Mth!$L$7:$AI$7,"<="&Fin.Qtr!N$7) -> 3000 | O88: =AVERAGEIFS(Fin.Mth!$L88:$AI88,Fin.Mth!$L$7:$AI$7,">="&Fin.Qtr!O$8,Fin.Mth!$L$7:$AI$7,"<="&Fin.Qtr!O$7) -> 5173.2801 | P88: =AVERAGEIFS(Fin.Mth!$L88:$AI88,Fin.Mth!$L$7:$AI$7,">="&Fin.Qtr!P$8,Fin.Mth!$L$7:$AI$7,"<="&Fin.Qtr!P$7) -> 6259.9201 | Q88: =AVERAGEIFS(Fin.Mth!$L88:$AI88,Fin.Mth!$L$7:$AI$7,">="&Fin.Qtr!Q$8,Fin.Mth!$L$7:$AI$7,"<="&Fin.Qtr!Q$7) -> 6259.9201 | R88: =AVERAGEIFS(Fin.Mth!$L88:$AI88,Fin.Mth!$L$7:$AI$7,">="&Fin.Qtr!R$8,Fin.Mth!$L$7:$AI$7,"<="&Fin.Qtr!R$7) -> 6259.9201 | S88: =AVERAGEIFS(Fin.Mth!$L88:$AI88,Fin.Mth!$L$7:$AI$7,">="&Fin.Qtr!S$8,Fin.Mth!$L$7:$AI$7,"<="&Fin.Qtr!S$7) -> 6259.9201 | U88: =AVERAGE(L88:O88) -> 3543.32 | V88: =AVERAGE(P88:S88) -> 6259.9201
B89: Retained Profits / (Accumulated Losses) | F89: $k | L89: =AVERAGEIFS(Fin.Mth!$L89:$AI89,Fin.Mth!$L$7:$AI$7,">="&Fin.Qtr!L$8,Fin.Mth!$L$7:$AI$7,"<="&Fin.Qtr!L$7) -> -1569.5342 | M89: =AVERAGEIFS(Fin.Mth!$L89:$AI89,Fin.Mth!$L$7:$AI$7,">="&Fin.Qtr!M$8,Fin.Mth!$L$7:$AI$7,"<="&Fin.Qtr!M$7) -> -2276.439 | N89: =AVERAGEIFS(Fin.Mth!$L89:$AI89,Fin.Mth!$L$7:$AI$7,">="&Fin.Qtr!N$8,Fin.Mth!$L$7:$AI$7,"<="&Fin.Qtr!N$7) -> -2664.9793 | O89: =AVERAGEIFS(Fin.Mth!$L89:$AI89,Fin.Mth!$L$7:$AI$7,">="&Fin.Qtr!O$8,Fin.Mth!$L$7:$AI$7,"<="&Fin.Qtr!O$7) -> -3098.9776 | P89: =AVERAGEIFS(Fin.Mth!$L89:$AI89,Fin.Mth!$L$7:$AI$7,">="&Fin.Qtr!P$8,Fin.Mth!$L$7:$AI$7,"<="&Fin.Qtr!P$7) -> -3662.1395 | Q89: =AVERAGEIFS(Fin.Mth!$L89:$AI89,Fin.Mth!$L$7:$AI$7,">="&Fin.Qtr!Q$8,Fin.Mth!$L$7:$AI$7,"<="&Fin.Qtr!Q$7) -> -4399.8542 | R89: =AVERAGEIFS(Fin.Mth!$L89:$AI89,Fin.Mth!$L$7:$AI$7,">="&Fin.Qtr!R$8,Fin.Mth!$L$7:$AI$7,"<="&Fin.Qtr!R$7) -> -5258.6285 | S89: =AVERAGEIFS(Fin.Mth!$L89:$AI89,Fin.Mth!$L$7:$AI$7,">="&Fin.Qtr!S$8,Fin.Mth!$L$7:$AI$7,"<="&Fin.Qtr!S$7) -> -6228.3646 | U89: =AVERAGE(L89:O89) -> -2402.4825 | V89: =AVERAGE(P89:S89) -> -4887.2467
B90: TOTAL | F90: $k | L90: =SUM(L88:L89) -> 1430.4658 | M90: =SUM(M88:M89) -> 723.56097 | N90: =SUM(N88:N89) -> 335.02073 | O90: =SUM(O88:O89) -> 2074.3025 | P90: =SUM(P88:P89) -> 2597.7806 | Q90: =SUM(Q88:Q89) -> 1860.0659 | R90: =SUM(R88:R89) -> 1001.2916 | S90: =SUM(S88:S89) -> 31.555439 | U90: =AVERAGE(L90:O90) -> 1140.8375 | V90: =AVERAGE(P90:S90) -> 1372.6734
B91: CHECK | F91: $k | K91: =SUM(L91:S91) -> 0 | L91: =ROUND(L90-L85,5) -> 0 | M91: =ROUND(M90-M85,5) -> 0 | N91: =ROUND(N90-N85,5) -> 0 | O91: =ROUND(O90-O85,5) -> 0 | P91: =ROUND(P90-P85,5) -> 0 | Q91: =ROUND(Q90-Q85,5) -> 0 | R91: =ROUND(R90-R85,5) -> 0 | S91: =ROUND(S90-S85,5) -> 0 | U91: =ROUND(U90-U85,5) -> 0 | V91: =ROUND(V90-V85,5) -> 0
A93: X | B93: END OF SHEET
