Workbook

Sheet C>
B6: Project Oracle
B7: Illustrative Annual Planning and Fundraising Model
B51: END OF SHEET

Sheet INP
B3: Project Oracle
B4: Model Inputs
F6: Units | H6: Input I | I6: Input II | J6: Input III | K6: TOTAL
A10: X | B10: TIMING
B12: Model Start | F12: date | H12: 46023 | L12: =($H12=L$78)*1 -> 1 | M12: =($H12=M$78)*1 -> 0 | N12: =($H12=N$78)*1 -> 0 | O12: =($H12=O$78)*1 -> 0 | P12: =($H12=P$78)*1 -> 0 | Q12: =($H12=Q$78)*1 -> 0 | R12: =($H12=R$78)*1 -> 0 | S12: =($H12=S$78)*1 -> 0 | ... W12: =($H12=W$78)*1 -> 0
A14: X | B14: HISTORICAL FINANCIAL DATA
B16: Cash Balance
B17: Opening | F17: $k | H17: 30000
A19: X | B19: MODEL INPUTS
B21: COHORT DATA | H21: SMB | I21: Mid-Market | J21: Enterprise | K21: Total / Wt. Avg.
B22: Opening Customers | F22: # | H22: 500 | I22: 80 | J22: 20 | K22: =SUM(H22:J22) -> 600
B23: New Adds / Month | F23: # | H23: 50 | I23: 25 | J23: 10 | K23: =SUM(H23:J23) -> 85
B24: Average Seats / Customer | F24: # | H24: 10 | I24: 30 | J24: 100 | K24: =SUMPRODUCT(H24:J24,H$22:J$22)/K$22 -> 15.666667
B25: Platform Fee / Customer / Month | F25: $ | H25: 200 | I25: 400 | J25: 800 | K25: =SUMPRODUCT(H25:J25,H$22:J$22)/K$22 -> 246.66667
B26: Per Seat Fee / Month | F26: $ | H26: 25 | I26: 30 | J26: 35 | K26: =SUMPRODUCT(H26:J26,H$22:J$22)/K$22 -> 26
B27: Monthly Churn | F27: % | H27: 0.05 | I27: 0.02 | J27: 0.01 | K27: =SUMPRODUCT(H27:J27,H$22:J$22)/K$22 -> 0.044666667
B28: Monthly Seats Expansion | F28: % | H28: 0.01 | I28: 0.04 | J28: 0.07 | K28: =SUMPRODUCT(H28:J28,H$22:J$22)/K$22 -> 0.016
B30: COST STRUCTURE & MARGIN
B31: COGS | F31: % MRR | H31: 0.18
B32: Sales & Marketing | F32: % MRR | H32: 0.9
B33: Product & Engineering | F33: % MRR | H33: 0.4
B34: G&A | F34: % MRR | H34: 0.1
B35: Tax Rate | F35: % of taxable income | H35: 0.25
B37: BALANCE SHEET
B38: Opening PPE | F38: $k | H38: 50
B39: Capex | F39: % revenue | H39: 0.02
B40: Depreciation | F40: % historical cost per month | H40: =1/36 -> 0.027777778
B41: Average Net Working Capital Days | F41: days to revenue | H41: 45
B43: EQUITY
B44: Accumulated Losses | F44: $k | H44: -5898.8356
B45: Contributed Capital | F45: $k | H45: 36000
A47: X | B47: FUNDRAISING INPUTS
B49: Pre-Money Series B Valuation for Selected Peers | H49: EV ($m) | I49: Net Debt ($m) | J49: EqVal ($m) | K49: NTM ARR ($m) | L49: NTM EV / ARR (x) | M49: LTM ARR ($m) | N49: NTM / LTM ARR (x)
B50: BI Peer 1 | H50: 500 | J50: =H50-I50 -> 500 | K50: 100 | L50: =J50/K50 -> 5 | M50: 70 | N50: =K50/M50 -> 1.4285714
B51: BI Peer 2 | H51: 550 | J51: =H51-I51 -> 550 | K51: 75 | L51: =J51/K51 -> 7.3333333 | M51: 35 | N51: =K51/M51 -> 2.1428571
B52: BI Peer 3 | H52: 2000 | J52: =H52-I52 -> 2000 | K52: 250 | L52: =J52/K52 -> 8 | M52: 100 | N52: =K52/M52 -> 2.5
B53: BI Peer 4 | H53: 103 | J53: =H53-I53 -> 103 | K53: 12 | L53: =J53/K53 -> 8.5833333 | M53: 5 | N53: =K53/M53 -> 2.4
B54: MEDIAN | L54: =MEDIAN(L50:L53) -> 7.6666667 | N54: =MEDIAN(N50:N53) -> 2.2714286
B56: Project Oracle Expected NTM ARR Multiplier | F56: x | H56: =N54 -> 2.2714286
B57: Project Oracle NTM EV / ARR | F57: x | H57: =L54 -> 7.6666667
B58: Project Oracle Series B Expected Dilution | F58: % | H58: 0.15
B60: Fundraising History | I60: Seed | J60: Series A
B61: Pre-Money Valuation | I61: 15 | J61: 250
B62: Funding Amount | I62: 1 | J62: 35
B63: POST-MONEY VALUATION | I63: =SUM(I61:I62) -> 16 | J63: =SUM(J61:J62) -> 285
B64: Incoming Investor Ownership | I64: =I62/I63 -> 0.0625 | J64: =J62/J63 -> 0.12280702
B66: EQUITY OWNERSHIP OVER TIME | H66: Founding | I66: Seed | J66: Series A
B67: Founders | F67: % | H67: 0.9 | I67: =($H$72-$I$69)*$H67 -> 0.84375 | J67: =(1-$J$64)*I67 -> 0.74013158
B68: Ownership Pool for Employees | F68: % | H68: 0.1 | I68: =($H$72-$I$69)*$H68 -> 0.09375 | J68: =(1-$J$64)*I68 -> 0.082236842
B69: Seed Investors | F69: % | I69: =I64 -> 0.0625 | J69: =(1-$J$64)*I69 -> 0.054824561
B70: Series A Investors | F70: % | J70: =J64 -> 0.12280702
B71: Series B Investors | F71: %
B72: CUMULATIVE | F72: % | H72: =SUM(H67:H71) -> 1 | I72: =SUM(I67:I71) -> 1 | J72: =SUM(J67:J71) -> 1
A74: X | B74: TIME SERIES
B76: MONTHLY
B77: Period End | F77: date | L77: =EOMONTH(L78,0) -> 46053 | M77: =EOMONTH(M78,0) -> 46081 | N77: =EOMONTH(N78,0) -> 46112 | O77: =EOMONTH(O78,0) -> 46142 | P77: =EOMONTH(P78,0) -> 46173 | Q77: =EOMONTH(Q78,0) -> 46203 | R77: =EOMONTH(R78,0) -> 46234 | S77: =EOMONTH(S78,0) -> 46265 | ... W77: =EOMONTH(W78,0) -> 46387
B78: Period Start | F78: date | L78: =$H$12 -> 46023 | M78: =L77+1 -> 46054 | N78: =M77+1 -> 46082 | O78: =N77+1 -> 46113 | P78: =O77+1 -> 46143 | Q78: =P77+1 -> 46174 | R78: =Q77+1 -> 46204 | S78: =R77+1 -> 46235 | T78: =S77+1 -> 46266 | ... W78: =V77+1 -> 46357
B79: Calendar Year | F79: year | L79: =YEAR(L77) -> 2026 | M79: =YEAR(M77) -> 2026 | N79: =YEAR(N77) -> 2026 | O79: =YEAR(O77) -> 2026 | P79: =YEAR(P77) -> 2026 | Q79: =YEAR(Q77) -> 2026 | R79: =YEAR(R77) -> 2026 | S79: =YEAR(S77) -> 2026 | ... W79: =YEAR(W77) -> 2026
B80: Days in Period | F80: # | L80: =L77-L78+1 -> 31 | M80: =M77-M78+1 -> 28 | N80: =N77-N78+1 -> 31 | O80: =O77-O78+1 -> 30 | P80: =P77-P78+1 -> 31 | Q80: =Q77-Q78+1 -> 30 | R80: =R77-R78+1 -> 31 | S80: =S77-S78+1 -> 31 | ... W80: =W77-W78+1 -> 31
B82: QUARTERLY
B83: Period End | F83: date | L83: =EOMONTH(L84,2) -> 46112 | M83: =EOMONTH(M84,2) -> 46203 | N83: =EOMONTH(N84,2) -> 46295 | O83: =EOMONTH(O84,2) -> 46387
B84: Period Start | F84: date | L84: =$H$12 -> 46023 | M84: =L83+1 -> 46113 | N84: =M83+1 -> 46204 | O84: =N83+1 -> 46296
B85: Calendar Year | F85: year | L85: =YEAR(L83) -> 2026 | M85: =YEAR(M83) -> 2026 | N85: =YEAR(N83) -> 2026 | O85: =YEAR(O83) -> 2026
B86: Days in Period | F86: # | L86: =L83-L84+1 -> 90 | M86: =M83-M84+1 -> 91 | N86: =N83-N84+1 -> 92 | O86: =O83-O84+1 -> 92
A88: X | B88: END OF SHEET

Sheet SUM
B3: Project Oracle
B4: Model Dashboard
A10: X | B10: DASHBOARD
N12: Monthly | AA12: Quarterly | AF12: Annual
J13: Period End | N13: =INP!L77 -> 46053 | O13: =INP!M77 -> 46081 | P13: =INP!N77 -> 46112 | Q13: =INP!O77 -> 46142 | R13: =INP!P77 -> 46173 | S13: =INP!Q77 -> 46203 | T13: =INP!R77 -> 46234 | U13: =INP!S77 -> 46265 | ... Y13: =INP!W77 -> 46387 | AA13: =INP!L83 -> 46112 | AB13: =INP!M83 -> 46203 | AC13: =INP!N83 -> 46295 | AD13: =INP!O83 -> 46387 | AF13: =AD13 -> 46387
J14: Period Start | N14: =INP!L78 -> 46023 | O14: =INP!M78 -> 46054 | P14: =INP!N78 -> 46082 | Q14: =INP!O78 -> 46113 | R14: =INP!P78 -> 46143 | S14: =INP!Q78 -> 46174 | T14: =INP!R78 -> 46204 | U14: =INP!S78 -> 46235 | ... Y14: =INP!W78 -> 46357 | AA14: =INP!L84 -> 46023 | AB14: =INP!M84 -> 46113 | AC14: =INP!N84 -> 46204 | AD14: =INP!O84 -> 46296 | AF14: =AA14 -> 46023
J15: Calendar Year | N15: =INP!L79 -> 2026 | O15: =INP!M79 -> 2026 | P15: =INP!N79 -> 2026 | Q15: =INP!O79 -> 2026 | R15: =INP!P79 -> 2026 | S15: =INP!Q79 -> 2026 | T15: =INP!R79 -> 2026 | U15: =INP!S79 -> 2026 | ... Y15: =INP!W79 -> 2026 | AA15: =INP!L85 -> 2026 | AB15: =INP!M85 -> 2026 | AC15: =INP!N85 -> 2026 | AD15: =INP!O85 -> 2026 | AF15: =AD15 -> 2026
B17: Fundraising Summary | J17: Operating Metrics
B18: LTM ARR at End of Fiscal Year | H18: =Y21 -> 24177.299 | J18: =ROLL_Q!B60 -> Customer Volumes | N18: =ARR_M!L19 -> 658.2 | O18: =ARR_M!M19 -> 714.584 | P18: =ARR_M!N19 -> 769.22484 | Q18: =ARR_M!O19 -> 822.19204 | R18: =ARR_M!P19 -> 873.55195 | S18: =ARR_M!Q19 -> 923.36792 | T18: =ARR_M!R19 -> 971.70044 | U18: =ARR_M!S19 -> 1018.6072 | ... Y18: =ARR_M!W19 -> 1193.0442 | AA18: =ROLL_Q!L60 -> 769.22484 | AB18: =ROLL_Q!M60 -> 923.36792 | AC18: =ROLL_Q!N60 -> 1064.1435 | AD18: =ROLL_Q!O60 -> 1193.0442 | AF18: =AD18 -> 1193.0442
B19: Expected Multiplier to FY27 | H19: =INP!H56 -> 2.2714286 | J19: =ROLL_Q!B61 -> Average Seats / Customer | N19: =ARR_M!L25 -> 17.216651 | O19: =ARR_M!M25 -> 19.186894 | P19: =ARR_M!N25 -> 21.162412 | Q19: =ARR_M!O25 -> 23.172893 | R19: =ARR_M!P25 -> 25.242028 | S19: =ARR_M!Q25 -> 27.389764 | T19: =ARR_M!R25 -> 29.63371 | U19: =ARR_M!S25 -> 31.990064 | ... Y19: =ARR_M!W25 -> 42.844663 | AA19: =ROLL_Q!L61 -> 21.162412 | AB19: =ROLL_Q!M61 -> 27.389764 | AC19: =ROLL_Q!N61 -> 34.474239 | AD19: =ROLL_Q!O61 -> 42.844663 | AF19: =AD19 -> 42.844663
B20: NTM (FY27) ARR | H20: =H18*H19 -> 54917.007 | J20: =ROLL_Q!B62 -> Average ARR / Customer | N20: =ARR_M!L31 -> 9.0940747 | O20: =ARR_M!M31 -> 10.019125 | P20: =ARR_M!N31 -> 10.926345 | Q20: =ARR_M!O31 -> 11.832549 | R20: =ARR_M!P31 -> 12.750754 | S20: =ARR_M!Q31 -> 13.691555 | T20: =ARR_M!R31 -> 14.663989 | U20: =ARR_M!S31 -> 15.676091 | ... Y20: =ARR_M!W31 -> 20.265216 | AA20: =ROLL_Q!L62 -> 10.926345 | AB20: =ROLL_Q!M62 -> 13.691555 | AC20: =ROLL_Q!N62 -> 16.735276 | AD20: =ROLL_Q!O62 -> 20.265216 | AF20: =AD20 -> 20.265216
B21: NTM ARR Multiple (Pre-Money) | H21: =INP!H57 -> 7.6666667 | J21: =ROLL_Q!B63 -> ARR | N21: =ARR_M!L43 -> 5985.72 | O21: =ARR_M!M43 -> 7159.5062 | P21: =ARR_M!N43 -> 8404.8159 | Q21: =ARR_M!O43 -> 9728.6277 | R21: =ARR_M!P43 -> 11138.446 | S21: =ARR_M!Q43 -> 12642.343 | T21: =ARR_M!R43 -> 14249.004 | U21: =ARR_M!S43 -> 15967.78 | ... Y21: =ARR_M!W43 -> 24177.299 | AA21: =ROLL_Q!L63 -> 8404.8159 | AB21: =ROLL_Q!M63 -> 12642.343 | AC21: =ROLL_Q!N63 -> 17808.735 | AD21: =ROLL_Q!O63 -> 24177.299 | AF21: =AD21 -> 24177.299
B22: Enterprise Value (Pre-Money) | H22: =H20*H21 -> 421030.39
B23: Implied LTM ARR Multiple (Pre-Money) | H23: =H22/H18 -> 17.414286 | J23: SaaS Metrics
B24: Intended Dilution | H24: =INP!H58 -> 0.15 | J24: =ROLL_Q!B67 -> CAC Payback | N24: =SAAS_M!L24 -> 5.5864734 | O24: =SAAS_M!M24 -> 5.7536922 | P24: =SAAS_M!N24 -> 6.320277 | Q24: =SAAS_M!O24 -> 6.8399654 | R24: =SAAS_M!P24 -> 7.3163433 | S24: =SAAS_M!Q24 -> 7.7528076 | T24: =SAAS_M!R24 -> 8.1525621 | U24: =SAAS_M!S24 -> 8.5186162 | ... Y24: =SAAS_M!W24 -> 9.699329 | AA24: =ROLL_Q!L67 -> 6.320277 | AB24: =ROLL_Q!M67 -> 7.7528076 | AC24: =ROLL_Q!N67 -> 8.8537861 | AD24: =ROLL_Q!O67 -> 9.699329 | AF24: =AD24 -> 9.699329
B25: Fundraising Amount | H25: =H22/(1-H24)*H24 -> 74299.48 | J25: =ROLL_Q!B68 -> CAC Payback % of Customer Life | N25: =SAAS_M!L28 -> 0.24952914 | O25: =SAAS_M!M28 -> 0.25014837 | P25: =SAAS_M!N28 -> 0.26851749 | Q25: =SAAS_M!O28 -> 0.28483643 | R25: =SAAS_M!P28 -> 0.29934908 | S25: =SAAS_M!Q28 -> 0.31225961 | T25: =SAAS_M!R28 -> 0.32374305 | U25: =SAAS_M!S28 -> 0.33395196 | ... Y25: =SAAS_M!W28 -> 0.36451961 | AA25: =ROLL_Q!L68 -> 0.26851749 | AB25: =ROLL_Q!M68 -> 0.31225961 | AC25: =ROLL_Q!N68 -> 0.34302081 | AD25: =ROLL_Q!O68 -> 0.36451961 | AF25: =AD25 -> 0.36451961
B26: Enterprise Value (Post-Money) | H26: =SUM(H22,H25) -> 495329.87 | J26: =ROLL_Q!B69 -> Implied S&M Multiple on Customer Acquisition | N26: =SAAS_M!L29 -> 4.0075479 | O26: =SAAS_M!M29 -> 3.9976275 | P26: =SAAS_M!N29 -> 3.7241522 | Q26: =SAAS_M!O29 -> 3.5107869 | R26: =SAAS_M!P29 -> 3.3405815 | S26: =SAAS_M!Q29 -> 3.2024635 | T26: =SAAS_M!R29 -> 3.0888694 | U26: =SAAS_M!S29 -> 2.9944427 | ... Y26: =SAAS_M!W29 -> 2.7433366 | AA26: =ROLL_Q!L69 -> 3.7241522 | AB26: =ROLL_Q!M69 -> 3.2024635 | AC26: =ROLL_Q!N69 -> 2.915275 | AD26: =ROLL_Q!O69 -> 2.7433366 | AF26: =AD26 -> 2.7433366
J27: =ROLL_Q!B70 -> GDR (%) | N27: =SAAS_M!L38 -> 0.96580723 | O27: =SAAS_M!M38 -> 0.96793291 | P27: =SAAS_M!N38 -> 0.97007527 | Q27: =SAAS_M!O38 -> 0.97176947 | R27: =SAAS_M!P38 -> 0.9731601 | S27: =SAAS_M!Q38 -> 0.97433456 | T27: =SAAS_M!R38 -> 0.97534875 | U27: =SAAS_M!S38 -> 0.97624008 | ... Y27: =SAAS_M!W38 -> 0.97899954 | AA27: =ROLL_Q!L70 -> 0.97007527 | AB27: =ROLL_Q!M70 -> 0.97433456 | AC27: =ROLL_Q!N70 -> 0.97703454 | AD27: =ROLL_Q!O70 -> 0.97899954 | AF27: =AD27 -> 0.97899954
B28: Post-Fundraising Cash Balance | H28: =Y52+H25 -> 95654.93 | J28: =ROLL_Q!B71 -> NDR (%) | N28: =SAAS_M!L46 -> 0.96580723 | O28: =SAAS_M!M46 -> 0.99266357 | P28: =SAAS_M!N46 -> 0.99768206 | Q28: =SAAS_M!O46 -> 1.0017889 | R28: =SAAS_M!P46 -> 1.0052763 | S28: =SAAS_M!Q46 -> 1.0083205 | T28: =SAAS_M!R46 -> 1.0110336 | U28: =SAAS_M!S46 -> 1.0134905 | ... Y28: =SAAS_M!W46 -> 1.0215916 | AA28: =ROLL_Q!L71 -> 0.99768206 | AB28: =ROLL_Q!M71 -> 1.0083205 | AC28: =ROLL_Q!N71 -> 1.0157426 | AD28: =ROLL_Q!O71 -> 1.0215916 | AF28: =AD28 -> 1.0215916
B29: FY26 Cash Burn | H29: =-SUM(N49:Y49) -> 8644.5504
B30: Expected Multiplier to FY27 | H30: =H19 -> 2.2714286 | J30: Financial Summary
B31: Runway Post-Fundraising | H31: =H28/(H29*H30) -> 4.8715354
J32: Profit & Loss
B33: Cap Table | E33: Founding | F33: Seed | G33: Series A | H33: Series B | J33: =FIN_M!B15 -> MRR | N33: =FIN_M!L15 -> 498.81 | O33: =FIN_M!M15 -> 596.62552 | P33: =FIN_M!N15 -> 700.40132 | Q33: =FIN_M!O15 -> 810.71897 | R33: =FIN_M!P15 -> 928.20382 | S33: =FIN_M!Q15 -> 1053.5286 | T33: =FIN_M!R15 -> 1187.417 | U33: =FIN_M!S15 -> 1330.6483 | ... Y33: =FIN_M!W15 -> 2014.7749 | AA33: =ROLL_Q!L15 -> 1795.8368 | AB33: =ROLL_Q!M15 -> 2792.4514 | AC33: =ROLL_Q!N15 -> 4002.1266 | AD33: =ROLL_Q!O15 -> 5488.4483 | AF33: =SUM(AA33:AD33) -> 14078.863
B34: Founders | E34: =INP!H67 -> 0.9 | F34: =INP!I67 -> 0.84375 | G34: =INP!J67 -> 0.74013158 | H34: =G34/$G$39*(1-$H$24) -> 0.62911184 | J34: =FIN_M!B16 -> % revenue growth | O34: =FIN_M!M16 -> 0.19609775 | P34: =FIN_M!N16 -> 0.17393793 | Q34: =FIN_M!O16 -> 0.15750634 | R34: =FIN_M!P16 -> 0.14491439 | S34: =FIN_M!Q16 -> 0.13501855 | T34: =FIN_M!R16 -> 0.12708575 | U34: =FIN_M!S16 -> 0.12062427 | V34: =FIN_M!T16 -> 0.11529187 | ... Y34: =FIN_M!W16 -> 0.10391708 | AA34: =ROLL_Q!L16 -> 0 | AB34: =ROLL_Q!M16 -> 0.55495827 | AC34: =ROLL_Q!N16 -> 0.43319476 | AD34: =ROLL_Q!O16 -> 0.37138296
B35: Employees | E35: =INP!H68 -> 0.1 | F35: =INP!I68 -> 0.09375 | G35: =INP!J68 -> 0.082236842 | H35: =G35/$G$39*(1-$H$24) -> 0.069901316 | J35: =FIN_M!B17 -> Less: COGS | N35: =FIN_M!L17 -> -89.7858 | O35: =FIN_M!M17 -> -107.39259 | P35: =FIN_M!N17 -> -126.07224 | Q35: =FIN_M!O17 -> -145.92942 | R35: =FIN_M!P17 -> -167.07669 | S35: =FIN_M!Q17 -> -189.63514 | T35: =FIN_M!R17 -> -213.73506 | U35: =FIN_M!S17 -> -239.5167 | ... Y35: =FIN_M!W17 -> -362.65948 | AA35: =ROLL_Q!L17 -> -323.25063 | AB35: =ROLL_Q!M17 -> -502.64124 | AC35: =ROLL_Q!N17 -> -720.38279 | AD35: =ROLL_Q!O17 -> -987.92069 | AF35: =SUM(AA35:AD35) -> -2534.1954
B36: Seed Investors | E36: =INP!H69 -> 0 | F36: =INP!I69 -> 0.0625 | G36: =INP!J69 -> 0.054824561 | H36: =G36/$G$39*(1-$H$24) -> 0.046600877 | J36: =FIN_M!B18 -> Gross Profit | N36: =FIN_M!L18 -> 409.0242 | O36: =FIN_M!M18 -> 489.23292 | P36: =FIN_M!N18 -> 574.32908 | Q36: =FIN_M!O18 -> 664.78956 | R36: =FIN_M!P18 -> 761.12713 | S36: =FIN_M!Q18 -> 863.89341 | T36: =FIN_M!R18 -> 973.68196 | U36: =FIN_M!S18 -> 1091.1316 | ... Y36: =FIN_M!W18 -> 1652.1154 | AA36: =ROLL_Q!L18 -> 1472.5862 | AB36: =ROLL_Q!M18 -> 2289.8101 | AC36: =ROLL_Q!N18 -> 3281.7438 | AD36: =ROLL_Q!O18 -> 4500.5276 | AF36: =SUM(AA36:AD36) -> 11544.668
B37: Series A Investors | E37: =INP!H70 -> 0 | F37: =INP!I70 -> 0 | G37: =INP!J70 -> 0.12280702 | H37: =G37/$G$39*(1-$H$24) -> 0.10438596 | J37: =FIN_M!B19 -> % gross margin | N37: =FIN_M!L19 -> 0.82 | O37: =FIN_M!M19 -> 0.82 | P37: =FIN_M!N19 -> 0.82 | Q37: =FIN_M!O19 -> 0.82 | R37: =FIN_M!P19 -> 0.82 | S37: =FIN_M!Q19 -> 0.82 | T37: =FIN_M!R19 -> 0.82 | U37: =FIN_M!S19 -> 0.82 | ... Y37: =FIN_M!W19 -> 0.82 | AA37: =ROLL_Q!L19 -> 0.82 | AB37: =ROLL_Q!M19 -> 0.82 | AC37: =ROLL_Q!N19 -> 0.82 | AD37: =ROLL_Q!O19 -> 0.82
B38: Series B Investors | E38: =INP!H71 -> 0 | F38: =INP!I71 -> 0 | G38: =INP!J71 -> 0 | H38: =H24 -> 0.15 | J38: =FIN_M!B20 -> Less: Sales & Marketing | N38: =FIN_M!L20 -> -448.929 | O38: =FIN_M!M20 -> -536.96297 | P38: =FIN_M!N20 -> -630.36119 | Q38: =FIN_M!O20 -> -729.64708 | R38: =FIN_M!P20 -> -835.38344 | S38: =FIN_M!Q20 -> -948.1757 | T38: =FIN_M!R20 -> -1068.6753 | U38: =FIN_M!S20 -> -1197.5835 | ... Y38: =FIN_M!W20 -> -1813.2974 | AA38: =ROLL_Q!L20 -> -1616.2532 | AB38: =ROLL_Q!M20 -> -2513.2062 | AC38: =ROLL_Q!N20 -> -3601.914 | AD38: =ROLL_Q!O20 -> -4939.6034 | AF38: =SUM(AA38:AD38) -> -12670.977
B39: Total | E39: =SUM(E34:E38) -> 1 | F39: =SUM(F34:F38) -> 1 | G39: =SUM(G34:G38) -> 1 | H39: =SUM(H34:H38) -> 1 | J39: =FIN_M!B21 -> Less: Product & Engineering | N39: =FIN_M!L21 -> -199.524 | O39: =FIN_M!M21 -> -238.65021 | P39: =FIN_M!N21 -> -280.16053 | Q39: =FIN_M!O21 -> -324.28759 | R39: =FIN_M!P21 -> -371.28153 | S39: =FIN_M!Q21 -> -421.41142 | T39: =FIN_M!R21 -> -474.96681 | U39: =FIN_M!S21 -> -532.25933 | ... Y39: =FIN_M!W21 -> -805.90996 | AA39: =ROLL_Q!L21 -> -718.33474 | AB39: =ROLL_Q!M21 -> -1116.9805 | AC39: =ROLL_Q!N21 -> -1600.8507 | AD39: =ROLL_Q!O21 -> -2195.3793 | AF39: =SUM(AA39:AD39) -> -5631.5452
B40: Equity Value (Post-Money) ($m) | F40: =INP!I61 -> 15 | G40: =INP!J61 -> 250 | H40: =H26/10^3 -> 495.32987 | J40: =FIN_M!B22 -> Less: G&A | N40: =FIN_M!L22 -> -49.881 | O40: =FIN_M!M22 -> -59.662552 | P40: =FIN_M!N22 -> -70.040132 | Q40: =FIN_M!O22 -> -81.071897 | R40: =FIN_M!P22 -> -92.820382 | S40: =FIN_M!Q22 -> -105.35286 | T40: =FIN_M!R22 -> -118.7417 | U40: =FIN_M!S22 -> -133.06483 | ... Y40: =FIN_M!W22 -> -201.47749 | AA40: =ROLL_Q!L22 -> -179.58368 | AB40: =ROLL_Q!M22 -> -279.24514 | AC40: =ROLL_Q!N22 -> -400.21266 | AD40: =ROLL_Q!O22 -> -548.84483 | AF40: =SUM(AA40:AD40) -> -1407.8863
J41: =FIN_M!B23 -> EBITDA | N41: =FIN_M!L23 -> -289.3098 | O41: =FIN_M!M23 -> -346.0428 | P41: =FIN_M!N23 -> -406.23277 | Q41: =FIN_M!O23 -> -470.21701 | R41: =FIN_M!P23 -> -538.35822 | S41: =FIN_M!Q23 -> -611.04656 | T41: =FIN_M!R23 -> -688.70187 | U41: =FIN_M!S23 -> -771.77604 | ... Y41: =FIN_M!W23 -> -1168.5694 | AA41: =ROLL_Q!L23 -> -1041.5854 | AB41: =ROLL_Q!M23 -> -1619.6218 | AC41: =ROLL_Q!N23 -> -2321.2334 | AD41: =ROLL_Q!O23 -> -3183.3 | AF41: =SUM(AA41:AD41) -> -8165.7406
B42: EqVal ($m, Post-Money) | E42: Founding | F42: Seed | G42: Series A | H42: Series B | J42: =FIN_M!B24 -> % EBITDA margin | N42: =FIN_M!L24 -> -0.58 | O42: =FIN_M!M24 -> -0.58 | P42: =FIN_M!N24 -> -0.58 | Q42: =FIN_M!O24 -> -0.58 | R42: =FIN_M!P24 -> -0.58 | S42: =FIN_M!Q24 -> -0.58 | T42: =FIN_M!R24 -> -0.58 | U42: =FIN_M!S24 -> -0.58 | ... Y42: =FIN_M!W24 -> -0.58 | AA42: =ROLL_Q!L24 -> -0.58 | AB42: =ROLL_Q!M24 -> -0.58 | AC42: =ROLL_Q!N24 -> -0.58 | AD42: =ROLL_Q!O24 -> -0.58 | AF42: =AF41/AF33 -> -0.58
B43: Founders | F43: =F$40*F34 -> 12.65625 | G43: =G$40*G34 -> 185.03289 | H43: =H$40*H34 -> 311.61788
B44: Employees | F44: =F$40*F35 -> 1.40625 | G44: =G$40*G35 -> 20.559211 | H44: =H$40*H35 -> 34.624209 | J44: =FIN_M!B32 -> CASH FLOW STATEMENT
B45: Seed Investors | F45: =F$40*F36 -> 0.9375 | G45: =G$40*G36 -> 13.70614 | H45: =H$40*H36 -> 23.082806 | J45: =FIN_M!B34 -> EBITDA | N45: =FIN_M!L34 -> -289.3098 | O45: =FIN_M!M34 -> -346.0428 | P45: =FIN_M!N34 -> -406.23277 | Q45: =FIN_M!O34 -> -470.21701 | R45: =FIN_M!P34 -> -538.35822 | S45: =FIN_M!Q34 -> -611.04656 | T45: =FIN_M!R34 -> -688.70187 | U45: =FIN_M!S34 -> -771.77604 | ... Y45: =FIN_M!W34 -> -1168.5694 | AA45: =ROLL_Q!L34 -> -1041.5854 | AB45: =ROLL_Q!M34 -> -1619.6218 | AC45: =ROLL_Q!N34 -> -2321.2334 | AD45: =ROLL_Q!O34 -> -3183.3 | AF45: =SUM(AA45:AD45) -> -8165.7406
B46: Series A Investors | F46: =F$40*F37 -> 0 | G46: =G$40*G37 -> 30.701754 | H46: =H$40*H37 -> 51.705486 | J46: =FIN_M!B35 -> Less: Capex | N46: =FIN_M!L35 -> -9.9762 | O46: =FIN_M!M35 -> -11.93251 | P46: =FIN_M!N35 -> -14.008026 | Q46: =FIN_M!O35 -> -16.214379 | R46: =FIN_M!P35 -> -18.564076 | S46: =FIN_M!Q35 -> -21.070571 | T46: =FIN_M!R35 -> -23.74834 | U46: =FIN_M!S35 -> -26.612967 | ... Y46: =FIN_M!W35 -> -40.295498 | AA46: =ROLL_Q!L35 -> -35.916737 | AB46: =ROLL_Q!M35 -> -55.849027 | AC46: =ROLL_Q!N35 -> -80.042533 | AD46: =ROLL_Q!O35 -> -109.76897 | AF46: =SUM(AA46:AD46) -> -281.57726
B47: Series B Investors | F47: =F$40*F38 -> 0 | G47: =G$40*G38 -> 0 | H47: =H$40*H38 -> 74.29948 | J47: =FIN_M!B36 -> Less: Change in Net Working Capital | N47: =FIN_M!L36 -> -10.33274 | O47: =FIN_M!M36 -> -12.059447 | P47: =FIN_M!N36 -> -12.794277 | Q47: =FIN_M!O36 -> -13.600806 | R47: =FIN_M!P36 -> -14.484433 | S47: =FIN_M!Q36 -> -15.450995 | T47: =FIN_M!R36 -> -16.506798 | U47: =FIN_M!S36 -> -17.658655 | ... Y47: =FIN_M!W36 -> -23.382808 | AA47: =ROLL_Q!L36 -> -35.186464 | AB47: =ROLL_Q!M36 -> -43.536234 | AC47: =ROLL_Q!N36 -> -53.079377 | AD47: =ROLL_Q!O36 -> -65.430445 | AF47: =SUM(AA47:AD47) -> -197.23252
B48: Total | F48: =SUM(F43:F47) -> 15 | G48: =SUM(G43:G47) -> 250 | H48: =SUM(H43:H47) -> 495.32987 | J48: =FIN_M!B37 -> Less: Cash Taxes Paid | N48: =FIN_M!L37 -> 0 | O48: =FIN_M!M37 -> 0 | P48: =FIN_M!N37 -> 0 | Q48: =FIN_M!O37 -> 0 | R48: =FIN_M!P37 -> 0 | S48: =FIN_M!Q37 -> 0 | T48: =FIN_M!R37 -> 0 | U48: =FIN_M!S37 -> 0 | ... Y48: =FIN_M!W37 -> 0 | AA48: =ROLL_Q!L37 -> 0 | AB48: =ROLL_Q!M37 -> 0 | AC48: =ROLL_Q!N37 -> 0 | AD48: =ROLL_Q!O37 -> 0 | AF48: =SUM(AA48:AD48) -> 0
J49: =FIN_M!B38 -> CASH (BURN) / ACCRUAL | N49: =FIN_M!L38 -> -309.61874 | O49: =FIN_M!M38 -> -370.03476 | P49: =FIN_M!N38 -> -433.03507 | Q49: =FIN_M!O38 -> -500.03219 | R49: =FIN_M!P38 -> -571.40673 | S49: =FIN_M!Q38 -> -647.56813 | T49: =FIN_M!R38 -> -728.95701 | U49: =FIN_M!S38 -> -816.04766 | ... Y49: =FIN_M!W38 -> -1232.2477 | AA49: =ROLL_Q!L38 -> -1112.6886 | AB49: =ROLL_Q!M38 -> -1719.007 | AC49: =ROLL_Q!N38 -> -2454.3554 | AD49: =ROLL_Q!O38 -> -3358.4994 | AF49: =SUM(AA49:AD49) -> -8644.5504
J51: Balance Sheet
J52: Cash and Cash Equivalents | N52: =FIN_M!L44 -> 29690.381 | O52: =FIN_M!M44 -> 29320.347 | P52: =FIN_M!N44 -> 28887.311 | Q52: =FIN_M!O44 -> 28387.279 | R52: =FIN_M!P44 -> 27815.873 | S52: =FIN_M!Q44 -> 27168.304 | T52: =FIN_M!R44 -> 26439.347 | U52: =FIN_M!S44 -> 25623.3 | ... Y52: =FIN_M!W44 -> 21355.45 | AA52: =ROLL_Q!L44 -> 28887.311 | AB52: =ROLL_Q!M44 -> 27168.304 | AC52: =ROLL_Q!N44 -> 24713.949 | AD52: =ROLL_Q!O44 -> 21355.45 | AF52: =AD52 -> 21355.45
A55: X | B55: END OF SHEET

Sheet M>
B6: Project Oracle
B7: Monthly Calculations
B51: END OF SHEET

Sheet ARR_M
B3: Project Oracle
B4: Annual Planning Model | Monthly ARR
B6: Period End | L6: =INP!L77 -> 46053 | M6: =INP!M77 -> 46081 | N6: =INP!N77 -> 46112 | O6: =INP!O77 -> 46142 | P6: =INP!P77 -> 46173 | Q6: =INP!Q77 -> 46203 | R6: =INP!R77 -> 46234 | S6: =INP!S77 -> 46265 | ... W6: =INP!W77 -> 46387
B7: Period Start | L7: =INP!L78 -> 46023 | M7: =INP!M78 -> 46054 | N7: =INP!N78 -> 46082 | O7: =INP!O78 -> 46113 | P7: =INP!P78 -> 46143 | Q7: =INP!Q78 -> 46174 | R7: =INP!R78 -> 46204 | S7: =INP!S78 -> 46235 | ... W7: =INP!W78 -> 46357
B8: Calendar Year | L8: =INP!L79 -> 2026 | M8: =INP!M79 -> 2026 | N8: =INP!N79 -> 2026 | O8: =INP!O79 -> 2026 | P8: =INP!P79 -> 2026 | Q8: =INP!Q79 -> 2026 | R8: =INP!R79 -> 2026 | S8: =INP!S79 -> 2026 | ... W8: =INP!W79 -> 2026
B9: Days in Period | F9: Units | H9: Input I | I9: Input II | J9: Input III | K9: TOTAL | L9: =INP!L80 -> 31 | M9: =INP!M80 -> 28 | N9: =INP!N80 -> 31 | O9: =INP!O80 -> 30 | P9: =INP!P80 -> 31 | Q9: =INP!Q80 -> 30 | R9: =INP!R80 -> 31 | S9: =INP!S80 -> 31 | ... W9: =INP!W80 -> 31
A13: X | B13: SUMMARY
B15: CUSTOMER VOLUMES
B16: =B52 -> SMB | F16: # | L16: =L70 -> 525 | M16: =M70 -> 548.75 | N16: =N70 -> 571.3125 | O16: =O70 -> 592.74688 | P16: =P70 -> 613.10953 | Q16: =Q70 -> 632.45405 | R16: =R70 -> 650.83135 | S16: =S70 -> 668.28978 | ... W16: =W70 -> 729.81996
B17: =B53 -> Mid-Market | F17: # | L17: =L71 -> 103.4 | M17: =M71 -> 126.332 | N17: =N71 -> 148.80536 | O17: =O71 -> 170.82925 | P17: =P71 -> 192.41267 | Q17: =Q71 -> 213.56441 | R17: =R71 -> 234.29313 | S17: =S71 -> 254.60726 | ... W17: =W71 -> 331.88143
B18: =B54 -> Enterprise | F18: # | L18: =L72 -> 29.8 | M18: =M72 -> 39.502 | N18: =N72 -> 49.10698 | O18: =O72 -> 58.61591 | P18: =P72 -> 68.029751 | Q18: =Q72 -> 77.349454 | R18: =R72 -> 86.575959 | S18: =S72 -> 95.710199 | ... W18: =W72 -> 131.34283
B19: TOTAL | F19: # | L19: =SUM(L16:L18) -> 658.2 | M19: =SUM(M16:M18) -> 714.584 | N19: =SUM(N16:N18) -> 769.22484 | O19: =SUM(O16:O18) -> 822.19204 | P19: =SUM(P16:P18) -> 873.55195 | Q19: =SUM(Q16:Q18) -> 923.36792 | R19: =SUM(R16:R18) -> 971.70044 | S19: =SUM(S16:S18) -> 1018.6072 | ... W19: =SUM(W16:W18) -> 1193.0442
B21: AVG. SEATS / CUSTOMER
B22: =B84 -> SMB | F22: # | L22: =L84 -> 10 | M22: =M84 -> 10.1 | N22: =N84 -> 10.201 | O22: =O84 -> 10.30301 | P22: =P84 -> 10.40604 | Q22: =Q84 -> 10.510101 | R22: =R84 -> 10.615202 | S22: =S84 -> 10.721354 | ... W22: =W84 -> 11.156683
B23: =B85 -> Mid-Market | F23: # | L23: =L85 -> 30 | M23: =M85 -> 31.2 | N23: =N85 -> 32.448 | O23: =O85 -> 33.74592 | P23: =P85 -> 35.095757 | Q23: =Q85 -> 36.499587 | R23: =R85 -> 37.959571 | S23: =S85 -> 39.477953 | ... W23: =W85 -> 46.183622
B24: =B86 -> Enterprise | F24: # | L24: =L86 -> 100 | M24: =M86 -> 107 | N24: =N86 -> 114.49 | O24: =O86 -> 122.5043 | P24: =P86 -> 131.0796 | Q24: =Q86 -> 140.25517 | R24: =R86 -> 150.07304 | S24: =S86 -> 160.57815 | ... W24: =W86 -> 210.4852
B25: WEIGHTED AVERAGE | F25: # | L25: =SUMPRODUCT(L22:L24,L70:L72)/L73 -> 17.216651 | M25: =SUMPRODUCT(M22:M24,M70:M72)/M73 -> 19.186894 | N25: =SUMPRODUCT(N22:N24,N70:N72)/N73 -> 21.162412 | O25: =SUMPRODUCT(O22:O24,O70:O72)/O73 -> 23.172893 | P25: =SUMPRODUCT(P22:P24,P70:P72)/P73 -> 25.242028 | Q25: =SUMPRODUCT(Q22:Q24,Q70:Q72)/Q73 -> 27.389764 | R25: =SUMPRODUCT(R22:R24,R70:R72)/R73 -> 29.63371 | S25: =SUMPRODUCT(S22:S24,S70:S72)/S73 -> 31.990064 | ... W25: =SUMPRODUCT(W22:W24,W70:W72)/W73 -> 42.844663
B27: AVERAGE ARR / CUSTOMER
B28: =B22 -> SMB | F28: $k | L28: =L40/L16 -> 5.4 | M28: =M40/M16 -> 5.43 | N28: =N40/N16 -> 5.4603 | O28: =O40/O16 -> 5.490903 | P28: =P40/P16 -> 5.521812 | Q28: =Q40/Q16 -> 5.5530302 | R28: =R40/R16 -> 5.5845605 | S28: =S40/S16 -> 5.6164061 | ... W28: =W40/W16 -> 5.747005
B29: =B23 -> Mid-Market | F29: $k | L29: =L41/L17 -> 15.6 | M29: =M41/M17 -> 16.032 | N29: =N41/N17 -> 16.48128 | O29: =O41/O17 -> 16.948531 | P29: =P41/P17 -> 17.434472 | Q29: =Q41/Q17 -> 17.939851 | R29: =R41/R17 -> 18.465445 | S29: =S41/S17 -> 19.012063 | ... W29: =W41/W17 -> 21.426104
B30: =B24 -> Enterprise | F30: $k | L30: =L42/L18 -> 51.6 | M30: =M42/M18 -> 54.54 | N30: =N42/N18 -> 57.6858 | O30: =O42/O18 -> 61.051806 | P30: =P42/P18 -> 64.653432 | Q30: =Q42/Q18 -> 68.507173 | R30: =R42/R18 -> 72.630675 | S30: =S42/S18 -> 77.042822 | ... W30: =W42/W18 -> 98.003782
B31: =B25 -> WEIGHTED AVERAGE | F31: $k | L31: =L43/L19 -> 9.0940747 | M31: =M43/M19 -> 10.019125 | N31: =N43/N19 -> 10.926345 | O31: =O43/O19 -> 11.832549 | P31: =P43/P19 -> 12.750754 | Q31: =Q43/Q19 -> 13.691555 | R31: =R43/R19 -> 14.663989 | S31: =S43/S19 -> 15.676091 | ... W31: =W43/W19 -> 20.265216
B33: MRR
B34: =B22 -> SMB | F34: $k | L34: =L132 -> 236.25 | M34: =M132 -> 248.30937 | N34: =N132 -> 259.96147 | O34: =O132 -> 271.2263 | P34: =P132 -> 282.12297 | Q34: =Q132 -> 292.6697 | R34: =R132 -> 302.88392 | S34: =S132 -> 312.78223 | ... W34: =W132 -> 349.52325
B35: =B23 -> Mid-Market | F35: $k | L35: =L133 -> 134.42 | M35: =M133 -> 168.77955 | N35: =N133 -> 204.37523 | O35: =O133 -> 241.27541 | P35: =P133 -> 279.55111 | Q35: =Q133 -> 319.27615 | R35: =R133 -> 360.52724 | S35: =S133 -> 403.38412 | ... W35: =W133 -> 592.57717
B36: =B24 -> Enterprise | F36: $k | L36: =L134 -> 128.14 | M36: =M134 -> 179.53659 | N36: =N134 -> 236.06462 | O36: =O134 -> 298.21726 | P36: =P134 -> 366.52974 | Q36: =Q134 -> 441.5827 | R36: =R134 -> 524.00586 | S36: =S134 -> 614.48199 | ... W36: =W134 -> 1072.6745
B37: TOTAL | F37: $k | L37: =SUM(L34:L36) -> 498.81 | M37: =SUM(M34:M36) -> 596.62552 | N37: =SUM(N34:N36) -> 700.40132 | O37: =SUM(O34:O36) -> 810.71897 | P37: =SUM(P34:P36) -> 928.20382 | Q37: =SUM(Q34:Q36) -> 1053.5286 | R37: =SUM(R34:R36) -> 1187.417 | S37: =SUM(S34:S36) -> 1330.6483 | ... W37: =SUM(W34:W36) -> 2014.7749
B39: ARR
B40: =B28 -> SMB | F40: $k | L40: =L140 -> 2835 | M40: =M140 -> 2979.7125 | N40: =N140 -> 3119.5376 | O40: =O140 -> 3254.7156 | P40: =P140 -> 3385.4756 | Q40: =Q140 -> 3512.0364 | R40: =R140 -> 3634.607 | S40: =S140 -> 3753.3868 | ... W40: =W140 -> 4194.279
B41: =B29 -> Mid-Market | F41: $k | L41: =L141 -> 1613.04 | M41: =M141 -> 2025.3546 | N41: =N141 -> 2452.5028 | O41: =O141 -> 2895.3049 | P41: =P141 -> 3354.6134 | Q41: =Q141 -> 3831.3138 | R41: =R141 -> 4326.3269 | S41: =S141 -> 4840.6094 | ... W41: =W141 -> 7110.926
B42: =B30 -> Enterprise | F42: $k | L42: =L142 -> 1537.68 | M42: =M142 -> 2154.4391 | N42: =N142 -> 2832.7754 | O42: =O142 -> 3578.6072 | P42: =P142 -> 4398.3569 | Q42: =Q142 -> 5298.9924 | R42: =R142 -> 6288.0703 | S42: =S142 -> 7373.7839 | ... W42: =W142 -> 12872.094
B43: TOTAL | F43: $k | L43: =SUM(L40:L42) -> 5985.72 | M43: =SUM(M40:M42) -> 7159.5062 | N43: =SUM(N40:N42) -> 8404.8159 | O43: =SUM(O40:O42) -> 9728.6277 | P43: =SUM(P40:P42) -> 11138.446 | Q43: =SUM(Q40:Q42) -> 12642.343 | R43: =SUM(R40:R42) -> 14249.004 | S43: =SUM(S40:S42) -> 15967.78 | ... W43: =SUM(W40:W42) -> 24177.299
A45: X | B45: COHORT VOLUMES
B47: # OF CUSTOMERS
B49: Start of Model | F49: [1,0] | L49: =INP!L12 -> 1 | M49: =INP!M12 -> 0 | N49: =INP!N12 -> 0 | O49: =INP!O12 -> 0 | P49: =INP!P12 -> 0 | Q49: =INP!Q12 -> 0 | R49: =INP!R12 -> 0 | S49: =INP!S12 -> 0 | ... W49: =INP!W12 -> 0
B51: OPENING
B52: =INP!$H$21 -> SMB | F52: # | H52: =INP!H22 -> 500 | L52: =$H52*L$49+K70 -> 500 | M52: =$H52*M$49+L70 -> 525 | N52: =$H52*N$49+M70 -> 548.75 | O52: =$H52*O$49+N70 -> 571.3125 | P52: =$H52*P$49+O70 -> 592.74688 | Q52: =$H52*Q$49+P70 -> 613.10953 | R52: =$H52*R$49+Q70 -> 632.45405 | S52: =$H52*S$49+R70 -> 650.83135 | ... W52: =$H52*W$49+V70 -> 715.59995
B53: =INP!$I$21 -> Mid-Market | F53: # | H53: =INP!I22 -> 80 | L53: =$H53*L$49+K71 -> 80 | M53: =$H53*M$49+L71 -> 103.4 | N53: =$H53*N$49+M71 -> 126.332 | O53: =$H53*O$49+N71 -> 148.80536 | P53: =$H53*P$49+O71 -> 170.82925 | Q53: =$H53*Q$49+P71 -> 192.41267 | R53: =$H53*R$49+Q71 -> 213.56441 | S53: =$H53*S$49+R71 -> 234.29313 | ... W53: =$H53*W$49+V71 -> 313.14432
B54: =INP!$J$21 -> Enterprise | F54: # | H54: =INP!J22 -> 20 | L54: =$H54*L$49+K72 -> 20 | M54: =$H54*M$49+L72 -> 29.8 | N54: =$H54*N$49+M72 -> 39.502 | O54: =$H54*O$49+N72 -> 49.10698 | P54: =$H54*P$49+O72 -> 58.61591 | Q54: =$H54*Q$49+P72 -> 68.029751 | R54: =$H54*R$49+Q72 -> 77.349454 | S54: =$H54*S$49+R72 -> 86.575959 | ... W54: =$H54*W$49+V72 -> 122.56851
B55: TOTAL | F55: # | L55: =SUM(L52:L54) -> 600 | M55: =SUM(M52:M54) -> 658.2 | N55: =SUM(N52:N54) -> 714.584 | O55: =SUM(O52:O54) -> 769.22484 | P55: =SUM(P52:P54) -> 822.19204 | Q55: =SUM(Q52:Q54) -> 873.55195 | R55: =SUM(R52:R54) -> 923.36792 | S55: =SUM(S52:S54) -> 971.70044 | ... W55: =SUM(W52:W54) -> 1151.3128
B57: ADDITIONS
B58: =INP!$H$21 -> SMB | F58: =$F$52 -> # | H58: =INP!H23 -> 50 | L58: =$H58 -> 50 | M58: =$H58 -> 50 | N58: =$H58 -> 50 | O58: =$H58 -> 50 | P58: =$H58 -> 50 | Q58: =$H58 -> 50 | R58: =$H58 -> 50 | S58: =$H58 -> 50 | ... W58: =$H58 -> 50
B59: =INP!$I$21 -> Mid-Market | F59: =$F$53 -> # | H59: =INP!I23 -> 25 | L59: =$H59 -> 25 | M59: =$H59 -> 25 | N59: =$H59 -> 25 | O59: =$H59 -> 25 | P59: =$H59 -> 25 | Q59: =$H59 -> 25 | R59: =$H59 -> 25 | S59: =$H59 -> 25 | ... W59: =$H59 -> 25
B60: =INP!$J$21 -> Enterprise | F60: =$F$54 -> # | H60: =INP!J23 -> 10 | L60: =$H60 -> 10 | M60: =$H60 -> 10 | N60: =$H60 -> 10 | O60: =$H60 -> 10 | P60: =$H60 -> 10 | Q60: =$H60 -> 10 | R60: =$H60 -> 10 | S60: =$H60 -> 10 | ... W60: =$H60 -> 10
B61: TOTAL | F61: =$F$55 -> # | L61: =SUM(L58:L60) -> 85 | M61: =SUM(M58:M60) -> 85 | N61: =SUM(N58:N60) -> 85 | O61: =SUM(O58:O60) -> 85 | P61: =SUM(P58:P60) -> 85 | Q61: =SUM(Q58:Q60) -> 85 | R61: =SUM(R58:R60) -> 85 | S61: =SUM(S58:S60) -> 85 | ... W61: =SUM(W58:W60) -> 85
B63: CHURN
B64: =INP!$H$21 -> SMB | F64: =$F$52 -> # | H64: =INP!H27 -> 0.05 | L64: =-$H64*L52 -> -25 | M64: =-$H64*M52 -> -26.25 | N64: =-$H64*N52 -> -27.4375 | O64: =-$H64*O52 -> -28.565625 | P64: =-$H64*P52 -> -29.637344 | Q64: =-$H64*Q52 -> -30.655477 | R64: =-$H64*R52 -> -31.622703 | S64: =-$H64*S52 -> -32.541568 | ... W64: =-$H64*W52 -> -35.779998
B65: =INP!$I$21 -> Mid-Market | F65: =$F$53 -> # | H65: =INP!I27 -> 0.02 | L65: =-$H65*L53 -> -1.6 | M65: =-$H65*M53 -> -2.068 | N65: =-$H65*N53 -> -2.52664 | O65: =-$H65*O53 -> -2.9761072 | P65: =-$H65*P53 -> -3.4165851 | Q65: =-$H65*Q53 -> -3.8482534 | R65: =-$H65*R53 -> -4.2712883 | S65: =-$H65*S53 -> -4.6858625 | ... W65: =-$H65*W53 -> -6.2628864
B66: =INP!$J$21 -> Enterprise | F66: =$F$54 -> # | H66: =INP!J27 -> 0.01 | L66: =-$H66*L54 -> -0.2 | M66: =-$H66*M54 -> -0.298 | N66: =-$H66*N54 -> -0.39502 | O66: =-$H66*O54 -> -0.4910698 | P66: =-$H66*P54 -> -0.5861591 | Q66: =-$H66*Q54 -> -0.68029751 | R66: =-$H66*R54 -> -0.77349454 | S66: =-$H66*S54 -> -0.86575959 | ... W66: =-$H66*W54 -> -1.2256851
B67: TOTAL | F67: =$F$55 -> # | L67: =SUM(L64:L66) -> -26.8 | M67: =SUM(M64:M66) -> -28.616 | N67: =SUM(N64:N66) -> -30.35916 | O67: =SUM(O64:O66) -> -32.032802 | P67: =SUM(P64:P66) -> -33.640088 | Q67: =SUM(Q64:Q66) -> -35.184027 | R67: =SUM(R64:R66) -> -36.667486 | S67: =SUM(S64:S66) -> -38.09319 | ... W67: =SUM(W64:W66) -> -43.268569
B69: CLOSING
B70: =INP!$H$21 -> SMB | F70: =$F$52 -> # | L70: =SUM(L52,L58,L64) -> 525 | M70: =SUM(M52,M58,M64) -> 548.75 | N70: =SUM(N52,N58,N64) -> 571.3125 | O70: =SUM(O52,O58,O64) -> 592.74688 | P70: =SUM(P52,P58,P64) -> 613.10953 | Q70: =SUM(Q52,Q58,Q64) -> 632.45405 | R70: =SUM(R52,R58,R64) -> 650.83135 | S70: =SUM(S52,S58,S64) -> 668.28978 | ... W70: =SUM(W52,W58,W64) -> 729.81996
B71: =INP!$I$21 -> Mid-Market | F71: =$F$53 -> # | L71: =SUM(L53,L59,L65) -> 103.4 | M71: =SUM(M53,M59,M65) -> 126.332 | N71: =SUM(N53,N59,N65) -> 148.80536 | O71: =SUM(O53,O59,O65) -> 170.82925 | P71: =SUM(P53,P59,P65) -> 192.41267 | Q71: =SUM(Q53,Q59,Q65) -> 213.56441 | R71: =SUM(R53,R59,R65) -> 234.29313 | S71: =SUM(S53,S59,S65) -> 254.60726 | ... W71: =SUM(W53,W59,W65) -> 331.88143
B72: =INP!$J$21 -> Enterprise | F72: =$F$54 -> # | L72: =SUM(L54,L60,L66) -> 29.8 | M72: =SUM(M54,M60,M66) -> 39.502 | N72: =SUM(N54,N60,N66) -> 49.10698 | O72: =SUM(O54,O60,O66) -> 58.61591 | P72: =SUM(P54,P60,P66) -> 68.029751 | Q72: =SUM(Q54,Q60,Q66) -> 77.349454 | R72: =SUM(R54,R60,R66) -> 86.575959 | S72: =SUM(S54,S60,S66) -> 95.710199 | ... W72: =SUM(W54,W60,W66) -> 131.34283
B73: TOTAL | F73: =$F$55 -> # | L73: =SUM(L70:L72) -> 658.2 | M73: =SUM(M70:M72) -> 714.584 | N73: =SUM(N70:N72) -> 769.22484 | O73: =SUM(O70:O72) -> 822.19204 | P73: =SUM(P70:P72) -> 873.55195 | Q73: =SUM(Q70:Q72) -> 923.36792 | R73: =SUM(R70:R72) -> 971.70044 | S73: =SUM(S70:S72) -> 1018.6072 | ... W73: =SUM(W70:W72) -> 1193.0442
B75: # OF SEATS
B77: SEAT EXPANSION
B78: =INP!$H$21 -> SMB | F78: =$F$52 -> # | H78: =INP!H28 -> 0.01 | L78: =$H78 -> 0.01 | M78: =$H78 -> 0.01 | N78: =$H78 -> 0.01 | O78: =$H78 -> 0.01 | P78: =$H78 -> 0.01 | Q78: =$H78 -> 0.01 | R78: =$H78 -> 0.01 | S78: =$H78 -> 0.01 | ... W78: =$H78 -> 0.01
B79: =INP!$I$21 -> Mid-Market | F79: =$F$53 -> # | H79: =INP!I28 -> 0.04 | L79: =$H79 -> 0.04 | M79: =$H79 -> 0.04 | N79: =$H79 -> 0.04 | O79: =$H79 -> 0.04 | P79: =$H79 -> 0.04 | Q79: =$H79 -> 0.04 | R79: =$H79 -> 0.04 | S79: =$H79 -> 0.04 | ... W79: =$H79 -> 0.04
B80: =INP!$J$21 -> Enterprise | F80: =$F$54 -> # | H80: =INP!J28 -> 0.07 | L80: =$H80 -> 0.07 | M80: =$H80 -> 0.07 | N80: =$H80 -> 0.07 | O80: =$H80 -> 0.07 | P80: =$H80 -> 0.07 | Q80: =$H80 -> 0.07 | R80: =$H80 -> 0.07 | S80: =$H80 -> 0.07 | ... W80: =$H80 -> 0.07
B81: WEIGHTED AVERAGE | F81: =$F$55 -> # | L81: =SUMPRODUCT(L78:L80,L$70:L$72)/L$73 -> 0.017429353 | M81: =SUMPRODUCT(M78:M80,M$70:M$72)/M$73 -> 0.018620512 | N81: =SUMPRODUCT(N78:N80,N$70:N$72)/N$73 -> 0.019633828 | O81: =SUMPRODUCT(O78:O80,O$70:O$72)/O$73 -> 0.020510722 | P81: =SUMPRODUCT(P78:P80,P$70:P$72)/P$73 -> 0.021280571 | Q81: =SUMPRODUCT(Q78:Q80,Q$70:Q$72)/Q$73 -> 0.021964786 | R81: =SUMPRODUCT(R78:R80,R$70:R$72)/R$73 -> 0.022579341 | S81: =SUMPRODUCT(S78:S80,S$70:S$72)/S$73 -> 0.023136398 | ... W81: =SUMPRODUCT(W78:W80,W$70:W$72)/W$73 -> 0.024950839
B83: AVG. # OF SEATS
B84: =INP!$H$21 -> SMB | F84: =$F$52 -> # | H84: =INP!H24 -> 10 | L84: =$H84*L$49+K84*(1+L78) -> 10 | M84: =$H84*M$49+L84*(1+M78) -> 10.1 | N84: =$H84*N$49+M84*(1+N78) -> 10.201 | O84: =$H84*O$49+N84*(1+O78) -> 10.30301 | P84: =$H84*P$49+O84*(1+P78) -> 10.40604 | Q84: =$H84*Q$49+P84*(1+Q78) -> 10.510101 | R84: =$H84*R$49+Q84*(1+R78) -> 10.615202 | S84: =$H84*S$49+R84*(1+S78) -> 10.721354 | ... W84: =$H84*W$49+V84*(1+W78) -> 11.156683
B85: =INP!$I$21 -> Mid-Market | F85: =$F$53 -> # | H85: =INP!I24 -> 30 | L85: =$H85*L$49+K85*(1+L79) -> 30 | M85: =$H85*M$49+L85*(1+M79) -> 31.2 | N85: =$H85*N$49+M85*(1+N79) -> 32.448 | O85: =$H85*O$49+N85*(1+O79) -> 33.74592 | P85: =$H85*P$49+O85*(1+P79) -> 35.095757 | Q85: =$H85*Q$49+P85*(1+Q79) -> 36.499587 | R85: =$H85*R$49+Q85*(1+R79) -> 37.959571 | S85: =$H85*S$49+R85*(1+S79) -> 39.477953 | ... W85: =$H85*W$49+V85*(1+W79) -> 46.183622
B86: =INP!$J$21 -> Enterprise | F86: =$F$54 -> # | H86: =INP!J24 -> 100 | L86: =$H86*L$49+K86*(1+L80) -> 100 | M86: =$H86*M$49+L86*(1+M80) -> 107 | N86: =$H86*N$49+M86*(1+N80) -> 114.49 | O86: =$H86*O$49+N86*(1+O80) -> 122.5043 | P86: =$H86*P$49+O86*(1+P80) -> 131.0796 | Q86: =$H86*Q$49+P86*(1+Q80) -> 140.25517 | R86: =$H86*R$49+Q86*(1+R80) -> 150.07304 | S86: =$H86*S$49+R86*(1+S80) -> 160.57815 | ... W86: =$H86*W$49+V86*(1+W80) -> 210.4852
B87: WEIGHTED AVERAGE | F87: =$F$55 -> # | L87: =SUMPRODUCT(L84:L86,L$70:L$72)/L$73 -> 17.216651 | M87: =SUMPRODUCT(M84:M86,M$70:M$72)/M$73 -> 19.186894 | N87: =SUMPRODUCT(N84:N86,N$70:N$72)/N$73 -> 21.162412 | O87: =SUMPRODUCT(O84:O86,O$70:O$72)/O$73 -> 23.172893 | P87: =SUMPRODUCT(P84:P86,P$70:P$72)/P$73 -> 25.242028 | Q87: =SUMPRODUCT(Q84:Q86,Q$70:Q$72)/Q$73 -> 27.389764 | R87: =SUMPRODUCT(R84:R86,R$70:R$72)/R$73 -> 29.63371 | S87: =SUMPRODUCT(S84:S86,S$70:S$72)/S$73 -> 31.990064 | ... W87: =SUMPRODUCT(W84:W86,W$70:W$72)/W$73 -> 42.844663
A89: X | B89: COHORT PRICING
B91: PLATFORM FEE / CUSTOMER / MONTH
B92: =INP!$H$21 -> SMB | F92: =$F$52 -> # | H92: =INP!H25 -> 200 | L92: =$H92 -> 200 | M92: =$H92 -> 200 | N92: =$H92 -> 200 | O92: =$H92 -> 200 | P92: =$H92 -> 200 | Q92: =$H92 -> 200 | R92: =$H92 -> 200 | S92: =$H92 -> 200 | ... W92: =$H92 -> 200
B93: =INP!$I$21 -> Mid-Market | F93: =$F$53 -> # | H93: =INP!I25 -> 400 | L93: =$H93 -> 400 | M93: =$H93 -> 400 | N93: =$H93 -> 400 | O93: =$H93 -> 400 | P93: =$H93 -> 400 | Q93: =$H93 -> 400 | R93: =$H93 -> 400 | S93: =$H93 -> 400 | ... W93: =$H93 -> 400
B94: =INP!$J$21 -> Enterprise | F94: =$F$54 -> # | H94: =INP!J25 -> 800 | L94: =$H94 -> 800 | M94: =$H94 -> 800 | N94: =$H94 -> 800 | O94: =$H94 -> 800 | P94: =$H94 -> 800 | Q94: =$H94 -> 800 | R94: =$H94 -> 800 | S94: =$H94 -> 800 | ... W94: =$H94 -> 800
B95: WEIGHTED AVERAGE | F95: =$F$55 -> # | L95: =SUMPRODUCT(L92:L94,L$70:L$72)/L$73 -> 258.58402 | M95: =SUMPRODUCT(M92:M94,M$70:M$72)/M$73 -> 268.52602 | N95: =SUMPRODUCT(N92:N94,N$70:N$72)/N$73 -> 276.99343 | O95: =SUMPRODUCT(O92:O94,O$70:O$72)/O$73 -> 284.32993 | P95: =SUMPRODUCT(P92:P94,P$70:P$72)/P$73 -> 290.77924 | Q95: =SUMPRODUCT(Q92:Q94,Q$70:Q$72)/Q$73 -> 296.51901 | R95: =SUMPRODUCT(R92:R94,R$70:R$72)/R$73 -> 301.68175 | S95: =SUMPRODUCT(S92:S94,S$70:S$72)/S$73 -> 306.36835 | ... W95: =SUMPRODUCT(W92:W94,W$70:W$72)/W$73 -> 321.69036
B97: PER SEAT FEE / MONTH
B98: =INP!$H$21 -> SMB | F98: =$F$52 -> # | H98: =INP!H26 -> 25 | L98: =$H98 -> 25 | M98: =$H98 -> 25 | N98: =$H98 -> 25 | O98: =$H98 -> 25 | P98: =$H98 -> 25 | Q98: =$H98 -> 25 | R98: =$H98 -> 25 | S98: =$H98 -> 25 | ... W98: =$H98 -> 25
B99: =INP!$I$21 -> Mid-Market | F99: =$F$53 -> # | H99: =INP!I26 -> 30 | L99: =$H99 -> 30 | M99: =$H99 -> 30 | N99: =$H99 -> 30 | O99: =$H99 -> 30 | P99: =$H99 -> 30 | Q99: =$H99 -> 30 | R99: =$H99 -> 30 | S99: =$H99 -> 30 | ... W99: =$H99 -> 30
B100: =INP!$J$21 -> Enterprise | F100: =$F$54 -> # | H100: =INP!J26 -> 35 | L100: =$H100 -> 35 | M100: =$H100 -> 35 | N100: =$H100 -> 35 | O100: =$H100 -> 35 | P100: =$H100 -> 35 | Q100: =$H100 -> 35 | R100: =$H100 -> 35 | S100: =$H100 -> 35 | ... W100: =$H100 -> 35
B101: WEIGHTED AVERAGE | F101: =$F$55 -> # | L101: =SUMPRODUCT(L98:L100,L$70:L$72)/L$73 -> 26.238225 | M101: =SUMPRODUCT(M98:M100,M$70:M$72)/M$73 -> 26.436752 | N101: =SUMPRODUCT(N98:N100,N$70:N$72)/N$73 -> 26.605638 | O101: =SUMPRODUCT(O98:O100,O$70:O$72)/O$73 -> 26.751787 | P101: =SUMPRODUCT(P98:P100,P$70:P$72)/P$73 -> 26.880095 | Q101: =SUMPRODUCT(Q98:Q100,Q$70:Q$72)/Q$73 -> 26.994131 | R101: =SUMPRODUCT(R98:R100,R$70:R$72)/R$73 -> 27.096557 | S101: =SUMPRODUCT(S98:S100,S$70:S$72)/S$73 -> 27.1894 | ... W101: =SUMPRODUCT(W98:W100,W$70:W$72)/W$73 -> 27.491807
A103: X | B103: RECURRING REVENUE
B105: MRR
B107: OPENING
B108: =INP!$H$21 -> SMB | F108: $k | H108: =(H52*H92+H98*H84*H52)/10^3 -> 225 | L108: =IF(L$49,$H108,K132) -> 225 | M108: =IF(M$49,$H108,L132) -> 236.25 | N108: =IF(N$49,$H108,M132) -> 248.30937 | O108: =IF(O$49,$H108,N132) -> 259.96147 | P108: =IF(P$49,$H108,O132) -> 271.2263 | Q108: =IF(Q$49,$H108,P132) -> 282.12297 | R108: =IF(R$49,$H108,Q132) -> 292.6697 | S108: =IF(S$49,$H108,R132) -> 302.88392 | ... W108: =IF(W$49,$H108,V132) -> 340.73688
B109: =INP!$I$21 -> Mid-Market | F109: $k | H109: =(H53*H93+H99*H85*H53)/10^3 -> 104 | L109: =IF(L$49,$H109,K133) -> 104 | M109: =IF(M$49,$H109,L133) -> 134.42 | N109: =IF(N$49,$H109,M133) -> 168.77955 | O109: =IF(O$49,$H109,N133) -> 204.37523 | P109: =IF(P$49,$H109,O133) -> 241.27541 | Q109: =IF(Q$49,$H109,P133) -> 279.55111 | R109: =IF(R$49,$H109,Q133) -> 319.27615 | S109: =IF(S$49,$H109,R133) -> 360.52724 | ... W109: =IF(W$49,$H109,V133) -> 542.43481
B110: =INP!$J$21 -> Enterprise | F110: $k | H110: =(H54*H94+H100*H86*H54)/10^3 -> 86 | L110: =IF(L$49,$H110,K134) -> 86 | M110: =IF(M$49,$H110,L134) -> 128.14 | N110: =IF(N$49,$H110,M134) -> 179.53659 | O110: =IF(O$49,$H110,N134) -> 236.06462 | P110: =IF(P$49,$H110,O134) -> 298.21726 | Q110: =IF(Q$49,$H110,P134) -> 366.52974 | R110: =IF(R$49,$H110,Q134) -> 441.5827 | S110: =IF(S$49,$H110,R134) -> 524.00586 | ... W110: =IF(W$49,$H110,V134) -> 941.94265
B111: TOTAL | F111: $k | L111: =SUM(L108:L110) -> 415 | M111: =SUM(M108:M110) -> 498.81 | N111: =SUM(N108:N110) -> 596.62552 | O111: =SUM(O108:O110) -> 700.40132 | P111: =SUM(P108:P110) -> 810.71897 | Q111: =SUM(Q108:Q110) -> 928.20382 | R111: =SUM(R108:R110) -> 1053.5286 | S111: =SUM(S108:S110) -> 1187.417 | ... W111: =SUM(W108:W110) -> 1825.1143
B113: ADDITIONS
B114: =INP!$H$21 -> SMB | F114: $k | L114: =(L58*L92+L98*L84*L58)/10^3 -> 22.5 | M114: =(M58*M92+M98*M84*M58)/10^3 -> 22.625 | N114: =(N58*N92+N98*N84*N58)/10^3 -> 22.75125 | O114: =(O58*O92+O98*O84*O58)/10^3 -> 22.878762 | P114: =(P58*P92+P98*P84*P58)/10^3 -> 23.00755 | Q114: =(Q58*Q92+Q98*Q84*Q58)/10^3 -> 23.137626 | R114: =(R58*R92+R98*R84*R58)/10^3 -> 23.269002 | S114: =(S58*S92+S98*S84*S58)/10^3 -> 23.401692 | ... W114: =(W58*W92+W98*W84*W58)/10^3 -> 23.945854
B115: =INP!$I$21 -> Mid-Market | F115: $k | L115: =(L59*L93+L99*L85*L59)/10^3 -> 32.5 | M115: =(M59*M93+M99*M85*M59)/10^3 -> 33.4 | N115: =(N59*N93+N99*N85*N59)/10^3 -> 34.336 | O115: =(O59*O93+O99*O85*O59)/10^3 -> 35.30944 | P115: =(P59*P93+P99*P85*P59)/10^3 -> 36.321818 | Q115: =(Q59*Q93+Q99*Q85*Q59)/10^3 -> 37.37469 | R115: =(R59*R93+R99*R85*R59)/10^3 -> 38.469678 | S115: =(S59*S93+S99*S85*S59)/10^3 -> 39.608465 | ... W115: =(W59*W93+W99*W85*W59)/10^3 -> 44.637716
B116: =INP!$J$21 -> Enterprise | F116: $k | L116: =(L60*L94+L100*L86*L60)/10^3 -> 43 | M116: =(M60*M94+M100*M86*M60)/10^3 -> 45.45 | N116: =(N60*N94+N100*N86*N60)/10^3 -> 48.0715 | O116: =(O60*O94+O100*O86*O60)/10^3 -> 50.876505 | P116: =(P60*P94+P100*P86*P60)/10^3 -> 53.87786 | Q116: =(Q60*Q94+Q100*Q86*Q60)/10^3 -> 57.089311 | R116: =(R60*R94+R100*R86*R60)/10^3 -> 60.525562 | S116: =(S60*S94+S100*S86*S60)/10^3 -> 64.202352 | ... W116: =(W60*W94+W100*W86*W60)/10^3 -> 81.669818
B117: =B111 -> TOTAL | F117: $k | L117: =SUM(L114:L116) -> 98 | M117: =SUM(M114:M116) -> 101.475 | N117: =SUM(N114:N116) -> 105.15875 | O117: =SUM(O114:O116) -> 109.06471 | P117: =SUM(P114:P116) -> 113.20723 | Q117: =SUM(Q114:Q116) -> 117.60163 | R117: =SUM(R114:R116) -> 122.26424 | S117: =SUM(S114:S116) -> 127.21251 | ... W117: =SUM(W114:W116) -> 150.25339
B119: EXPANSION
B120: =INP!$H$21 -> SMB | F120: $k | L120: =(L84-IF(L$49,$H84,K84))*L52/10^3*L98 -> 0 | M120: =(M84-IF(M$49,$H84,L84))*M52/10^3*M98 -> 1.3125 | N120: =(N84-IF(N$49,$H84,M84))*N52/10^3*N98 -> 1.3855938 | O120: =(O84-IF(O$49,$H84,N84))*O52/10^3*O98 -> 1.4569897 | P120: =(P84-IF(P$49,$H84,O84))*P52/10^3*P98 -> 1.5267692 | Q120: =(Q84-IF(Q$49,$H84,P84))*Q52/10^3*Q98 -> 1.5950106 | R120: =(R84-IF(R$49,$H84,Q84))*R52/10^3*R98 -> 1.6617889 | S120: =(S84-IF(S$49,$H84,R84))*S52/10^3*S98 -> 1.7271765 | ... W120: =(W84-IF(W$49,$H84,V84))*W52/10^3*W98 -> 1.9761689
B121: =INP!$I$21 -> Mid-Market | F121: $k | L121: =(L85-IF(L$49,$H85,K85))*L53/10^3*L99 -> 0 | M121: =(M85-IF(M$49,$H85,L85))*M53/10^3*M99 -> 3.7224 | N121: =(N85-IF(N$49,$H85,M85))*N53/10^3*N99 -> 4.7298701 | O121: =(O85-IF(O$49,$H85,N85))*O53/10^3*O99 -> 5.7941236 | P121: =(P85-IF(P$49,$H85,O85))*P53/10^3*P99 -> 6.9177484 | Q121: =(Q85-IF(Q$49,$H85,P85))*Q53/10^3*Q99 -> 8.1034418 | R121: =(R85-IF(R$49,$H85,Q85))*R53/10^3*R99 -> 9.3540155 | S121: =(S85-IF(S$49,$H85,R85))*S53/10^3*S99 -> 10.6724 | ... W121: =(W85-IF(W$49,$H85,V85))*W53/10^3*W99 -> 16.687083
B122: =INP!$J$21 -> Enterprise | F122: $k | L122: =(L86-IF(L$49,$H86,K86))*L54/10^3*L100 -> 0 | M122: =(M86-IF(M$49,$H86,L86))*M54/10^3*M100 -> 7.301 | N122: =(N86-IF(N$49,$H86,M86))*N54/10^3*N100 -> 10.355449 | O122: =(O86-IF(O$49,$H86,N86))*O54/10^3*O100 -> 13.774532 | P122: =(P86-IF(P$49,$H86,O86))*P54/10^3*P100 -> 17.592718 | Q122: =(Q86-IF(Q$49,$H86,P86))*Q54/10^3*Q100 -> 21.847416 | R122: =(R86-IF(R$49,$H86,Q86))*R54/10^3*R100 -> 26.579219 | S122: =(S86-IF(S$49,$H86,R86))*S54/10^3*S100 -> 31.832157 | ... W122: =(W86-IF(W$49,$H86,V86))*W54/10^3*W100 -> 59.072149
B123: =B117 -> TOTAL | F123: $k | L123: =SUM(L120:L122) -> 0 | M123: =SUM(M120:M122) -> 12.3359 | N123: =SUM(N120:N122) -> 16.470913 | O123: =SUM(O120:O122) -> 21.025646 | P123: =SUM(P120:P122) -> 26.037235 | Q123: =SUM(Q120:Q122) -> 31.545868 | R123: =SUM(R120:R122) -> 37.595024 | S123: =SUM(S120:S122) -> 44.231733 | ... W123: =SUM(W120:W122) -> 77.735401
B125: CHURN
B126: =INP!$H$21 -> SMB | F126: $k | L126: =(L64*L92+L98*L84*L64)/10^3 -> -11.25 | M126: =(M64*M92+M98*M84*M64)/10^3 -> -11.878125 | N126: =(N64*N92+N98*N84*N64)/10^3 -> -12.484748 | O126: =(O64*O92+O98*O84*O64)/10^3 -> -13.070923 | P126: =(P64*P92+P98*P84*P64)/10^3 -> -13.637653 | Q126: =(Q64*Q92+Q98*Q84*Q64)/10^3 -> -14.185899 | R126: =(R64*R92+R98*R84*R64)/10^3 -> -14.716575 | S126: =(S64*S92+S98*S84*S64)/10^3 -> -15.230555 | ... W126: =(W64*W92+W98*W84*W64)/10^3 -> -17.135652
B127: =INP!$I$21 -> Mid-Market | F127: $k | L127: =(L65*L93+L99*L85*L65)/10^3 -> -2.08 | M127: =(M65*M93+M99*M85*M65)/10^3 -> -2.762848 | N127: =(N65*N93+N99*N85*N65)/10^3 -> -3.4701884 | O127: =(O65*O93+O99*O85*O65)/10^3 -> -4.2033871 | P127: =(P65*P93+P99*P85*P65)/10^3 -> -4.9638632 | Q127: =(Q65*Q93+Q99*Q85*Q65)/10^3 -> -5.7530911 | R127: =(R65*R93+R99*R85*R65)/10^3 -> -6.5726034 | S127: =(S65*S93+S99*S85*S65)/10^3 -> -7.4239929 | ... W127: =(W65*W93+W99*W85*W65)/10^3 -> -11.182438
B128: =INP!$J$21 -> Enterprise | F128: $k | L128: =(L66*L94+L100*L86*L66)/10^3 -> -0.86 | M128: =(M66*M94+M100*M86*M66)/10^3 -> -1.35441 | N128: =(N66*N94+N100*N86*N66)/10^3 -> -1.8989204 | O128: =(O66*O94+O100*O86*O66)/10^3 -> -2.4983915 | P128: =(P66*P94+P100*P86*P66)/10^3 -> -3.1580998 | Q128: =(Q66*Q94+Q100*Q86*Q66)/10^3 -> -3.8837716 | R128: =(R66*R94+R100*R86*R66)/10^3 -> -4.6816192 | S128: =(S66*S94+S100*S86*S66)/10^3 -> -5.5583802 | ... W128: =(W66*W94+W100*W86*W66)/10^3 -> -10.010148
B129: =B123 -> TOTAL | F129: $k | L129: =SUM(L126:L128) -> -14.19 | M129: =SUM(M126:M128) -> -15.995383 | N129: =SUM(N126:N128) -> -17.853857 | O129: =SUM(O126:O128) -> -19.772702 | P129: =SUM(P126:P128) -> -21.759616 | Q129: =SUM(Q126:Q128) -> -23.822761 | R129: =SUM(R126:R128) -> -25.970797 | S129: =SUM(S126:S128) -> -28.212928 | ... W129: =SUM(W126:W128) -> -38.328238
B131: CLOSING
...

Sheet FIN_M
B3: Project Oracle
B4: Annual Planning Model | Summary Monthly Financials
B6: Period End | L6: =INP!L77 -> 46053 | M6: =INP!M77 -> 46081 | N6: =INP!N77 -> 46112 | O6: =INP!O77 -> 46142 | P6: =INP!P77 -> 46173 | Q6: =INP!Q77 -> 46203 | R6: =INP!R77 -> 46234 | S6: =INP!S77 -> 46265 | ... W6: =INP!W77 -> 46387
B7: Period Start | L7: =INP!L78 -> 46023 | M7: =INP!M78 -> 46054 | N7: =INP!N78 -> 46082 | O7: =INP!O78 -> 46113 | P7: =INP!P78 -> 46143 | Q7: =INP!Q78 -> 46174 | R7: =INP!R78 -> 46204 | S7: =INP!S78 -> 46235 | ... W7: =INP!W78 -> 46357
B8: Calendar Year | L8: =INP!L79 -> 2026 | M8: =INP!M79 -> 2026 | N8: =INP!N79 -> 2026 | O8: =INP!O79 -> 2026 | P8: =INP!P79 -> 2026 | Q8: =INP!Q79 -> 2026 | R8: =INP!R79 -> 2026 | S8: =INP!S79 -> 2026 | ... W8: =INP!W79 -> 2026
B9: Days in Period | F9: Units | H9: Input I | I9: Input II | J9: Input III | K9: TOTAL | L9: =INP!L80 -> 31 | M9: =INP!M80 -> 28 | N9: =INP!N80 -> 31 | O9: =INP!O80 -> 30 | P9: =INP!P80 -> 31 | Q9: =INP!Q80 -> 30 | R9: =INP!R80 -> 31 | S9: =INP!S80 -> 31 | ... W9: =INP!W80 -> 31
A13: X | B13: PROFIT & LOSS
B15: MRR | F15: $k | L15: =ARR_M!L37 -> 498.81 | M15: =ARR_M!M37 -> 596.62552 | N15: =ARR_M!N37 -> 700.40132 | O15: =ARR_M!O37 -> 810.71897 | P15: =ARR_M!P37 -> 928.20382 | Q15: =ARR_M!Q37 -> 1053.5286 | R15: =ARR_M!R37 -> 1187.417 | S15: =ARR_M!S37 -> 1330.6483 | ... W15: =ARR_M!W37 -> 2014.7749
B16: % revenue growth | F16: % | M16: =M15/L15-1 -> 0.19609775 | N16: =N15/M15-1 -> 0.17393793 | O16: =O15/N15-1 -> 0.15750634 | P16: =P15/O15-1 -> 0.14491439 | Q16: =Q15/P15-1 -> 0.13501855 | R16: =R15/Q15-1 -> 0.12708575 | S16: =S15/R15-1 -> 0.12062427 | T16: =T15/S15-1 -> 0.11529187 | ... W16: =W15/V15-1 -> 0.10391708
B17: Less: COGS | F17: $k | L17: =-L64 -> -89.7858 | M17: =-M64 -> -107.39259 | N17: =-N64 -> -126.07224 | O17: =-O64 -> -145.92942 | P17: =-P64 -> -167.07669 | Q17: =-Q64 -> -189.63514 | R17: =-R64 -> -213.73506 | S17: =-S64 -> -239.5167 | ... W17: =-W64 -> -362.65948
B18: Gross Profit | F18: $k | L18: =SUM(L15,L17) -> 409.0242 | M18: =SUM(M15,M17) -> 489.23292 | N18: =SUM(N15,N17) -> 574.32908 | O18: =SUM(O15,O17) -> 664.78956 | P18: =SUM(P15,P17) -> 761.12713 | Q18: =SUM(Q15,Q17) -> 863.89341 | R18: =SUM(R15,R17) -> 973.68196 | S18: =SUM(S15,S17) -> 1091.1316 | ... W18: =SUM(W15,W17) -> 1652.1154
B19: % gross margin | F19: % | L19: =L18/L15 -> 0.82 | M19: =M18/M15 -> 0.82 | N19: =N18/N15 -> 0.82 | O19: =O18/O15 -> 0.82 | P19: =P18/P15 -> 0.82 | Q19: =Q18/Q15 -> 0.82 | R19: =R18/R15 -> 0.82 | S19: =S18/S15 -> 0.82 | ... W19: =W18/W15 -> 0.82
B20: Less: Sales & Marketing | F20: $k | L20: =-L65 -> -448.929 | M20: =-M65 -> -536.96297 | N20: =-N65 -> -630.36119 | O20: =-O65 -> -729.64708 | P20: =-P65 -> -835.38344 | Q20: =-Q65 -> -948.1757 | R20: =-R65 -> -1068.6753 | S20: =-S65 -> -1197.5835 | ... W20: =-W65 -> -1813.2974
B21: Less: Product & Engineering | F21: $k | L21: =-L66 -> -199.524 | M21: =-M66 -> -238.65021 | N21: =-N66 -> -280.16053 | O21: =-O66 -> -324.28759 | P21: =-P66 -> -371.28153 | Q21: =-Q66 -> -421.41142 | R21: =-R66 -> -474.96681 | S21: =-S66 -> -532.25933 | ... W21: =-W66 -> -805.90996
B22: Less: G&A | F22: $k | L22: =-L67 -> -49.881 | M22: =-M67 -> -59.662552 | N22: =-N67 -> -70.040132 | O22: =-O67 -> -81.071897 | P22: =-P67 -> -92.820382 | Q22: =-Q67 -> -105.35286 | R22: =-R67 -> -118.7417 | S22: =-S67 -> -133.06483 | ... W22: =-W67 -> -201.47749
B23: EBITDA | F23: $k | L23: =SUM(L20:L22,L18) -> -289.3098 | M23: =SUM(M20:M22,M18) -> -346.0428 | N23: =SUM(N20:N22,N18) -> -406.23277 | O23: =SUM(O20:O22,O18) -> -470.21701 | P23: =SUM(P20:P22,P18) -> -538.35822 | Q23: =SUM(Q20:Q22,Q18) -> -611.04656 | R23: =SUM(R20:R22,R18) -> -688.70187 | S23: =SUM(S20:S22,S18) -> -771.77604 | ... W23: =SUM(W20:W22,W18) -> -1168.5694
B24: % EBITDA margin | F24: % | L24: =L23/L15 -> -0.58 | M24: =M23/M15 -> -0.58 | N24: =N23/N15 -> -0.58 | O24: =O23/O15 -> -0.58 | P24: =P23/P15 -> -0.58 | Q24: =Q23/Q15 -> -0.58 | R24: =R23/R15 -> -0.58 | S24: =S23/S15 -> -0.58 | ... W24: =W23/W15 -> -0.58
B25: Less: Depreciation | F25: $k | L25: =L79 -> -1.6660056 | M25: =M79 -> -1.9974642 | N25: =N79 -> -2.386576 | O25: =O79 -> -2.8369755 | P25: =P79 -> -3.3526442 | Q25: =Q79 -> -3.9379379 | R25: =R79 -> -4.597614 | S25: =S79 -> -5.3368631 | ... W25: =W79 -> -9.2104795
B26: EBIT | F26: $k | L26: =SUM(L23,L25) -> -290.97581 | M26: =SUM(M23,M25) -> -348.04026 | N26: =SUM(N23,N25) -> -408.61934 | O26: =SUM(O23,O25) -> -473.05398 | P26: =SUM(P23,P25) -> -541.71086 | Q26: =SUM(Q23,Q25) -> -614.9845 | R26: =SUM(R23,R25) -> -693.29949 | S26: =SUM(S23,S25) -> -777.1129 | ... W26: =SUM(W23,W25) -> -1177.7799
B27: Less: Interest Expense | F27: $k
B28: EBT | F28: $k | L28: =SUM(L26:L27) -> -290.97581 | M28: =SUM(M26:M27) -> -348.04026 | N28: =SUM(N26:N27) -> -408.61934 | O28: =SUM(O26:O27) -> -473.05398 | P28: =SUM(P26:P27) -> -541.71086 | Q28: =SUM(Q26:Q27) -> -614.9845 | R28: =SUM(R26:R27) -> -693.29949 | S28: =SUM(S26:S27) -> -777.1129 | ... W28: =SUM(W26:W27) -> -1177.7799
B29: Less: Tax Expense | F29: $k | H29: =INP!$H$35 -> 0.25 | L29: =-MAX(0,L28)*$H29 -> 0 | M29: =-MAX(0,M28)*$H29 -> 0 | N29: =-MAX(0,N28)*$H29 -> 0 | O29: =-MAX(0,O28)*$H29 -> 0 | P29: =-MAX(0,P28)*$H29 -> 0 | Q29: =-MAX(0,Q28)*$H29 -> 0 | R29: =-MAX(0,R28)*$H29 -> 0 | S29: =-MAX(0,S28)*$H29 -> 0 | ... W29: =-MAX(0,W28)*$H29 -> 0
B30: PAT | F30: $k | L30: =SUM(L28:L29) -> -290.97581 | M30: =SUM(M28:M29) -> -348.04026 | N30: =SUM(N28:N29) -> -408.61934 | O30: =SUM(O28:O29) -> -473.05398 | P30: =SUM(P28:P29) -> -541.71086 | Q30: =SUM(Q28:Q29) -> -614.9845 | R30: =SUM(R28:R29) -> -693.29949 | S30: =SUM(S28:S29) -> -777.1129 | ... W30: =SUM(W28:W29) -> -1177.7799
A32: X | B32: CASH FLOW STATEMENT
B34: EBITDA | F34: $k | L34: =L23 -> -289.3098 | M34: =M23 -> -346.0428 | N34: =N23 -> -406.23277 | O34: =O23 -> -470.21701 | P34: =P23 -> -538.35822 | Q34: =Q23 -> -611.04656 | R34: =R23 -> -688.70187 | S34: =S23 -> -771.77604 | ... W34: =W23 -> -1168.5694
B35: Less: Capex | F35: $k | L35: =-L77 -> -9.9762 | M35: =-M77 -> -11.93251 | N35: =-N77 -> -14.008026 | O35: =-O77 -> -16.214379 | P35: =-P77 -> -18.564076 | Q35: =-Q77 -> -21.070571 | R35: =-R77 -> -23.74834 | S35: =-S77 -> -26.612967 | ... W35: =-W77 -> -40.295498
B36: Less: Change in Net Working Capital | F36: $k | L36: =-L88 -> -10.33274 | M36: =-M88 -> -12.059447 | N36: =-N88 -> -12.794277 | O36: =-O88 -> -13.600806 | P36: =-P88 -> -14.484433 | Q36: =-Q88 -> -15.450995 | R36: =-R88 -> -16.506798 | S36: =-S88 -> -17.658655 | ... W36: =-W88 -> -23.382808
B37: Less: Cash Taxes Paid | F37: $k | L37: =L29 -> 0 | M37: =M29 -> 0 | N37: =N29 -> 0 | O37: =O29 -> 0 | P37: =P29 -> 0 | Q37: =Q29 -> 0 | R37: =R29 -> 0 | S37: =S29 -> 0 | ... W37: =W29 -> 0
B38: CASH (BURN) / ACCRUAL | F38: $k | L38: =SUM(L34:L37) -> -309.61874 | M38: =SUM(M34:M37) -> -370.03476 | N38: =SUM(N34:N37) -> -433.03507 | O38: =SUM(O34:O37) -> -500.03219 | P38: =SUM(P34:P37) -> -571.40673 | Q38: =SUM(Q34:Q37) -> -647.56813 | R38: =SUM(R34:R37) -> -728.95701 | S38: =SUM(S34:S37) -> -816.04766 | ... W38: =SUM(W34:W37) -> -1232.2477
B40: CASH AND CASH EQUIVALENTS
B41: Opening | F41: $k | L41: =K44 -> 0 | M41: =L44 -> 29690.381 | N41: =M44 -> 29320.347 | O41: =N44 -> 28887.311 | P41: =O44 -> 28387.279 | Q41: =P44 -> 27815.873 | R41: =Q44 -> 27168.304 | S41: =R44 -> 26439.347 | ... W41: =V44 -> 22587.697
B42: Add: Rollforward of Historical Balance | F42: $k | H42: =INP!$H$17 -> 30000 | L42: =$H42*L$60 -> 30000 | M42: =$H42*M$60 -> 0 | N42: =$H42*N$60 -> 0 | O42: =$H42*O$60 -> 0 | P42: =$H42*P$60 -> 0 | Q42: =$H42*Q$60 -> 0 | R42: =$H42*R$60 -> 0 | S42: =$H42*S$60 -> 0 | ... W42: =$H42*W$60 -> 0
B43: Add / Less: Cash (Burn) / Accrual | F43: $k | L43: =L38 -> -309.61874 | M43: =M38 -> -370.03476 | N43: =N38 -> -433.03507 | O43: =O38 -> -500.03219 | P43: =P38 -> -571.40673 | Q43: =Q38 -> -647.56813 | R43: =R38 -> -728.95701 | S43: =S38 -> -816.04766 | ... W43: =W38 -> -1232.2477
B44: CLOSING | F44: $k | L44: =SUM(L41:L43) -> 29690.381 | M44: =SUM(M41:M43) -> 29320.347 | N44: =SUM(N41:N43) -> 28887.311 | O44: =SUM(O41:O43) -> 28387.279 | P44: =SUM(P41:P43) -> 27815.873 | Q44: =SUM(Q41:Q43) -> 27168.304 | R44: =SUM(R41:R43) -> 26439.347 | S44: =SUM(S41:S43) -> 25623.3 | ... W44: =SUM(W41:W43) -> 21355.45
A46: X | B46: BALANCE SHEET
B48: Cash and Cash Equivalents | F48: $k | L48: =L44 -> 29690.381 | M48: =M44 -> 29320.347 | N48: =N44 -> 28887.311 | O48: =O44 -> 28387.279 | P48: =P44 -> 27815.873 | Q48: =Q44 -> 27168.304 | R48: =R44 -> 26439.347 | S48: =S44 -> 25623.3 | ... W48: =W44 -> 21355.45
B49: Fixed Assets | F49: $k | L49: =L80 -> 58.310194 | M49: =M80 -> 68.245241 | N49: =N80 -> 79.866691 | O49: =O80 -> 93.244095 | P49: =P80 -> 108.45553 | Q49: =Q80 -> 125.58816 | R49: =R80 -> 144.73889 | S49: =S80 -> 166.01499 | ... W49: =W80 -> 274.92499
B50: Net Working Capital | F50: $k | L50: =L92 -> 61.497123 | M50: =M92 -> 73.556571 | N50: =N92 -> 86.350848 | O50: =O92 -> 99.951654 | P50: =P92 -> 114.43609 | Q50: =Q92 -> 129.88708 | R50: =R92 -> 146.39388 | S50: =S92 -> 164.05253 | ... W50: =W92 -> 248.3969
B51: NET ASSETS | F51: $k | L51: =SUM(L48:L50) -> 29810.189 | M51: =SUM(M48:M50) -> 29462.148 | N51: =SUM(N48:N50) -> 29053.529 | O51: =SUM(O48:O50) -> 28580.475 | P51: =SUM(P48:P50) -> 28038.764 | Q51: =SUM(Q48:Q50) -> 27423.78 | R51: =SUM(R48:R50) -> 26730.48 | S51: =SUM(S48:S50) -> 25953.367 | ... W51: =SUM(W48:W50) -> 21878.772
B53: Accumulated Losses | F53: $k | L53: =L101 -> -6189.8114 | M53: =M101 -> -6537.8517 | N53: =N101 -> -6946.471 | O53: =O101 -> -7419.525 | P53: =P101 -> -7961.2359 | Q53: =Q101 -> -8576.2204 | R53: =R101 -> -9269.5199 | S53: =S101 -> -10046.633 | ... W53: =W101 -> -14121.228
B54: Contributed Capital | F54: $k | H54: =INP!H45 -> 36000 | L54: =$H54 -> 36000 | M54: =$H54 -> 36000 | N54: =$H54 -> 36000 | O54: =$H54 -> 36000 | P54: =$H54 -> 36000 | Q54: =$H54 -> 36000 | R54: =$H54 -> 36000 | S54: =$H54 -> 36000 | ... W54: =$H54 -> 36000
B55: TOTAL EQUITY | F55: $k | L55: =SUM(L53:L54) -> 29810.189 | M55: =SUM(M53:M54) -> 29462.148 | N55: =SUM(N53:N54) -> 29053.529 | O55: =SUM(O53:O54) -> 28580.475 | P55: =SUM(P53:P54) -> 28038.764 | Q55: =SUM(Q53:Q54) -> 27423.78 | R55: =SUM(R53:R54) -> 26730.48 | S55: =SUM(S53:S54) -> 25953.367 | ... W55: =SUM(W53:W54) -> 21878.772
B56: Check | F56: $k | L56: =L55-L51 -> 0 | M56: =M55-M51 -> 0 | N56: =N55-N51 -> 0 | O56: =O55-O51 -> 0 | P56: =P55-P51 -> 0 | Q56: =Q55-Q51 -> 0 | R56: =R55-R51 -> 0 | S56: =S55-S51 -> 0 | ... W56: =W55-W51 -> 0
A58: X | B58: SUPPORTING SCHEDULES
B60: =ARR_M!B49 -> Start of Model | F60: =ARR_M!F49 -> [1,0] | L60: =ARR_M!L49 -> 1 | M60: =ARR_M!M49 -> 0 | N60: =ARR_M!N49 -> 0 | O60: =ARR_M!O49 -> 0 | P60: =ARR_M!P49 -> 0 | Q60: =ARR_M!Q49 -> 0 | R60: =ARR_M!R49 -> 0 | S60: =ARR_M!S49 -> 0 | ... W60: =ARR_M!W49 -> 0
B62: COST STRUCTURE
B64: =INP!B31 -> COGS | F64: =INP!F31 -> % MRR | H64: =INP!H31 -> 0.18 | L64: =$H64*L$15 -> 89.7858 | M64: =$H64*M$15 -> 107.39259 | N64: =$H64*N$15 -> 126.07224 | O64: =$H64*O$15 -> 145.92942 | P64: =$H64*P$15 -> 167.07669 | Q64: =$H64*Q$15 -> 189.63514 | R64: =$H64*R$15 -> 213.73506 | S64: =$H64*S$15 -> 239.5167 | ... W64: =$H64*W$15 -> 362.65948
B65: =INP!B32 -> Sales & Marketing | F65: =INP!F32 -> % MRR | H65: =INP!H32 -> 0.9 | L65: =$H65*L$15 -> 448.929 | M65: =$H65*M$15 -> 536.96297 | N65: =$H65*N$15 -> 630.36119 | O65: =$H65*O$15 -> 729.64708 | P65: =$H65*P$15 -> 835.38344 | Q65: =$H65*Q$15 -> 948.1757 | R65: =$H65*R$15 -> 1068.6753 | S65: =$H65*S$15 -> 1197.5835 | ... W65: =$H65*W$15 -> 1813.2974
B66: =INP!B33 -> Product & Engineering | F66: =INP!F33 -> % MRR | H66: =INP!H33 -> 0.4 | L66: =$H66*L$15 -> 199.524 | M66: =$H66*M$15 -> 238.65021 | N66: =$H66*N$15 -> 280.16053 | O66: =$H66*O$15 -> 324.28759 | P66: =$H66*P$15 -> 371.28153 | Q66: =$H66*Q$15 -> 421.41142 | R66: =$H66*R$15 -> 474.96681 | S66: =$H66*S$15 -> 532.25933 | ... W66: =$H66*W$15 -> 805.90996
B67: =INP!B34 -> G&A | F67: =INP!F34 -> % MRR | H67: =INP!H34 -> 0.1 | L67: =$H67*L$15 -> 49.881 | M67: =$H67*M$15 -> 59.662552 | N67: =$H67*N$15 -> 70.040132 | O67: =$H67*O$15 -> 81.071897 | P67: =$H67*P$15 -> 92.820382 | Q67: =$H67*Q$15 -> 105.35286 | R67: =$H67*R$15 -> 118.7417 | S67: =$H67*S$15 -> 133.06483 | ... W67: =$H67*W$15 -> 201.47749
B69: FIXED ASSET SCHEDULE
B71: Depreciation Period Counter | F71: # | L71: =COLUMNS($L60:L60) -> 1 | M71: =COLUMNS($L60:M60) -> 2 | N71: =COLUMNS($L60:N60) -> 3 | O71: =COLUMNS($L60:O60) -> 4 | P71: =COLUMNS($L60:P60) -> 5 | Q71: =COLUMNS($L60:Q60) -> 6 | R71: =COLUMNS($L60:R60) -> 7 | S71: =COLUMNS($L60:S60) -> 8 | ... W71: =COLUMNS($L60:W60) -> 12
B72: Incremental Additions to PPE | F72: $k | L72: =SUM(L77:L78) -> 59.9762 | M72: =SUM(M77:M78) -> 11.93251 | N72: =SUM(N77:N78) -> 14.008026 | O72: =SUM(O77:O78) -> 16.214379 | P72: =SUM(P77:P78) -> 18.564076 | Q72: =SUM(Q77:Q78) -> 21.070571 | R72: =SUM(R77:R78) -> 23.74834 | S72: =SUM(S77:S78) -> 26.612967 | ... W72: =SUM(W77:W78) -> 40.295498
B73: Historical Cost Base to Depreciate | F73: $k | H73: =1/H79 -> 36 | L73: =SUMIF($L71:L71,">"&MIN(L71-$H73/12,L71),$L72:L72) -> 59.9762 | M73: =SUMIF($L71:M71,">"&MIN(M71-$H73,M71),$L72:M72) -> 71.90871 | N73: =SUMIF($L71:N71,">"&MIN(N71-$H73,N71),$L72:N72) -> 85.916737 | O73: =SUMIF($L71:O71,">"&MIN(O71-$H73,O71),$L72:O72) -> 102.13112 | P73: =SUMIF($L71:P71,">"&MIN(P71-$H73,P71),$L72:P72) -> 120.69519 | Q73: =SUMIF($L71:Q71,">"&MIN(Q71-$H73,Q71),$L72:Q72) -> 141.76576 | R73: =SUMIF($L71:R71,">"&MIN(R71-$H73,R71),$L72:R72) -> 165.5141 | S73: =SUMIF($L71:S71,">"&MIN(S71-$H73,S71),$L72:S72) -> 192.12707 | T73: =SUMIF($L71:T71,">"&MIN(T71-$H73,T71),$L72:T72) -> 221.8083 | ... W73: =SUMIF($L71:W71,">"&MIN(W71-$H73,W71),$L72:W72) -> 331.57726
B75: BALANCE
B76: Opening | L76: =K80 -> 0 | M76: =L80 -> 58.310194 | N76: =M80 -> 68.245241 | O76: =N80 -> 79.866691 | P76: =O80 -> 93.244095 | Q76: =P80 -> 108.45553 | R76: =Q80 -> 125.58816 | S76: =R80 -> 144.73889 | ... W76: =V80 -> 243.83997
B77: Add: Capex | F77: $k | H77: =INP!H39 -> 0.02 | L77: =$H77*ARR_M!L$135 -> 9.9762 | M77: =$H77*ARR_M!M$135 -> 11.93251 | N77: =$H77*ARR_M!N$135 -> 14.008026 | O77: =$H77*ARR_M!O$135 -> 16.214379 | P77: =$H77*ARR_M!P$135 -> 18.564076 | Q77: =$H77*ARR_M!Q$135 -> 21.070571 | R77: =$H77*ARR_M!R$135 -> 23.74834 | S77: =$H77*ARR_M!S$135 -> 26.612967 | ... W77: =$H77*ARR_M!W$135 -> 40.295498
B78: Add: Rollforward of Historical Balance | F78: $k | H78: =INP!H38 -> 50 | L78: =$H78*L$60 -> 50 | M78: =$H78*M$60 -> 0 | N78: =$H78*N$60 -> 0 | O78: =$H78*O$60 -> 0 | P78: =$H78*P$60 -> 0 | Q78: =$H78*Q$60 -> 0 | R78: =$H78*R$60 -> 0 | S78: =$H78*S$60 -> 0 | ... W78: =$H78*W$60 -> 0
B79: Less: Depreciation | F79: $k | H79: =INP!H40 -> 0.027777778 | L79: =-$H79*L73 -> -1.6660056 | M79: =-$H79*M73 -> -1.9974642 | N79: =-$H79*N73 -> -2.386576 | O79: =-$H79*O73 -> -2.8369755 | P79: =-$H79*P73 -> -3.3526442 | Q79: =-$H79*Q73 -> -3.9379379 | R79: =-$H79*R73 -> -4.597614 | S79: =-$H79*S73 -> -5.3368631 | ... W79: =-$H79*W73 -> -9.2104795
B80: CLOSING | L80: =SUM(L76:L79) -> 58.310194 | M80: =SUM(M76:M79) -> 68.245241 | N80: =SUM(N76:N79) -> 79.866691 | O80: =SUM(O76:O79) -> 93.244095 | P80: =SUM(P76:P79) -> 108.45553 | Q80: =SUM(Q76:Q79) -> 125.58816 | R80: =SUM(R76:R79) -> 144.73889 | S80: =SUM(S76:S79) -> 166.01499 | ... W80: =SUM(W76:W79) -> 274.92499
B82: NET WORKING CAPITAL
B84: Opening MRR [A] | F84: $k | L84: =ARR_M!L111 -> 415 | M84: =ARR_M!M111 -> 498.81 | N84: =ARR_M!N111 -> 596.62552 | O84: =ARR_M!O111 -> 700.40132 | P84: =ARR_M!P111 -> 810.71897 | Q84: =ARR_M!Q111 -> 928.20382 | R84: =ARR_M!R111 -> 1053.5286 | S84: =ARR_M!S111 -> 1187.417 | ... W84: =ARR_M!W111 -> 1825.1143
B85: Closing MRR [B] | F85: $k | L85: =L15 -> 498.81 | M85: =M15 -> 596.62552 | N85: =N15 -> 700.40132 | O85: =O15 -> 810.71897 | P85: =P15 -> 928.20382 | Q85: =Q15 -> 1053.5286 | R85: =R15 -> 1187.417 | S85: =S15 -> 1330.6483 | ... W85: =W15 -> 2014.7749
B86: iMRR [B - A] | F86: $k | L86: =L85-L84 -> 83.81 | M86: =M85-M84 -> 97.815517 | N86: =N85-N84 -> 103.77581 | O86: =O85-O84 -> 110.31765 | P86: =P85-P84 -> 117.48485 | Q86: =Q85-Q84 -> 125.32473 | R86: =R85-R84 -> 133.88847 | S86: =S85-S84 -> 143.23131 | ... W86: =W85-W84 -> 189.66055
B87: Net Working Capital Days | F87: # | H87: =INP!H41 -> 45 | L87: =$H87 -> 45 | M87: =$H87 -> 45 | N87: =$H87 -> 45 | O87: =$H87 -> 45 | P87: =$H87 -> 45 | Q87: =$H87 -> 45 | R87: =$H87 -> 45 | S87: =$H87 -> 45 | ... W87: =$H87 -> 45
B88: CHANGE IN NET WORKING CAPITAL | F88: $k | L88: =L87/SUM($L$9:$W$9)*L86 -> 10.33274 | M88: =M87/SUM($L$9:$W$9)*M86 -> 12.059447 | N88: =N87/SUM($L$9:$W$9)*N86 -> 12.794277 | O88: =O87/SUM($L$9:$W$9)*O86 -> 13.600806 | P88: =P87/SUM($L$9:$W$9)*P86 -> 14.484433 | Q88: =Q87/SUM($L$9:$W$9)*Q86 -> 15.450995 | R88: =R87/SUM($L$9:$W$9)*R86 -> 16.506798 | S88: =S87/SUM($L$9:$W$9)*S86 -> 17.658655 | ... W88: =W87/SUM($L$9:$W$9)*W86 -> 23.382808
B90: MRR | F90: $k | L90: =L15 -> 498.81 | M90: =M15 -> 596.62552 | N90: =N15 -> 700.40132 | O90: =O15 -> 810.71897 | P90: =P15 -> 928.20382 | Q90: =Q15 -> 1053.5286 | R90: =R15 -> 1187.417 | S90: =S15 -> 1330.6483 | ... W90: =W15 -> 2014.7749
B91: Net Working Capital Days | F91: $k | L91: =L87 -> 45 | M91: =M87 -> 45 | N91: =N87 -> 45 | O91: =O87 -> 45 | P91: =P87 -> 45 | Q91: =Q87 -> 45 | R91: =R87 -> 45 | S91: =S87 -> 45 | ... W91: =W87 -> 45
B92: TOTAL NET WORKING CAPITAL | F92: $k | L92: =L91/SUM($L$9:$W$9)*L90 -> 61.497123 | M92: =M91/SUM($L$9:$W$9)*M90 -> 73.556571 | N92: =N91/SUM($L$9:$W$9)*N90 -> 86.350848 | O92: =O91/SUM($L$9:$W$9)*O90 -> 99.951654 | P92: =P91/SUM($L$9:$W$9)*P90 -> 114.43609 | Q92: =Q91/SUM($L$9:$W$9)*Q90 -> 129.88708 | R92: =R91/SUM($L$9:$W$9)*R90 -> 146.39388 | S92: =S91/SUM($L$9:$W$9)*S90 -> 164.05253 | ... W92: =W91/SUM($L$9:$W$9)*W90 -> 248.3969
B93: Check | F93: $k | M93: =M92-L92-M88 -> 0 | N93: =N92-M92-N88 -> 0 | O93: =O92-N92-O88 -> 0 | P93: =P92-O92-P88 -> 0 | Q93: =Q92-P92-Q88 -> 0 | R93: =R92-Q92-R88 -> 0 | S93: =S92-R92-S88 -> 0 | T93: =T92-S92-T88 -> 0 | ... W93: =W92-V92-W88 -> 0
B95: EQUITY ACCOUNTS
B97: ACCUMULATED LOSSES
B98: Opening | F98: $k | L98: =K101 -> 0 | M98: =L101 -> -6189.8114 | N98: =M101 -> -6537.8517 | O98: =N101 -> -6946.471 | P98: =O101 -> -7419.525 | Q98: =P101 -> -7961.2359 | R98: =Q101 -> -8576.2204 | S98: =R101 -> -9269.5199 | ... W98: =V101 -> -12943.449
B99: Add: Rollforward of Historical Balance | F99: $k | H99: =INP!H44 -> -5898.8356 | L99: =$H99*L60 -> -5898.8356 | M99: =$H99*M60 -> 0 | N99: =$H99*N60 -> 0 | O99: =$H99*O60 -> 0 | P99: =$H99*P60 -> 0 | Q99: =$H99*Q60 -> 0 | R99: =$H99*R60 -> 0 | S99: =$H99*S60 -> 0 | ... W99: =$H99*W60 -> 0
B100: Add / Less: PAT | F100: $k | L100: =L30 -> -290.97581 | M100: =M30 -> -348.04026 | N100: =N30 -> -408.61934 | O100: =O30 -> -473.05398 | P100: =P30 -> -541.71086 | Q100: =Q30 -> -614.9845 | R100: =R30 -> -693.29949 | S100: =S30 -> -777.1129 | ... W100: =W30 -> -1177.7799
B101: CLOSING | F101: $k | L101: =SUM(L98:L100) -> -6189.8114 | M101: =SUM(M98:M100) -> -6537.8517 | N101: =SUM(N98:N100) -> -6946.471 | O101: =SUM(O98:O100) -> -7419.525 | P101: =SUM(P98:P100) -> -7961.2359 | Q101: =SUM(Q98:Q100) -> -8576.2204 | R101: =SUM(R98:R100) -> -9269.5199 | S101: =SUM(S98:S100) -> -10046.633 | ... W101: =SUM(W98:W100) -> -14121.228
A103: X | B103: END OF SHEET

Sheet SAAS_M
B3: Project Oracle
B4: Annual Planning Model | Monthly SaaS Metrics
B6: Period End | L6: =INP!L77 -> 46053 | M6: =INP!M77 -> 46081 | N6: =INP!N77 -> 46112 | O6: =INP!O77 -> 46142 | P6: =INP!P77 -> 46173 | Q6: =INP!Q77 -> 46203 | R6: =INP!R77 -> 46234 | S6: =INP!S77 -> 46265 | ... W6: =INP!W77 -> 46387
B7: Period Start | L7: =INP!L78 -> 46023 | M7: =INP!M78 -> 46054 | N7: =INP!N78 -> 46082 | O7: =INP!O78 -> 46113 | P7: =INP!P78 -> 46143 | Q7: =INP!Q78 -> 46174 | R7: =INP!R78 -> 46204 | S7: =INP!S78 -> 46235 | ... W7: =INP!W78 -> 46357
B8: Calendar Year | L8: =INP!L79 -> 2026 | M8: =INP!M79 -> 2026 | N8: =INP!N79 -> 2026 | O8: =INP!O79 -> 2026 | P8: =INP!P79 -> 2026 | Q8: =INP!Q79 -> 2026 | R8: =INP!R79 -> 2026 | S8: =INP!S79 -> 2026 | ... W8: =INP!W79 -> 2026
B9: Days in Period | F9: Units | H9: Input I | I9: Input II | J9: Input III | K9: TOTAL | L9: =INP!L80 -> 31 | M9: =INP!M80 -> 28 | N9: =INP!N80 -> 31 | O9: =INP!O80 -> 30 | P9: =INP!P80 -> 31 | Q9: =INP!Q80 -> 30 | R9: =INP!R80 -> 31 | S9: =INP!S80 -> 31 | ... W9: =INP!W80 -> 31
A13: X | B13: CAC PAYBACK
B15: S&M | F15: $k | L15: =-FIN_M!L20 -> 448.929 | M15: =-FIN_M!M20 -> 536.96297 | N15: =-FIN_M!N20 -> 630.36119 | O15: =-FIN_M!O20 -> 729.64708 | P15: =-FIN_M!P20 -> 835.38344 | Q15: =-FIN_M!Q20 -> 948.1757 | R15: =-FIN_M!R20 -> 1068.6753 | S15: =-FIN_M!S20 -> 1197.5835 | ... W15: =-FIN_M!W20 -> 1813.2974
B17: Addition MRR | F17: $k | L17: =ARR_M!L117 -> 98 | M17: =ARR_M!M117 -> 101.475 | N17: =ARR_M!N117 -> 105.15875 | O17: =ARR_M!O117 -> 109.06471 | P17: =ARR_M!P117 -> 113.20723 | Q17: =ARR_M!Q117 -> 117.60163 | R17: =ARR_M!R117 -> 122.26424 | S17: =ARR_M!S117 -> 127.21251 | ... W17: =ARR_M!W117 -> 150.25339
B18: Expansion MRR | F18: $k | L18: =ARR_M!L123 -> 0 | M18: =ARR_M!M123 -> 12.3359 | N18: =ARR_M!N123 -> 16.470913 | O18: =ARR_M!O123 -> 21.025646 | P18: =ARR_M!P123 -> 26.037235 | Q18: =ARR_M!Q123 -> 31.545868 | R18: =ARR_M!R123 -> 37.595024 | S18: =ARR_M!S123 -> 44.231733 | ... W18: =ARR_M!W123 -> 77.735401
B19: Gross Margin (%) | F19: % | L19: =FIN_M!L19 -> 0.82 | M19: =FIN_M!M19 -> 0.82 | N19: =FIN_M!N19 -> 0.82 | O19: =FIN_M!O19 -> 0.82 | P19: =FIN_M!P19 -> 0.82 | Q19: =FIN_M!Q19 -> 0.82 | R19: =FIN_M!R19 -> 0.82 | S19: =FIN_M!S19 -> 0.82 | ... W19: =FIN_M!W19 -> 0.82
B20: MARGIN CONTRIBUTION | F20: $k | L20: =SUM(L17:L18)*L19 -> 80.36 | M20: =SUM(M17:M18)*M19 -> 93.324938 | N20: =SUM(N17:N18)*N19 -> 99.736324 | O20: =SUM(O17:O18)*O19 -> 106.67409 | P20: =SUM(P17:P18)*P19 -> 114.18046 | Q20: =SUM(Q17:Q18)*Q19 -> 122.30095 | R20: =SUM(R17:R18)*R19 -> 131.0846 | S20: =SUM(S17:S18)*S19 -> 140.58428 | ... W20: =SUM(W17:W18)*W19 -> 186.95081
B22: S&M | F22: $k | L22: =L15 -> 448.929 | M22: =M15 -> 536.96297 | N22: =N15 -> 630.36119 | O22: =O15 -> 729.64708 | P22: =P15 -> 835.38344 | Q22: =Q15 -> 948.1757 | R22: =R15 -> 1068.6753 | S22: =S15 -> 1197.5835 | ... W22: =W15 -> 1813.2974
B23: Gross Margin | F23: $k | L23: =L20 -> 80.36 | M23: =M20 -> 93.324938 | N23: =N20 -> 99.736324 | O23: =O20 -> 106.67409 | P23: =P20 -> 114.18046 | Q23: =Q20 -> 122.30095 | R23: =R20 -> 131.0846 | S23: =S20 -> 140.58428 | ... W23: =W20 -> 186.95081
B24: CAC PAYBACK | F24: months | L24: =L22/L23 -> 5.5864734 | M24: =M22/M23 -> 5.7536922 | N24: =N22/N23 -> 6.320277 | O24: =O22/O23 -> 6.8399654 | P24: =P22/P23 -> 7.3163433 | Q24: =Q22/Q23 -> 7.7528076 | R24: =R22/R23 -> 8.1525621 | S24: =S22/S23 -> 8.5186162 | ... W24: =W22/W23 -> 9.699329
B26: Weighted Average Churn | F26: % | L26: =-ARR_M!L67/ARR_M!L55 -> 0.044666667 | M26: =-ARR_M!M67/ARR_M!M55 -> 0.043476147 | N26: =-ARR_M!N67/ARR_M!N55 -> 0.042485082 | O26: =-ARR_M!O67/ARR_M!O55 -> 0.041642964 | P26: =-ARR_M!P67/ARR_M!P55 -> 0.040915122 | Q26: =-ARR_M!Q67/ARR_M!Q55 -> 0.040276972 | R26: =-ARR_M!R67/ARR_M!R55 -> 0.039710591 | S26: =-ARR_M!S67/ARR_M!S55 -> 0.039202606 | ... W26: =-ARR_M!W67/ARR_M!W55 -> 0.037581941
B27: Weighted Average Customer Life | F27: months | L27: =1/L26 -> 22.38806 | M27: =1/M26 -> 23.001118 | N27: =1/N26 -> 23.537674 | O27: =1/O26 -> 24.013661 | P27: =1/P26 -> 24.440841 | Q27: =1/Q26 -> 24.828083 | R27: =1/R26 -> 25.182199 | S27: =1/S26 -> 25.508508 | ... W27: =1/W26 -> 26.608525
B28: CAC Payback % of Customer Life | F28: % | L28: =L24/L27 -> 0.24952914 | M28: =M24/M27 -> 0.25014837 | N28: =N24/N27 -> 0.26851749 | O28: =O24/O27 -> 0.28483643 | P28: =P24/P27 -> 0.29934908 | Q28: =Q24/Q27 -> 0.31225961 | R28: =R24/R27 -> 0.32374305 | S28: =S24/S27 -> 0.33395196 | ... W28: =W24/W27 -> 0.36451961
B29: Implied S&M Multiple on Customer Acquisition | F29: x | L29: =L27/L24 -> 4.0075479 | M29: =M27/M24 -> 3.9976275 | N29: =N27/N24 -> 3.7241522 | O29: =O27/O24 -> 3.5107869 | P29: =P27/P24 -> 3.3405815 | Q29: =Q27/Q24 -> 3.2024635 | R29: =R27/R24 -> 3.0888694 | S29: =S27/S24 -> 2.9944427 | ... W29: =W27/W24 -> 2.7433366
A31: X | B31: DOLLAR RETENTION
B33: GDR
B34: Opening MRR | F34: $k | L34: =ARR_M!L111 -> 415 | M34: =ARR_M!M111 -> 498.81 | N34: =ARR_M!N111 -> 596.62552 | O34: =ARR_M!O111 -> 700.40132 | P34: =ARR_M!P111 -> 810.71897 | Q34: =ARR_M!Q111 -> 928.20382 | R34: =ARR_M!R111 -> 1053.5286 | S34: =ARR_M!S111 -> 1187.417 | ... W34: =ARR_M!W111 -> 1825.1143
B35: Churn MRR | F35: $k | L35: =ARR_M!L129 -> -14.19 | M35: =ARR_M!M129 -> -15.995383 | N35: =ARR_M!N129 -> -17.853857 | O35: =ARR_M!O129 -> -19.772702 | P35: =ARR_M!P129 -> -21.759616 | Q35: =ARR_M!Q129 -> -23.822761 | R35: =ARR_M!R129 -> -25.970797 | S35: =ARR_M!S129 -> -28.212928 | ... W35: =ARR_M!W129 -> -38.328238
B36: OPENING - CHURN MRR | F36: $k | L36: =SUM(L34:L35) -> 400.81 | M36: =SUM(M34:M35) -> 482.81462 | N36: =SUM(N34:N35) -> 578.77166 | O36: =SUM(O34:O35) -> 680.62862 | P36: =SUM(P34:P35) -> 788.95936 | Q36: =SUM(Q34:Q35) -> 904.38106 | R36: =SUM(R34:R35) -> 1027.5578 | S36: =SUM(S34:S35) -> 1159.2041 | ... W36: =SUM(W34:W35) -> 1786.7861
B38: GDR (%) | F38: % | L38: =L36/L34 -> 0.96580723 | M38: =M36/M34 -> 0.96793291 | N38: =N36/N34 -> 0.97007527 | O38: =O36/O34 -> 0.97176947 | P38: =P36/P34 -> 0.9731601 | Q38: =Q36/Q34 -> 0.97433456 | R38: =R36/R34 -> 0.97534875 | S38: =S36/S34 -> 0.97624008 | ... W38: =W36/W34 -> 0.97899954
B40: NDR
B41: Opening MRR | F41: $k | L41: =L34 -> 415 | M41: =M34 -> 498.81 | N41: =N34 -> 596.62552 | O41: =O34 -> 700.40132 | P41: =P34 -> 810.71897 | Q41: =Q34 -> 928.20382 | R41: =R34 -> 1053.5286 | S41: =S34 -> 1187.417 | ... W41: =W34 -> 1825.1143
B42: Expansion MRR | F42: $k | L42: =ARR_M!L123 -> 0 | M42: =ARR_M!M123 -> 12.3359 | N42: =ARR_M!N123 -> 16.470913 | O42: =ARR_M!O123 -> 21.025646 | P42: =ARR_M!P123 -> 26.037235 | Q42: =ARR_M!Q123 -> 31.545868 | R42: =ARR_M!R123 -> 37.595024 | S42: =ARR_M!S123 -> 44.231733 | ... W42: =ARR_M!W123 -> 77.735401
B43: Churn MRR | F43: $k | L43: =L35 -> -14.19 | M43: =M35 -> -15.995383 | N43: =N35 -> -17.853857 | O43: =O35 -> -19.772702 | P43: =P35 -> -21.759616 | Q43: =Q35 -> -23.822761 | R43: =R35 -> -25.970797 | S43: =S35 -> -28.212928 | ... W43: =W35 -> -38.328238
B44: NET MRR (PRE-ADDITIONS) | F44: $k | L44: =SUM(L41:L43) -> 400.81 | M44: =SUM(M41:M43) -> 495.15052 | N44: =SUM(N41:N43) -> 595.24257 | O44: =SUM(O41:O43) -> 701.65427 | P44: =SUM(P41:P43) -> 814.99659 | Q44: =SUM(Q41:Q43) -> 935.92693 | R44: =SUM(R41:R43) -> 1065.1528 | S44: =SUM(S41:S43) -> 1203.4358 | ... W44: =SUM(W41:W43) -> 1864.5215
B46: NDR (%) | F46: % | L46: =L44/L41 -> 0.96580723 | M46: =M44/M41 -> 0.99266357 | N46: =N44/N41 -> 0.99768206 | O46: =O44/O41 -> 1.0017889 | P46: =P44/P41 -> 1.0052763 | Q46: =Q44/Q41 -> 1.0083205 | R46: =R44/R41 -> 1.0110336 | S46: =S44/S41 -> 1.0134905 | ... W46: =W44/W41 -> 1.0215916
A48: X | B48: END OF SHEET
B55: END OF SHEET

Sheet Q>
B6: Project Oracle
B7: Quarterly Rollup
B51: END OF SHEET

Sheet ROLL_Q
B3: Project Oracle
B4: Annual Planning Model | Quarterly Rollup Metrics
B6: Period End | L6: =INP!L83 -> 46112 | M6: =INP!M83 -> 46203 | N6: =INP!N83 -> 46295 | O6: =INP!O83 -> 46387
B7: Period Start | L7: =INP!L84 -> 46023 | M7: =INP!M84 -> 46113 | N7: =INP!N84 -> 46204 | O7: =INP!O84 -> 46296
B8: Calendar Year | L8: =INP!L85 -> 2026 | M8: =INP!M85 -> 2026 | N8: =INP!N85 -> 2026 | O8: =INP!O85 -> 2026
B9: Days in Period | F9: Units | H9: Input I | I9: Input II | J9: Input III | K9: TOTAL | L9: =INP!L86 -> 90 | M9: =INP!M86 -> 91 | N9: =INP!N86 -> 92 | O9: =INP!O86 -> 92
A13: X | B13: PROFIT & LOSS
B15: MRR | F15: $k | L15: =SUMIFS(FIN_M!$L15:$W15,FIN_M!$L$6:$W$6,">"&L$7,FIN_M!$L$6:$W$6,"<="&L$6) -> 1795.8368 | M15: =SUMIFS(FIN_M!$L15:$W15,FIN_M!$L$6:$W$6,">"&M$7,FIN_M!$L$6:$W$6,"<="&M$6) -> 2792.4514 | N15: =SUMIFS(FIN_M!$L15:$W15,FIN_M!$L$6:$W$6,">"&N$7,FIN_M!$L$6:$W$6,"<="&N$6) -> 4002.1266 | O15: =SUMIFS(FIN_M!$L15:$W15,FIN_M!$L$6:$W$6,">"&O$7,FIN_M!$L$6:$W$6,"<="&O$6) -> 5488.4483
B16: % growth | F16: % | M16: =M15/L15-1 -> 0.55495827 | N16: =N15/M15-1 -> 0.43319476 | O16: =O15/N15-1 -> 0.37138296
B17: Less: COGS | F17: $k | L17: =SUMIFS(FIN_M!$L17:$W17,FIN_M!$L$6:$W$6,">"&L$7,FIN_M!$L$6:$W$6,"<="&L$6) -> -323.25063 | M17: =SUMIFS(FIN_M!$L17:$W17,FIN_M!$L$6:$W$6,">"&M$7,FIN_M!$L$6:$W$6,"<="&M$6) -> -502.64124 | N17: =SUMIFS(FIN_M!$L17:$W17,FIN_M!$L$6:$W$6,">"&N$7,FIN_M!$L$6:$W$6,"<="&N$6) -> -720.38279 | O17: =SUMIFS(FIN_M!$L17:$W17,FIN_M!$L$6:$W$6,">"&O$7,FIN_M!$L$6:$W$6,"<="&O$6) -> -987.92069
B18: Gross Profit | F18: $k | L18: =SUM(L15,L17) -> 1472.5862 | M18: =SUM(M15,M17) -> 2289.8101 | N18: =SUM(N15,N17) -> 3281.7438 | O18: =SUM(O15,O17) -> 4500.5276
B19: % margin | F19: % | L19: =L18/L15 -> 0.82 | M19: =M18/M15 -> 0.82 | N19: =N18/N15 -> 0.82 | O19: =O18/O15 -> 0.82
B20: Less: Sales & Marketing | F20: $k | L20: =SUMIFS(FIN_M!$L20:$W20,FIN_M!$L$6:$W$6,">"&L$7,FIN_M!$L$6:$W$6,"<="&L$6) -> -1616.2532 | M20: =SUMIFS(FIN_M!$L20:$W20,FIN_M!$L$6:$W$6,">"&M$7,FIN_M!$L$6:$W$6,"<="&M$6) -> -2513.2062 | N20: =SUMIFS(FIN_M!$L20:$W20,FIN_M!$L$6:$W$6,">"&N$7,FIN_M!$L$6:$W$6,"<="&N$6) -> -3601.914 | O20: =SUMIFS(FIN_M!$L20:$W20,FIN_M!$L$6:$W$6,">"&O$7,FIN_M!$L$6:$W$6,"<="&O$6) -> -4939.6034
B21: Less: Product & Engineering | F21: $k | L21: =SUMIFS(FIN_M!$L21:$W21,FIN_M!$L$6:$W$6,">"&L$7,FIN_M!$L$6:$W$6,"<="&L$6) -> -718.33474 | M21: =SUMIFS(FIN_M!$L21:$W21,FIN_M!$L$6:$W$6,">"&M$7,FIN_M!$L$6:$W$6,"<="&M$6) -> -1116.9805 | N21: =SUMIFS(FIN_M!$L21:$W21,FIN_M!$L$6:$W$6,">"&N$7,FIN_M!$L$6:$W$6,"<="&N$6) -> -1600.8507 | O21: =SUMIFS(FIN_M!$L21:$W21,FIN_M!$L$6:$W$6,">"&O$7,FIN_M!$L$6:$W$6,"<="&O$6) -> -2195.3793
B22: Less: G&A | F22: $k | L22: =SUMIFS(FIN_M!$L22:$W22,FIN_M!$L$6:$W$6,">"&L$7,FIN_M!$L$6:$W$6,"<="&L$6) -> -179.58368 | M22: =SUMIFS(FIN_M!$L22:$W22,FIN_M!$L$6:$W$6,">"&M$7,FIN_M!$L$6:$W$6,"<="&M$6) -> -279.24514 | N22: =SUMIFS(FIN_M!$L22:$W22,FIN_M!$L$6:$W$6,">"&N$7,FIN_M!$L$6:$W$6,"<="&N$6) -> -400.21266 | O22: =SUMIFS(FIN_M!$L22:$W22,FIN_M!$L$6:$W$6,">"&O$7,FIN_M!$L$6:$W$6,"<="&O$6) -> -548.84483
B23: EBITDA | F23: $k | L23: =SUM(L20:L22,L18) -> -1041.5854 | M23: =SUM(M20:M22,M18) -> -1619.6218 | N23: =SUM(N20:N22,N18) -> -2321.2334 | O23: =SUM(O20:O22,O18) -> -3183.3
B24: % margin | F24: % | L24: =L23/L15 -> -0.58 | M24: =M23/M15 -> -0.58 | N24: =N23/N15 -> -0.58 | O24: =O23/O15 -> -0.58
B25: Less: Depreciation | F25: $k | L25: =SUMIFS(FIN_M!$L25:$W25,FIN_M!$L$6:$W$6,">"&L$7,FIN_M!$L$6:$W$6,"<="&L$6) -> -6.0500458 | M25: =SUMIFS(FIN_M!$L25:$W25,FIN_M!$L$6:$W$6,">"&M$7,FIN_M!$L$6:$W$6,"<="&M$6) -> -10.127558 | N25: =SUMIFS(FIN_M!$L25:$W25,FIN_M!$L$6:$W$6,">"&N$7,FIN_M!$L$6:$W$6,"<="&N$6) -> -16.095819 | O25: =SUMIFS(FIN_M!$L25:$W25,FIN_M!$L$6:$W$6,">"&O$7,FIN_M!$L$6:$W$6,"<="&O$6) -> -24.378847
B26: EBIT | F26: $k | L26: =SUM(L23,L25) -> -1047.6354 | M26: =SUM(M23,M25) -> -1629.7493 | N26: =SUM(N23,N25) -> -2337.3293 | O26: =SUM(O23,O25) -> -3207.6788
B27: Less: Interest Expense | F27: $k
B28: EBT | F28: $k | L28: =SUM(L26:L27) -> -1047.6354 | M28: =SUM(M26:M27) -> -1629.7493 | N28: =SUM(N26:N27) -> -2337.3293 | O28: =SUM(O26:O27) -> -3207.6788
B29: Less: Tax Expense | F29: $k | H29: =INP!$H$35 -> 0.25 | L29: =-MAX(0,L28)*$H29 -> 0 | M29: =-MAX(0,M28)*$H29 -> 0 | N29: =-MAX(0,N28)*$H29 -> 0 | O29: =-MAX(0,O28)*$H29 -> 0
B30: PAT | F30: $k | L30: =SUM(L28:L29) -> -1047.6354 | M30: =SUM(M28:M29) -> -1629.7493 | N30: =SUM(N28:N29) -> -2337.3293 | O30: =SUM(O28:O29) -> -3207.6788
A32: X | B32: CASH FLOW STATEMENT
B34: EBITDA | F34: $k | L34: =L23 -> -1041.5854 | M34: =M23 -> -1619.6218 | N34: =N23 -> -2321.2334 | O34: =O23 -> -3183.3
B35: Less: Capex | F35: $k | L35: =SUMIFS(FIN_M!$L35:$W35,FIN_M!$L$6:$W$6,">"&L$7,FIN_M!$L$6:$W$6,"<="&L$6) -> -35.916737 | M35: =SUMIFS(FIN_M!$L35:$W35,FIN_M!$L$6:$W$6,">"&M$7,FIN_M!$L$6:$W$6,"<="&M$6) -> -55.849027 | N35: =SUMIFS(FIN_M!$L35:$W35,FIN_M!$L$6:$W$6,">"&N$7,FIN_M!$L$6:$W$6,"<="&N$6) -> -80.042533 | O35: =SUMIFS(FIN_M!$L35:$W35,FIN_M!$L$6:$W$6,">"&O$7,FIN_M!$L$6:$W$6,"<="&O$6) -> -109.76897
B36: Less: Change in Net Working Capital | F36: $k | L36: =SUMIFS(FIN_M!$L36:$W36,FIN_M!$L$6:$W$6,">"&L$7,FIN_M!$L$6:$W$6,"<="&L$6) -> -35.186464 | M36: =SUMIFS(FIN_M!$L36:$W36,FIN_M!$L$6:$W$6,">"&M$7,FIN_M!$L$6:$W$6,"<="&M$6) -> -43.536234 | N36: =SUMIFS(FIN_M!$L36:$W36,FIN_M!$L$6:$W$6,">"&N$7,FIN_M!$L$6:$W$6,"<="&N$6) -> -53.079377 | O36: =SUMIFS(FIN_M!$L36:$W36,FIN_M!$L$6:$W$6,">"&O$7,FIN_M!$L$6:$W$6,"<="&O$6) -> -65.430445
B37: Less: Cash Taxes Paid | F37: $k | L37: =L29 -> 0 | M37: =M29 -> 0 | N37: =N29 -> 0 | O37: =O29 -> 0
B38: CASH (BURN) / ACCRUAL | F38: $k | L38: =SUM(L34:L37) -> -1112.6886 | M38: =SUM(M34:M37) -> -1719.007 | N38: =SUM(N34:N37) -> -2454.3554 | O38: =SUM(O34:O37) -> -3358.4994
B40: Cash and Cash Equivalents
B41: Opening | F41: $k | L41: =K44 -> 0 | M41: =L44 -> 28887.311 | N41: =M44 -> 27168.304 | O41: =N44 -> 24713.949
B42: Add: Rollforward of Historical Balance | F42: $k | L42: =SUMIFS(FIN_M!$L42:$W42,FIN_M!$L$6:$W$6,">"&L$7,FIN_M!$L$6:$W$6,"<="&L$6) -> 30000 | M42: =SUMIFS(FIN_M!$L42:$W42,FIN_M!$L$6:$W$6,">"&M$7,FIN_M!$L$6:$W$6,"<="&M$6) -> 0 | N42: =SUMIFS(FIN_M!$L42:$W42,FIN_M!$L$6:$W$6,">"&N$7,FIN_M!$L$6:$W$6,"<="&N$6) -> 0 | O42: =SUMIFS(FIN_M!$L42:$W42,FIN_M!$L$6:$W$6,">"&O$7,FIN_M!$L$6:$W$6,"<="&O$6) -> 0
B43: Add / Less: Cash (Burn) / Accrual | F43: $k | L43: =L38 -> -1112.6886 | M43: =M38 -> -1719.007 | N43: =N38 -> -2454.3554 | O43: =O38 -> -3358.4994
B44: CLOSING | F44: $k | L44: =SUM(L41:L43) -> 28887.311 | M44: =SUM(M41:M43) -> 27168.304 | N44: =SUM(N41:N43) -> 24713.949 | O44: =SUM(O41:O43) -> 21355.45
A46: X | B46: BALANCE SHEET
B48: Cash and Cash Equivalents | F48: $k | L48: =SUMIFS(FIN_M!$L48:$W48,FIN_M!$L$6:$W$6,L$6) -> 28887.311 | M48: =SUMIFS(FIN_M!$L48:$W48,FIN_M!$L$6:$W$6,M$6) -> 27168.304 | N48: =SUMIFS(FIN_M!$L48:$W48,FIN_M!$L$6:$W$6,N$6) -> 24713.949 | O48: =SUMIFS(FIN_M!$L48:$W48,FIN_M!$L$6:$W$6,O$6) -> 21355.45
B49: Fixed Assets | F49: $k | L49: =SUMIFS(FIN_M!$L49:$W49,FIN_M!$L$6:$W$6,L$6) -> 79.866691 | M49: =SUMIFS(FIN_M!$L49:$W49,FIN_M!$L$6:$W$6,M$6) -> 125.58816 | N49: =SUMIFS(FIN_M!$L49:$W49,FIN_M!$L$6:$W$6,N$6) -> 189.53487 | O49: =SUMIFS(FIN_M!$L49:$W49,FIN_M!$L$6:$W$6,O$6) -> 274.92499
B50: Net Working Capital | F50: $k | L50: =SUMIFS(FIN_M!$L50:$W50,FIN_M!$L$6:$W$6,L$6) -> 86.350848 | M50: =SUMIFS(FIN_M!$L50:$W50,FIN_M!$L$6:$W$6,M$6) -> 129.88708 | N50: =SUMIFS(FIN_M!$L50:$W50,FIN_M!$L$6:$W$6,N$6) -> 182.96646 | O50: =SUMIFS(FIN_M!$L50:$W50,FIN_M!$L$6:$W$6,O$6) -> 248.3969
B51: Net Assets | F51: $k | L51: =SUM(L48:L50) -> 29053.529 | M51: =SUM(M48:M50) -> 27423.78 | N51: =SUM(N48:N50) -> 25086.45 | O51: =SUM(O48:O50) -> 21878.772
B53: Accumulated Losses | F53: $k | L53: =SUMIFS(FIN_M!$L53:$W53,FIN_M!$L$6:$W$6,L$6) -> -6946.471 | M53: =SUMIFS(FIN_M!$L53:$W53,FIN_M!$L$6:$W$6,M$6) -> -8576.2204 | N53: =SUMIFS(FIN_M!$L53:$W53,FIN_M!$L$6:$W$6,N$6) -> -10913.55 | O53: =SUMIFS(FIN_M!$L53:$W53,FIN_M!$L$6:$W$6,O$6) -> -14121.228
B54: Contributed Capital | F54: $k | H54: =INP!H45 -> 36000 | L54: =SUMIFS(FIN_M!$L54:$W54,FIN_M!$L$6:$W$6,L$6) -> 36000 | M54: =SUMIFS(FIN_M!$L54:$W54,FIN_M!$L$6:$W$6,M$6) -> 36000 | N54: =SUMIFS(FIN_M!$L54:$W54,FIN_M!$L$6:$W$6,N$6) -> 36000 | O54: =SUMIFS(FIN_M!$L54:$W54,FIN_M!$L$6:$W$6,O$6) -> 36000
B55: TOTAL EQUITY | F55: $k | L55: =SUM(L53:L54) -> 29053.529 | M55: =SUM(M53:M54) -> 27423.78 | N55: =SUM(N53:N54) -> 25086.45 | O55: =SUM(O53:O54) -> 21878.772
B56: Check | F56: $k | L56: =L55-L51 -> 0 | M56: =M55-M51 -> 0 | N56: =N55-N51 -> 0 | O56: =O55-O51 -> 0
A58: X | B58: OPERATING METRICS
B60: Customer Volumes | F60: $k | L60: =SUMIFS(ARR_M!$L19:$W19,ARR_M!$L$6:$W$6,L$6) -> 769.22484 | M60: =SUMIFS(ARR_M!$L19:$W19,ARR_M!$L$6:$W$6,M$6) -> 923.36792 | N60: =SUMIFS(ARR_M!$L19:$W19,ARR_M!$L$6:$W$6,N$6) -> 1064.1435 | O60: =SUMIFS(ARR_M!$L19:$W19,ARR_M!$L$6:$W$6,O$6) -> 1193.0442
B61: Average Seats / Customer | F61: # | L61: =SUMIFS(ARR_M!$L25:$W25,ARR_M!$L$6:$W$6,L$6) -> 21.162412 | M61: =SUMIFS(ARR_M!$L25:$W25,ARR_M!$L$6:$W$6,M$6) -> 27.389764 | N61: =SUMIFS(ARR_M!$L25:$W25,ARR_M!$L$6:$W$6,N$6) -> 34.474239 | O61: =SUMIFS(ARR_M!$L25:$W25,ARR_M!$L$6:$W$6,O$6) -> 42.844663
B62: Average ARR / Customer | F62: $k | L62: =SUMIFS(ARR_M!$L31:$W31,ARR_M!$L$6:$W$6,L$6) -> 10.926345 | M62: =SUMIFS(ARR_M!$L31:$W31,ARR_M!$L$6:$W$6,M$6) -> 13.691555 | N62: =SUMIFS(ARR_M!$L31:$W31,ARR_M!$L$6:$W$6,N$6) -> 16.735276 | O62: =SUMIFS(ARR_M!$L31:$W31,ARR_M!$L$6:$W$6,O$6) -> 20.265216
B63: ARR | F63: $k | L63: =SUMIFS(ARR_M!$L43:$W43,ARR_M!$L$6:$W$6,L$6) -> 8404.8159 | M63: =SUMIFS(ARR_M!$L43:$W43,ARR_M!$L$6:$W$6,M$6) -> 12642.343 | N63: =SUMIFS(ARR_M!$L43:$W43,ARR_M!$L$6:$W$6,N$6) -> 17808.735 | O63: =SUMIFS(ARR_M!$L43:$W43,ARR_M!$L$6:$W$6,O$6) -> 24177.299
A65: X | B65: SAAS METRICS
B67: CAC Payback | F67: months | L67: =SUMIFS(SAAS_M!$L24:$W24,SAAS_M!$L$6:$W$6,L$6) -> 6.320277 | M67: =SUMIFS(SAAS_M!$L24:$W24,SAAS_M!$L$6:$W$6,M$6) -> 7.7528076 | N67: =SUMIFS(SAAS_M!$L24:$W24,SAAS_M!$L$6:$W$6,N$6) -> 8.8537861 | O67: =SUMIFS(SAAS_M!$L24:$W24,SAAS_M!$L$6:$W$6,O$6) -> 9.699329
B68: =SAAS_M!B28 -> CAC Payback % of Customer Life | F68: % | L68: =SUMIFS(SAAS_M!$L28:$W28,SAAS_M!$L$6:$W$6,L$6) -> 0.26851749 | M68: =SUMIFS(SAAS_M!$L28:$W28,SAAS_M!$L$6:$W$6,M$6) -> 0.31225961 | N68: =SUMIFS(SAAS_M!$L28:$W28,SAAS_M!$L$6:$W$6,N$6) -> 0.34302081 | O68: =SUMIFS(SAAS_M!$L28:$W28,SAAS_M!$L$6:$W$6,O$6) -> 0.36451961
B69: =SAAS_M!B29 -> Implied S&M Multiple on Customer Acquisition | F69: x | L69: =SUMIFS(SAAS_M!$L29:$W29,SAAS_M!$L$6:$W$6,L$6) -> 3.7241522 | M69: =SUMIFS(SAAS_M!$L29:$W29,SAAS_M!$L$6:$W$6,M$6) -> 3.2024635 | N69: =SUMIFS(SAAS_M!$L29:$W29,SAAS_M!$L$6:$W$6,N$6) -> 2.915275 | O69: =SUMIFS(SAAS_M!$L29:$W29,SAAS_M!$L$6:$W$6,O$6) -> 2.7433366
B70: =SAAS_M!B38 -> GDR (%) | F70: % | L70: =SUMIFS(SAAS_M!$L38:$W38,SAAS_M!$L$6:$W$6,L$6) -> 0.97007527 | M70: =SUMIFS(SAAS_M!$L38:$W38,SAAS_M!$L$6:$W$6,M$6) -> 0.97433456 | N70: =SUMIFS(SAAS_M!$L38:$W38,SAAS_M!$L$6:$W$6,N$6) -> 0.97703454 | O70: =SUMIFS(SAAS_M!$L38:$W38,SAAS_M!$L$6:$W$6,O$6) -> 0.97899954
B71: =SAAS_M!B46 -> NDR (%) | F71: % | L71: =SUMIFS(SAAS_M!$L46:$W46,SAAS_M!$L$6:$W$6,L$6) -> 0.99768206 | M71: =SUMIFS(SAAS_M!$L46:$W46,SAAS_M!$L$6:$W$6,M$6) -> 1.0083205 | N71: =SUMIFS(SAAS_M!$L46:$W46,SAAS_M!$L$6:$W$6,N$6) -> 1.0157426 | O71: =SUMIFS(SAAS_M!$L46:$W46,SAAS_M!$L$6:$W$6,O$6) -> 1.0215916
A73: X | B73: END OF SHEET
